Workbook
Name Advocacy: Sheet1!$F$2:$F$4
Name all_outcome_indicator: indicators!$O$2:$O$27
Name all_output_indicator: indicators!$P$2:$P$100
Name Child_Protection_Activity: '3. Sector_Child Protection'!$D$56:$D$85
Name Child_Protection_Output: '3. Sector_Child Protection'!$D$38:$D$52
Name Child_Sponsorship: Sheet1!$A$2:$A$4
Name climate_outcome_indicator: indicators!$I$2:$I$3
Name climate_output_indicator: indicators!$J$2:$J$10
Name community_output_indicator: indicators!$Q$2:$Q$13
Name Core_Alliance: Sheet1!$A$21:$A$28
Name Design_Type: Sheet1!$C$21:$C$23
Name Economic_Empowerment_Activity: '3. Sector_Economic Empowerment'!$D$57:$D$86
Name Economic_Empowerment_Output: '3. Sector_Economic Empowerment'!$D$39:$D$53
Name economy_outcome_indicator: indicators!$G$2:$G$7
Name economy_output_indicator: indicators!$H$2:$H$20
Name Education: Sheet1!$B$2:$B$7
Name Education_Activity: '3. Sector_Education'!$D$59:$D$88
Name education_outcome_indicator: indicators!$C$2:$C$8
Name Education_Output: '3. Sector_Education'!$D$41:$D$55
Name education_output_indicator: indicators!$D$2:$D$26
Name Environment: Sheet1!$G$2:$G$6
Name Health_Avtivity: '3. Sector_Health & Well-being'!$D$57:$D$86
Name health_outcome_indicator: indicators!$E$2:$E$4
Name health_output_indicator: indicators!$F$2:$F$39
Name Health_WellBeing: Table12[_03000_Health]
Name Health_WellBeing_Activity: '3. Sector_Health & Well-being'!$D$57:$D$86
Name Health_WellBeing_Output: '3. Sector_Health & Well-being'!$D$39:$D$53
Name Humanitarian_Assistance: Sheet1!$H$2:$H$8
Name humanitarian_outcome_indicator: indicators!$K$2:$K$2
Name humanitarian_output_indicator: indicators!$L$2:$L$14
Name Income_Generation: Sheet1!$D$2:$D$6
Name ITT_ChildProtection_OC_A: '3. Sector_Child Protection'!$A$32:$A$36
Name ITT_ChildProtection_OC_B: '3. Sector_Child Protection'!$B$32:$B$36
Name ITT_ChildProtection_OC_E: '3. Sector_Child Protection'!$E$32:$E$36
Name ITT_ChildProtection_OC_G: '3. Sector_Child Protection'!$G$32:$G$36
Name ITT_ChildProtection_OC_J: '3. Sector_Child Protection'!$J$32:$J$36
Name ITT_ChildProtection_OC_K: '3. Sector_Child Protection'!$K$32:$K$36
Name ITT_ChildProtection_OP_A: '3. Sector_Child Protection'!$A$38:$A$52
Name ITT_ChildProtection_OP_B: '3. Sector_Child Protection'!$B$38:$B$52
Name ITT_ChildProtection_OP_E: '3. Sector_Child Protection'!$E$38:$E$52
Name ITT_ChildProtection_OP_G: '3. Sector_Child Protection'!$G$38:$G$52
Name ITT_ChildProtection_OP_J: '3. Sector_Child Protection'!$J$38:$J$52
Name ITT_ChildProtection_OP_K: '3. Sector_Child Protection'!$K$38:$K$52
Name ITT_EconomicEmpowerment_OC_A: '3. Sector_Economic Empowerment'!$A$33:$A$37
Name ITT_EconomicEmpowerment_OC_B: '3. Sector_Economic Empowerment'!$B$33:$B$37
Name ITT_EconomicEmpowerment_OC_E: '3. Sector_Economic Empowerment'!$E$33:$E$37
Name ITT_EconomicEmpowerment_OC_G: '3. Sector_Economic Empowerment'!$G$33:$G$37
Name ITT_EconomicEmpowerment_OC_J: '3. Sector_Economic Empowerment'!$J$33:$J$37
Name ITT_EconomicEmpowerment_OC_K: '3. Sector_Economic Empowerment'!$K$33:$K$37
Name ITT_EconomicEmpowerment_OP_A: '3. Sector_Economic Empowerment'!$A$39:$A$53
Name ITT_EconomicEmpowerment_OP_B: '3. Sector_Economic Empowerment'!$B$39:$B$53
Name ITT_EconomicEmpowerment_OP_E: '3. Sector_Economic Empowerment'!$E$39:$E$53
Name ITT_EconomicEmpowerment_OP_G: '3. Sector_Economic Empowerment'!$G$39:$G$53
Name ITT_EconomicEmpowerment_OP_J: '3. Sector_Economic Empowerment'!$J$39:$J$53
Name ITT_EconomicEmpowerment_OP_K: '3. Sector_Economic Empowerment'!$K$39:$K$53
Name ITT_Education_OC_A: '3. Sector_Education'!$A$35:$A$39
Name ITT_Education_OC_B: '3. Sector_Education'!$B$35:$B$39
Name ITT_Education_OC_E: '3. Sector_Education'!$E$35:$E$39
Name ITT_Education_OC_G: '3. Sector_Education'!$G$35:$G$39
Name ITT_Education_OC_J: '3. Sector_Education'!$J$35:$J$39

Sheet Cover
B3: Project Proposal Form
B7: Country Name
B8: Project Name
B9: Project Type
B10: Design Type
B11: Prepared by | E11: (Name) | H11: (Position)
B12: Reviewed by | E12: (Name) | H12: (Position)
B13: Authorized by | E13: (Name) | H13: (Position)
B14: Submission Date | E14: MM-DD-YY
B17: Table of Contents
C19: 1. Project Overview
C21: 2. Community Assessment Result
D22: Basic Information of the Community
D23: Needs Assessment Result *Commencement Only
D24: Contextual Analysis
C26: 3. Sectoral Approach
D27: Project Overview
D28: Situation Analysis
D29: Project Scope
D30: Project Implementation Plan
C32: 4. Child Sponsorship Management (If applicable)
D33: Program Area Overview
D34: Sponsorship Program Operation Plan
D35: Risk Management Plan
C37: 5. Project Management Plan
D38: Network Management Plan
D39: Budget Management Plan
D40: Human Resource Management Plan
C42: (Annex) Indicator Tracking Tool

Sheet 1. Project Overview
A1: 1. Project Overview
A2: Category | B2: Description
A3: Target Area | B3: Target Area Name
B4: GPS coordinates of target area
B5: Distance from the Head Office
B6: Please put the map of the Target Area.
A7: Project Period (MM.YYYY~MM.YYYY) | D7: ~
A8: Project Budget (USD)
A9: Direct Participants | B9: Children | C9: Boy
C10: Girl
B11: Adults | C11: Male
C12: Female
A13: Indirect Participants | B13: Male
B14: Female
A15: Expected Outcome and Output | B15: Please share the overall logical framework of the project.

Sheet 2. Community Assessment Result
A1: 2. Community Assessment Result
A2: General Information of the Community
A3: Total Population | E3: =A5+B5+C5+E5+F5+G5+H5 -> 0
A4: Age 0-5 (Under 5) | B4: Ages 6-12 (Primary) | C4: Ages 13-18 (Secondary) | E4: Ages 19-24 (Youth) | F4: Ages 25-39 | G4: Ages 40-59 | H4: Ages Over 60 (Elderly)
A6: Number of Households | B6: Average Number of People per Household | C6: Distance to Nearest Market | E6: Average Household Income (USD) | F6: Race(s) / Tribe(s) / Ethnic Group(s) | G6: Prevailing Religion(s) | H6: Native Language(s)
A8: Need Assessment Result
A9: PAP Methodology | B9: Target Group / Respondents | C9: ► | D9: Assessment Findings
D10: Provide a concise summary of the key findings from the PAP. - Major issues - Community needs - Existing resources - Any notable patterns or gaps identified during the assessment
A15: Contextual Analysis
A16: Category | B16: Status | F16: Consideration
A17: Political Context | B17: Please provide information about the community situations based on the following categories: - Government structure - Political conflicts - Legal system - Others | F17: Please provide an overview of the relevant contextual factors that GN should consider when implementing the project.
A18: Social Context | B18: - Decision-making structure - Dominant religion (faith group) and their influence - Most vulnerable group - Others
A19: Economic Context | B19: - Major income source of households - Income level of the community people - Others (e.g., technology, etc.)
A20: Environmental Context | B20: - Climate change issues in the community - Most frequent natural disasters - Natural resources - Others (e.g., technology, etc.)

Sheet 3. Sector_Child Protection
A1: 3. Sectoral Approach_Child Protection
A2: Target Participants | C2: Children (Boy) | I2: Adults (Male)
C3: Children (Girl) | I3: Adults (Female)
A4: Key Statistics
A5: Birth Registration Rate | C5: Child Marriage Rate | E5: Median Age at First Marriage | F5: Adolescent Birth Rate | G5: Child Labor Rate | I5: Out of School Children Rate | K5: Prevalence of violence against child | M5: Existence of child abuse reporting and response system | O5: Remarks
A7: Data Source | C7: Please indicate the source of the statistics entered above, including the name of the source (e.g., national census, DHS/MICS, government or ministry report, GN community assessment), the reference year, and the geographic level of the data (national, provincial, district, or project community). Where figures come from different sources, please specify the source for each indicator.
A8: Situation Analysis
A9: Child Protection-related Status in the Community | C9: Please describe child protection related situations in the community and consider how they relate with the following sections. - Child protection-related situations in the community that requires GN's intervention - Contextual properties of the community and cross-cutting issues that GN should consider when implementing a sectoral approach.
A10: Problem Tree
A11: Effect | C11: Please put the image of the problem tree. (Insert > Pictures > This Device)
A12: Main Problem
A13: Causes
A14: Photos | C14: Please include photos that clearly show the current problem situation in the community.
A15: Case Story | C15: Please share a case story that illustrates the problem situation well.
A16: Objective Tree
A17: Ends | C17: Please put the image of objective tree. (Insert > Pictures > This Device)
A18: Objectives
A19: Means
A20: Alignment with Country MLTSP
A21: Related Programmatic Direction | C21: Strategic Objective
C23: Expected Outcome | I23: Related Outcome Indicator
A27: Project Result and M&E Framework
A28: Cross-cutting Issue | K28: Remarks
A29: Log Frame | E29: M&E Framework
A30: Objective | E30: Indicator | G30: Definition | I30: Unit | J30: Baseline | K30: Target | L30: Means of Verification | O30: Frequency of Data Collection
A31: Outcome
A32: 1
A33: 2
A34: 3
A35: 4
A36: 5
A37: Output
A38: 1.1 | D38: =A38&" "&B38 -> 1.1
A39: 1.2 | D39: =A39&" "&B39 -> 1.2
A40: 1.3 | D40: =A40&" "&B40 -> 1.3
A41: 2.1 | D41: =A41&" "&B41 -> 2.1
A42: 2.2 | D42: =A42&" "&B42 -> 2.2
A43: 2.3 | D43: =A43&" "&B43 -> 2.3
A44: 3.1 | D44: =A44&" "&B44 -> 3.1
A45: 3.2 | D45: =A45&" "&B45 -> 3.2
A46: 3.3 | D46: =A46&" "&B46 -> 3.3
A47: 4.1 | D47: =A47&" "&B47 -> 4.1
A48: 4.2 | D48: =A48&" "&B48 -> 4.2
A49: 4.3 | D49: =A49&" "&B49 -> 4.3
... A52: 5.3 | D52: =A52&" "&B52 -> 5.3
A53: Action Plan
A54: Major Activities | E54: Timeline | M54: Remarks
E55: Year 1 | F55: Year 2 | G55: Year 3 | I55: Year 4 | K55: Year 5
A56: 1.1.1 | D56: =A56&" "&B56 -> 1.1.1
A57: 1.1.2 | D57: =A57&" "&B57 -> 1.1.2
A58: 1.2.1 | D58: =A58&" "&B58 -> 1.2.1
A59: 1.2.2 | D59: =A59&" "&B59 -> 1.2.2
A60: 1.3.1 | D60: =A60&" "&B60 -> 1.3.1
A61: 1.3.2 | D61: =A61&" "&B61 -> 1.3.2
A62: 2.1.1 | D62: =A62&" "&B62 -> 2.1.1
A63: 2.1.2 | D63: =A63&" "&B63 -> 2.1.2
A64: 2.2.1 | D64: =A64&" "&B64 -> 2.2.1
A65: 2.2.2 | D65: =A65&" "&B65 -> 2.2.2
A66: 2.3.1 | D66: =A66&" "&B66 -> 2.3.1
A67: 2.3.2 | D67: =A67&" "&B67 -> 2.3.2
... A85: 5.3.2 | D85: =A85&" "&B85 -> 5.3.2
A86: Budget Plan
A87: Output | C87: Major Activities | E87: Basis of Calculation | G87: Unit | H87: Unit Cost ($) | I87: Quantity | J87: Total | K87: Y1 | L87: Y2 | M87: Y3 | N87: Y4 | O87: Y5 | P87: Total
J88: =H88*I88 -> 0 | P88: =SUM(K88:O88) -> 0
J89: =H89*I89 -> 0 | P89: =SUM(K89:O89) -> 0
J90: =H90*I90 -> 0 | P90: =SUM(K90:O90) -> 0
J91: =H91*I91 -> 0 | P91: =SUM(K91:O91) -> 0
J92: =H92*I92 -> 0 | P92: =SUM(K92:O92) -> 0
J93: =H93*I93 -> 0 | P93: =SUM(K93:O93) -> 0
J94: =H94*I94 -> 0 | P94: =SUM(K94:O94) -> 0
J95: =H95*I95 -> 0 | P95: =SUM(K95:O95) -> 0
J96: =H96*I96 -> 0 | P96: =SUM(K96:O96) -> 0
J97: =H97*I97 -> 0 | P97: =SUM(K97:O97) -> 0
J98: =H98*I98 -> 0 | P98: =SUM(K98:O98) -> 0
J99: =H99*I99 -> 0 | P99: =SUM(K99:O99) -> 0
... J109: =H109*I109 -> 0 | P109: =SUM(K109:O109) -> 0
A110: Child Protection Total | J110: =SUM(J88:J109) -> 0 | K110: =SUM(K88:K109) -> 0 | L110: =SUM(L88:L109) -> 0 | M110: =SUM(M88:M109) -> 0 | N110: =SUM(N88:N109) -> 0 | O110: =SUM(O88:O109) -> 0 | P110: =SUM(K110:O110) -> 0

Sheet 3. Sector_Education
A1: 3. Sectoral Approach_Education
A2: Target Participants | C2: Children (Boy) | I2: Adults (Male)
C3: Children (Girl) | I3: Adults (Female)
A4: Key Statistics
A5: School System | C5: Number of School | E5: Enrolment Rate | F5: Attendance Rate | G5: Completion Rate | I5: Dropout Rate | K5: Student-Teacher Ratio | M5: Age Group | O5: Literacy Rate | P5: Numeracy Rate
A6: Nursery / Pre-school | M6: Children
A7: Primary School
A8: Secondary School | M8: Adult
A9: Tertiary
A10: Data Source | C10: Please indicate the source of the statistics entered above, including the name of the source (e.g., national census, DHS/MICS, government or ministry report, GN community assessment), the reference year, and the geographic level of the data (national, provincial, district, or project community). Where figures come from different sources, please specify the source for each indicator.
A11: Situation Analysis
A12: Education-related Status in the Community | C12: Please describe education-related situations within the community and consider how they relate with the following sections. - Education-related situation in the community that requires GN's intervention - Contextual properties of the community and cross-cutting issues that GN should consider when implementing a sectoral approach
A13: Problem Tree
A14: Effect | C14: Please put the image of the problem tree. (Insert > Pictures > This Device)
A15: Main Problem
A16: Causes
A17: Photos | C17: Please include photos that clearly show the current problem situation in the community.
A18: Case Story | C18: Please share a case story that illustrates the problem situation well.
A19: Objective Tree
A20: Ends | C20: Please put the image of objective tree. (Insert > Pictures > This Device)
A21: Objectives
A22: Means
A23: Alignment with Country MLTSP
A24: Related Programmatic Direction | C24: Strategic Objective
C26: Expected Outcome | I26: Related Outcome Indicator
A30: Project Result and M&E Framework
A31: Cross-cutting Issue | K31: Remarks
A32: Log Frame | E32: M&E Framework
A33: Objective | E33: Indicator | G33: Definition | I33: Unit | J33: Baseline | K33: Target | L33: Means of Verification | O33: Frequency of Data Collection
A34: Outcome
A35: 1
A36: 2
A37: 3
A38: 4
A39: 5
A40: Output
A41: 1.1 | D41: =A41&" "&B41 -> 1.1
A42: 1.2 | D42: =A42&" "&B42 -> 1.2
A43: 1.3 | D43: =A43&" "&B43 -> 1.3
A44: 2.1 | D44: =A44&" "&B44 -> 2.1
A45: 2.2 | D45: =A45&" "&B45 -> 2.2
A46: 2.3 | D46: =A46&" "&B46 -> 2.3
A47: 3.1 | D47: =A47&" "&B47 -> 3.1
A48: 3.2 | D48: =A48&" "&B48 -> 3.2
A49: 3.3 | D49: =A49&" "&B49 -> 3.3
A50: 4.1 | D50: =A50&" "&B50 -> 4.1
A51: 4.2 | D51: =A51&" "&B51 -> 4.2
A52: 4.3 | D52: =A52&" "&B52 -> 4.3
... A55: 5.3 | D55: =A55&" "&B55 -> 5.3
A56: Action Plan
A57: Major Activities | E57: Timeline | M57: Remarks
E58: Year 1 | F58: Year 2 | G58: Year 3 | I58: Year 4 | K58: Year 5
A59: 1.1.1 | D59: =A59&" "&B59 -> 1.1.1
A60: 1.1.2 | D60: =A60&" "&B60 -> 1.1.2
A61: 1.2.1 | D61: =A61&" "&B61 -> 1.2.1
A62: 1.2.2 | D62: =A62&" "&B62 -> 1.2.2
A63: 1.3.1 | D63: =A63&" "&B63 -> 1.3.1
A64: 1.3.2 | D64: =A64&" "&B64 -> 1.3.2
A65: 2.1.1 | D65: =A65&" "&B65 -> 2.1.1
A66: 2.1.2 | D66: =A66&" "&B66 -> 2.1.2
A67: 2.2.1 | D67: =A67&" "&B67 -> 2.2.1
A68: 2.2.2 | D68: =A68&" "&B68 -> 2.2.2
A69: 2.3.1 | D69: =A69&" "&B69 -> 2.3.1
A70: 2.3.2 | D70: =A70&" "&B70 -> 2.3.2
... A88: 5.3.2 | D88: =A88&" "&B88 -> 5.3.2
A89: Budget Plan
A90: Output | C90: Major Activity | E90: Basis of Calculation | G90: Unit | H90: Unit Cost ($) | I90: Quantity | J90: Total | K90: Y1 | L90: Y2 | M90: Y3 | N90: Y4 | O90: Y5 | P90: Total
J91: =H91*I91 -> 0 | P91: =SUM(K91:O91) -> 0
J92: =H92*I92 -> 0 | P92: =SUM(K92:O92) -> 0
J93: =H93*I93 -> 0 | P93: =SUM(K93:O93) -> 0
J94: =H94*I94 -> 0 | P94: =SUM(K94:O94) -> 0
J95: =H95*I95 -> 0 | P95: =SUM(K95:O95) -> 0
J96: =H96*I96 -> 0 | P96: =SUM(K96:O96) -> 0
J97: =H97*I97 -> 0 | P97: =SUM(K97:O97) -> 0
J98: =H98*I98 -> 0 | P98: =SUM(K98:O98) -> 0
J99: =H99*I99 -> 0 | P99: =SUM(K99:O99) -> 0
J100: =H100*I100 -> 0 | P100: =SUM(K100:O100) -> 0
J101: =H101*I101 -> 0 | P101: =SUM(K101:O101) -> 0
J102: =H102*I102 -> 0 | P102: =SUM(K102:O102) -> 0
... J112: =H112*I112 -> 0 | P112: =SUM(K112:O112) -> 0
A113: Education Total | J113: =SUM(J91:J112) -> 0 | K113: =SUM(K91:K112) -> 0 | L113: =SUM(L91:L112) -> 0 | M113: =SUM(M91:M112) -> 0 | N113: =SUM(N91:N112) -> 0 | O113: =SUM(O91:O112) -> 0 | P113: =SUM(K113:O113) -> 0

Sheet 3. Sector_Health & Well-being
A1: 3. Sectoral Approach_Health and Well-being
A2: Target Participants | C2: Children (Boy) | I2: Adults (Male)
C3: Children (Girl) | I3: Adults (Female)
A4: Key Statistics
A5: Health | K5: WASH | O5: Remarks
A6: Access Rate to the Basic Health Services | C6: No. of Equipped Health Facility | E6: Under 5 Mortality Rate | F6: Skilled Birth Attendance Rate | G6: Immunization Coverage Rate (Under 5) | I6: Leading Causes of Morbidity & Mortality | K6: Access Rate to Safe Drinking Water | M6: Access Rate to Basic Sanitation
A8: Data Source | C8: Please indicate the source of the statistics entered above, including the name of the source (e.g., national census, DHS/MICS, government or ministry report, GN community assessment), the reference year, and the geographic level of the data (national, provincial, district, or project community). Where figures come from different sources, please specify the source for each indicator.
A9: Situation Analysis
A10: Health & Well-being-related Status in the Community | C10: Please describe the Health & Well-being situation in the community, with consideration of the following: - Health & Well-being conditions that require GN's intervention - Contextual factors and cross-cutting issues GN should consider when implementing a sectoral approach
A11: Problem Tree
A12: Effect | C12: Please put the image of the problem tree. (Insert > Pictures > This Device)
A13: Main Problem
A14: Causes
A15: Photos | C15: Please include photos that clearly show the current problem situation in the community.
A16: Case Story | C16: Please share a case story that illustrates the problem situation well.
A17: Objective Tree
A18: Ends | C18: Please put the image of objective tree. (Insert > Pictures > This Device)
A19: Objectives
A20: Means
A21: Alignment with Country MLTSP
A22: Related Programmatic Direction | C22: Strategic Objective
C24: Expected Outcome | I24: Related Outcome Indicator
A28: Project Result and M&E Framework
A29: Cross-cutting Issue | K29: Remarks
A30: Log Frame | E30: M&E Framework
A31: Objective | E31: Indicator | G31: Definition | I31: Unit | J31: Baseline | K31: Target | L31: Means of Verification | O31: Frequency of Data Collection
A32: Outcome
A33: 1
A34: 2
A35: 3
A36: 4
A37: 5
A38: Output
A39: 1.1 | D39: =A39&" "&B39 -> 1.1
A40: 1.2 | D40: =A40&" "&B40 -> 1.2
A41: 1.3 | D41: =A41&" "&B41 -> 1.3
A42: 2.1 | D42: =A42&" "&B42 -> 2.1
A43: 2.2 | D43: =A43&" "&B43 -> 2.2
A44: 2.3 | D44: =A44&" "&B44 -> 2.3
A45: 3.1 | D45: =A45&" "&B45 -> 3.1
A46: 3.2 | D46: =A46&" "&B46 -> 3.2
A47: 3.3 | D47: =A47&" "&B47 -> 3.3
A48: 4.1 | D48: =A48&" "&B48 -> 4.1
A49: 4.2 | D49: =A49&" "&B49 -> 4.2
A50: 4.3 | D50: =A50&" "&B50 -> 4.3
... A53: 5.3 | D53: =A53&" "&B53 -> 5.3
A54: Action Plan
A55: Major Activities | E55: Timeline | M55: Remarks
E56: Year 1 | F56: Year 2 | G56: Year 3 | I56: Year 4 | K56: Year 5
A57: 1.1.1 | D57: =A57&" "&B57 -> 1.1.1
A58: 1.1.2 | D58: =A58&" "&B58 -> 1.1.2
A59: 1.2.1 | D59: =A59&" "&B59 -> 1.2.1
A60: 1.2.2 | D60: =A60&" "&B60 -> 1.2.2
A61: 1.3.1 | D61: =A61&" "&B61 -> 1.3.1
A62: 1.3.2 | D62: =A62&" "&B62 -> 1.3.2
A63: 2.1.1 | D63: =A63&" "&B63 -> 2.1.1
A64: 2.1.2 | D64: =A64&" "&B64 -> 2.1.2
A65: 2.2.1 | D65: =A65&" "&B65 -> 2.2.1
A66: 2.2.2 | D66: =A66&" "&B66 -> 2.2.2
A67: 2.3.1 | D67: =A67&" "&B67 -> 2.3.1
A68: 2.3.2 | D68: =A68&" "&B68 -> 2.3.2
... A86: 5.3.2 | D86: =A86&" "&B86 -> 5.3.2
A87: Budget Plan
A88: Output | C88: Major Activities | E88: Basis of Calculation | G88: Unit | H88: Unit Cost ($) | I88: Quantity | J88: Total | K88: Y1 | L88: Y2 | M88: Y3 | N88: Y4 | O88: Y5 | P88: Total
J89: =H89*I89 -> 0 | P89: =SUM(K89:O89) -> 0
J90: =H90*I90 -> 0 | P90: =SUM(K90:O90) -> 0
J91: =H91*I91 -> 0 | P91: =SUM(K91:O91) -> 0
J92: =H92*I92 -> 0 | P92: =SUM(K92:O92) -> 0
J93: =H93*I93 -> 0 | P93: =SUM(K93:O93) -> 0
J94: =H94*I94 -> 0 | P94: =SUM(K94:O94) -> 0
J95: =H95*I95 -> 0 | P95: =SUM(K95:O95) -> 0
J96: =H96*I96 -> 0 | P96: =SUM(K96:O96) -> 0
J97: =H97*I97 -> 0 | P97: =SUM(K97:O97) -> 0
J98: =H98*I98 -> 0 | P98: =SUM(K98:O98) -> 0
J99: =H99*I99 -> 0 | P99: =SUM(K99:O99) -> 0
J100: =H100*I100 -> 0 | P100: =SUM(K100:O100) -> 0
... J110: =H110*I110 -> 0 | P110: =SUM(K110:O110) -> 0
A111: Health & Well-being Total | J111: =SUM(J89:J110) -> 0 | K111: =SUM(K89:K110) -> 0 | L111: =SUM(L89:L110) -> 0 | M111: =SUM(M89:M110) -> 0 | N111: =SUM(N89:N110) -> 0 | O111: =SUM(O89:O110) -> 0 | P111: =SUM(K111:O111) -> 0

Sheet 3. Sector_Economic Empowerment
A1: 3. Sectoral Approach_Economic Empowerment
A2: Target Participants | C2: Children (Boy) | I2: Adults (Male)
C3: Children (Girl) | I3: Adults (Female)
A4: Key Statistics
C5: Labor Force Participation Rate | E5: Unemployment Rate | F5: Average Monthly Income of Household | G5: Primary Source of Income | M5: Access Rate to Financial Services | O5: Remarks
A6: Male
A7: Female
A8: Data Source | C8: Please indicate the source of the statistics entered above, including the name of the source (e.g., national census, DHS/MICS, government or ministry report, GN community assessment), the reference year, and the geographic level of the data (national, provincial, district, or project community). Where figures come from different sources, please specify the source for each indicator.
A9: Situation Analysis
A10: Economic Empowerment-related Status in the Community | C10: Please describe Economic Empowerment-related situations in the community and consider how they relate with the following sections. - Economic Empowerment related situation in the community that requires GN's intervention - Contextual properties of the community and cross-cutting issues that GN should consider when implementing a sectoral approach.
A11: Problem Tree
A12: Effect | C12: Please put the image of the problem tree. (Insert > Pictures > This Device)
A13: Main Problem
A14: Causes
A15: Photos | C15: Please include photos that clearly show the current problem situation in the community.
A16: Case Story | C16: Please share a case story that illustrates the problem situation well.
A17: Objective Tree
A18: Ends | C18: Please put the image of objective tree. (Insert > Pictures > This Device)
A19: Objectives
A20: Means
A21: Alignment with Country MLTSP
A22: Related Programmatic Direction | C22: Strategic Objective
C24: Expected Outcome | I24: Related Outcome Indicator
A28: Project Result and M&E Framework
A29: Cross-cutting Issue | K29: Remarks
A30: Log Frame | E30: M&E Framework
A31: Objective | E31: Indicator | G31: Definition | I31: Unit | J31: Baseline | K31: Target | L31: Means of Verification | O31: Frequency of Data Collection
A32: Outcome
A33: 1
A34: 2
A35: 3
A36: 4
A37: 5
A38: Output
A39: 1.1 | D39: =A39&" "&B39 -> 1.1
A40: 1.2 | D40: =A40&" "&B40 -> 1.2
A41: 1.3 | D41: =A41&" "&B41 -> 1.3
A42: 2.1 | D42: =A42&" "&B42 -> 2.1
A43: 2.2 | D43: =A43&" "&B43 -> 2.2
A44: 2.3 | D44: =A44&" "&B44 -> 2.3
A45: 3.1 | D45: =A45&" "&B45 -> 3.1
A46: 3.2 | D46: =A46&" "&B46 -> 3.2
A47: 3.3 | D47: =A47&" "&B47 -> 3.3
A48: 4.1 | D48: =A48&" "&B48 -> 4.1
A49: 4.2 | D49: =A49&" "&B49 -> 4.2
A50: 4.3 | D50: =A50&" "&B50 -> 4.3
... A53: 5.3 | D53: =A53&" "&B53 -> 5.3
A54: Action Plan
A55: Major Activities | E55: Timeline | M55: Remarks
E56: Year 1 | F56: Year 2 | G56: Year 3 | I56: Year 4 | K56: Year 5
A57: 1.1.1 | D57: =A57&" "&B57 -> 1.1.1
A58: 1.1.2 | D58: =A58&" "&B58 -> 1.1.2
A59: 1.2.1 | D59: =A59&" "&B59 -> 1.2.1
A60: 1.2.2 | D60: =A60&" "&B60 -> 1.2.2
A61: 1.3.1 | D61: =A61&" "&B61 -> 1.3.1
A62: 1.3.2 | D62: =A62&" "&B62 -> 1.3.2
A63: 2.1.1 | D63: =A63&" "&B63 -> 2.1.1
A64: 2.1.2 | D64: =A64&" "&B64 -> 2.1.2
A65: 2.2.1 | D65: =A65&" "&B65 -> 2.2.1
A66: 2.2.2 | D66: =A66&" "&B66 -> 2.2.2
A67: 2.3.1 | D67: =A67&" "&B67 -> 2.3.1
A68: 2.3.2 | D68: =A68&" "&B68 -> 2.3.2
... A86: 5.3.2 | D86: =A86&" "&B86 -> 5.3.2
A87: Budget Plan
A88: Output | C88: Major Activity | E88: Basis of Calculation | G88: Unit | H88: Unit Cost ($) | I88: Quantity | J88: Total | K88: Y1 | L88: Y2 | M88: Y3 | N88: Y4 | O88: Y5 | P88: Total
J89: =H89*I89 -> 0 | P89: =SUM(K89:O89) -> 0
J90: =H90*I90 -> 0 | P90: =SUM(K90:O90) -> 0
J91: =H91*I91 -> 0 | P91: =SUM(K91:O91) -> 0
J92: =H92*I92 -> 0 | P92: =SUM(K92:O92) -> 0
J93: =H93*I93 -> 0 | P93: =SUM(K93:O93) -> 0
J94: =H94*I94 -> 0 | P94: =SUM(K94:O94) -> 0
J95: =H95*I95 -> 0 | P95: =SUM(K95:O95) -> 0
J96: =H96*I96 -> 0 | P96: =SUM(K96:O96) -> 0
J97: =H97*I97 -> 0 | P97: =SUM(K97:O97) -> 0
J98: =H98*I98 -> 0 | P98: =SUM(K98:O98) -> 0
J99: =H99*I99 -> 0 | P99: =SUM(K99:O99) -> 0
J100: =H100*I100 -> 0 | P100: =SUM(K100:O100) -> 0
... J110: =H110*I110 -> 0 | P110: =SUM(K110:O110) -> 0
A111: Economic Empowerment Total | J111: =SUM(J89:J110) -> 0 | K111: =SUM(K89:K110) -> 0 | L111: =SUM(L89:L110) -> 0 | M111: =SUM(M89:M110) -> 0 | N111: =SUM(N89:N110) -> 0 | O111: =SUM(O89:O110) -> 0 | P111: =SUM(K111:O111) -> 0

Sheet 3. Sector_Others
A1: 3. Sectoral Approach_Others
A2: Target Participants | C2: Children (Boy) | I2: Adults (Male)
C3: Children (Girl) | I3: Adults (Female)
A4: Key Statistics
A7: Data Source | C7: Please indicate the source of the statistics entered above, including the name of the source (e.g., national census, DHS/MICS, government or ministry report, GN community assessment), the reference year, and the geographic level of the data (national, provincial, district, or project community). Where figures come from different sources, please specify the source for each indicator.
A8: Situation Analysis
A9: Sector-specific Status in the Community | C9: This section is for sectors not covered under Education, Health & Well-being, Economic Empowerment, or Child Protection (e.g., Climate Change, Humanitarian Assistance). Clearly specify the sector being addressed (e.g., Climate Change, Humanitarian Assistance, Environment, Psychosocial Support, etc.) and describe the sector-specific situation in the community - Key issues that require GN's intervention in this sector; - Contextual properties of the community and cross-cutting issues that GN should consider when implementing a sectoral approach.
A10: Problem Tree
A11: Effect | C11: Please put the image of the problem tree. (Insert > Pictures > This Device)
A12: Main Problem
A13: Causes
A14: Photos | C14: Please include photos that clearly show the current problem situation in the community.
A15: Case Story | C15: Please share a case story that illustrates the problem situation well.
A16: Objective Tree
A17: Ends | C17: Please put the image of objective tree. (Insert > Pictures > This Device)
A18: Objectives
A19: Means
A20: Alignment with Country MLTSP
A21: Related Programmatic Direction | C21: Strategic Objective
C23: Expected Outcome | I23: Related Outcome Indicator
A27: Project Result and M&E Framework
A28: Cross-cutting Issue | K28: Remarks
A29: Log Frame | E29: M&E Framework
A30: Objective | E30: Indicator | G30: Definition | I30: Unit | J30: Baseline | K30: Target | L30: Means of Verification | O30: Frequency of Data Collection
A31: Outcome
A32: 1
A33: 2
A34: 3
A35: 4
A36: 5
A37: Output
A38: 1.1 | D38: =A38&" "&B38 -> 1.1
A39: 1.2 | D39: =A39&" "&B39 -> 1.2
A40: 1.3 | D40: =A40&" "&B40 -> 1.3
A41: 2.1 | D41: =A41&" "&B41 -> 2.1
A42: 2.2 | D42: =A42&" "&B42 -> 2.2
A43: 2.3 | D43: =A43&" "&B43 -> 2.3
A44: 3.1 | D44: =A44&" "&B44 -> 3.1
A45: 3.2 | D45: =A45&" "&B45 -> 3.2
A46: 3.3 | D46: =A46&" "&B46 -> 3.3
A47: 4.1 | D47: =A47&" "&B47 -> 4.1
A48: 4.2 | D48: =A48&" "&B48 -> 4.2
A49: 4.3 | D49: =A49&" "&B49 -> 4.3
... A52: 5.3 | D52: =A52&" "&B52 -> 5.3
A53: Action Plan
A54: Major Activities | E54: Timeline | M54: Remarks
E55: Year 1 | F55: Year 2 | G55: Year 3 | I55: Year 4 | K55: Year 5
A56: 1.1.1 | D56: =A56&" "&B56 -> 1.1.1
A57: 1.1.2 | D57: =A57&" "&B57 -> 1.1.2
A58: 1.2.1 | D58: =A58&" "&B58 -> 1.2.1
A59: 1.2.2 | D59: =A59&" "&B59 -> 1.2.2
A60: 1.3.1 | D60: =A60&" "&B60 -> 1.3.1
A61: 1.3.2 | D61: =A61&" "&B61 -> 1.3.2
A62: 2.1.1 | D62: =A62&" "&B62 -> 2.1.1
A63: 2.1.2 | D63: =A63&" "&B63 -> 2.1.2
A64: 2.2.1 | D64: =A64&" "&B64 -> 2.2.1
A65: 2.2.2 | D65: =A65&" "&B65 -> 2.2.2
A66: 2.3.1 | D66: =A66&" "&B66 -> 2.3.1
A67: 2.3.2 | D67: =A67&" "&B67 -> 2.3.2
... A85: 5.3.2 | D85: =A85&" "&B85 -> 5.3.2
A86: Budget Plan
A87: Output | C87: Major Activity | E87: Basis of Calculation | G87: Unit | H87: Unit Cost ($) | I87: Quantity | J87: Total | K87: Y1 | L87: Y2 | M87: Y3 | N87: Y4 | O87: Y5 | P87: Total
J88: =H88*I88 -> 0 | P88: =SUM(K88:O88) -> 0
J89: =H89*I89 -> 0 | P89: =SUM(K89:O89) -> 0
J90: =H90*I90 -> 0 | P90: =SUM(K90:O90) -> 0
J91: =H91*I91 -> 0 | P91: =SUM(K91:O91) -> 0
J92: =H92*I92 -> 0 | P92: =SUM(K92:O92) -> 0
J93: =H93*I93 -> 0 | P93: =SUM(K93:O93) -> 0
J94: =H94*I94 -> 0 | P94: =SUM(K94:O94) -> 0
J95: =H95*I95 -> 0 | P95: =SUM(K95:O95) -> 0
J96: =H96*I96 -> 0 | P96: =SUM(K96:O96) -> 0
J97: =H97*I97 -> 0 | P97: =SUM(K97:O97) -> 0
J98: =H98*I98 -> 0 | P98: =SUM(K98:O98) -> 0
J99: =H99*I99 -> 0 | P99: =SUM(K99:O99) -> 0
... J109: =H109*I109 -> 0 | P109: =SUM(K109:O109) -> 0
A110: Others Total | J110: =SUM(J88:J109) -> 0 | K110: =SUM(K88:K109) -> 0 | L110: =SUM(L88:L109) -> 0 | M110: =SUM(M88:M109) -> 0 | N110: =SUM(N88:N109) -> 0 | O110: =SUM(O88:O109) -> 0 | P110: =SUM(K110:O110) -> 0

Sheet 4. Child Sponsorship Management
A1: 4. Child Sponsorship Management (If applicable)
A2: Program Area Overview
A3: Category | C3: Description
A4: Possibility and Ground of Child Sponsorship Program | C4: Please describe the possibility and ground of the child sponsorship program, considering the following points. - Validity of area selection (socio-economic vulnerability; high concentration of children in need of protection) - Scale of eligible children (at least 1,000 children) - No overlap with other NGOs (area not currently covered by other NGO support)
A5: Selection Criteria for Children | C5: Please describe the criteria used to select sponsored children, referring to the guidelines. - Age range and priority given to vulnerable children - Number of children selected per household - Length of residence in the target area - Children not already sponsored by GN or another organization
A6: Community Participation | C6: Please describe the level of participation and cooperation expected from the community. - Roles of sponsored children (CIF, APR, ACL, health check-up, letter writing) and participation in community project activities - Roles of parents / guardians (supporting the child's participation, using the support for its intended purpose, joining the parents association and volunteer network, reporting changes in family circumstances) - Cooperation of local government, schools and community leaders
A7: Positive and Negative Factors | C7: Please describe the conditions that may help or hinder the program, and how the project will respond. - Positive factors (e.g., cooperation of local government and schools, level of need in the community) - Negative factors (e.g., travel time to households, language differences, early marriage) and planned mitigation measures
A8: Sponsored Children by Year
A9: Category | B9: Sponsor | C9: Existing | D9: Year 1 | G9: Year 2 | J9: Year 3 | M9: Year 4 | P9: Year 5
D10: New | E10: Drop-out | F10: Total | G10: New | H10: Drop-out | I10: Total | J10: New | K10: Drop-out | L10: Total | M10: New | N10: Drop-out | O10: Total | P10: New | Q10: Drop-out | R10: Total
A11: Core Alliance Country | B11: Korea | F11: =C11+D11-E11 -> 0 | I11: =F11+G11-H11 -> 0 | L11: =I11+J11-K11 -> 0 | O11: =L11+M11-N11 -> 0 | R11: =O11+P11-Q11 -> 0
B12: USA | F12: =C12+D12-E12 -> 0 | I12: =F12+G12-H12 -> 0 | L12: =I12+J12-K12 -> 0 | O12: =L12+M12-N12 -> 0 | R12: =O12+P12-Q12 -> 0
B13: Japan | F13: =C13+D13-E13 -> 0 | I13: =F13+G13-H13 -> 0 | L13: =I13+J13-K13 -> 0 | O13: =L13+M13-N13 -> 0 | R13: =O13+P13-Q13 -> 0
B14: Canada | F14: =C14+D14-E14 -> 0 | I14: =F14+G14-H14 -> 0 | L14: =I14+J14-K14 -> 0 | O14: =L14+M14-N14 -> 0 | R14: =O14+P14-Q14 -> 0
B15: Australia | F15: =C15+D15-E15 -> 0 | I15: =F15+G15-H15 -> 0 | L15: =I15+J15-K15 -> 0 | O15: =L15+M15-N15 -> 0 | R15: =O15+P15-Q15 -> 0
B16: UK | F16: =C16+D16-E16 -> 0 | I16: =F16+G16-H16 -> 0 | L16: =I16+J16-K16 -> 0 | O16: =L16+M16-N16 -> 0 | R16: =O16+P16-Q16 -> 0
B17: Taiwan | F17: =C17+D17-E17 -> 0 | I17: =F17+G17-H17 -> 0 | L17: =I17+J17-K17 -> 0 | O17: =L17+M17-N17 -> 0 | R17: =O17+P17-Q17 -> 0
A18: Sub total | C18: =SUM(C11:C17) -> 0 | D18: =SUM(D11:D17) -> 0 | E18: =SUM(E11:E17) -> 0 | F18: =SUM(F11:F17) -> 0 | G18: =SUM(G11:G17) -> 0 | H18: =SUM(H11:H17) -> 0 | I18: =SUM(I11:I17) -> 0 | J18: =SUM(J11:J17) -> 0 | ... R18: =SUM(R11:R17) -> 0
A19: Local | F19: =C19+D19-E19 -> 0 | I19: =F19+G19-H19 -> 0 | L19: =I19+J19-K19 -> 0 | O19: =L19+M19-N19 -> 0 | R19: =O19+P19-Q19 -> 0
A20: Total | C20: =C18+C19 -> 0 | D20: =D18+D19 -> 0 | E20: =E18+E19 -> 0 | F20: =F18+F19 -> 0 | G20: =G18+G19 -> 0 | H20: =H18+H19 -> 0 | I20: =I18+I19 -> 0 | J20: =J18+J19 -> 0 | ... R20: =R18+R19 -> 0
A21: Five-Year Program Plan
A22: Child Sponsorship Program
A23: Classification | B23: Service | C23: Target | E23: Standard | G23: Basis of Calculation | J23: Unit | K23: Unit cost ($) | L23: Total | M23: FY1 | N23: FY2 | O23: FY3 | P23: FY4 | Q23: FY5 | R23: Total
A24: Child Sponsorship Management | B24: Child Management | C24: All sponsored children | E24: 3 times / year | L24: =J24*K24 -> 0 | R24: =SUM(M24:Q24) -> 0
A25: Child Protection | B25: Child Rights Campaign | E25: - | L25: =J25*K25 -> 0 | R25: =SUM(M25:Q25) -> 0
A26: Education | B26: Financial / Material Support | E26: - | L26: =J26*K26 -> 0 | R26: =SUM(M26:Q26) -> 0
B27: Alternative (Non-formal) Education Support | C27: All sponsored children not in school | E27: 1 time / child / year | L27: =J27*K27 -> 0 | R27: =SUM(M27:Q27) -> 0
A28: Health & Well-being | B28: Health Check-up | C28: All sponsored children | E28: - | L28: =J28*K28 -> 0 | R28: =SUM(M28:Q28) -> 0
B29: Nutrition Support | C29: All sponsored children with severe malnutrition | E29: 100% of target children | L29: =J29*K29 -> 0 | R29: =SUM(M29:Q29) -> 0
B30: WASH Education | C30: All sponsored children | E30: - | L30: =J30*K30 -> 0 | R30: =SUM(M30:Q30) -> 0
A31: Others | L31: =J31*K31 -> 0 | R31: =SUM(M31:Q31) -> 0
L32: =J32*K32 -> 0 | R32: =SUM(M32:Q32) -> 0
L33: =J33*K33 -> 0 | R33: =SUM(M33:Q33) -> 0
A34: Total | L34: =SUM(L24:L33) -> 0 | M34: =SUM(M24:M33) -> 0 | N34: =SUM(N24:N33) -> 0 | O34: =SUM(O24:O33) -> 0 | P34: =SUM(P24:P33) -> 0 | Q34: =SUM(Q24:Q33) -> 0 | R34: =SUM(R24:R33) -> 0
A35: Monitoring & Evaluation
A36: Service | B36: Frequency | C36: Method | F36: Basis of Calculation | J36: Unit | K36: Unit cost ($) | L36: Total | M36: FY1 | N36: FY2 | O36: FY3 | P36: FY4 | Q36: FY5 | R36: Total
A37: CIF | L37: =J37*K37 -> 0 | R37: =SUM(M37:Q37) -> 0
A38: APR | L38: =J38*K38 -> 0 | R38: =SUM(M38:Q38) -> 0
A39: ACL | L39: =J39*K39 -> 0 | R39: =SUM(M39:Q39) -> 0
A40: Others | L40: =J40*K40 -> 0 | R40: =SUM(M40:Q40) -> 0
L41: =J41*K41 -> 0 | R41: =SUM(M41:Q41) -> 0
A42: Total | L42: =SUM(L37:L41) -> 0 | M42: =SUM(M37:M41) -> 0 | N42: =SUM(N37:N41) -> 0 | O42: =SUM(O37:O41) -> 0 | P42: =SUM(P37:P41) -> 0 | Q42: =SUM(Q37:Q41) -> 0 | R42: =SUM(R37:R41) -> 0
A43: Risk Management
A44: Area | C44: Risk | J44: Mitigation Plan
A45: Submission Rate
A46: Error Rate
A47: Dropout
A48: CMS Management
A49: Document Management

Sheet 5. Project Management Plan
A1: 5. Project Management
A2: Network Management
A3: Community Engagement Plan
A4: Related indicator | D4: Target | E4: Description
E5: Name of Committee | F5: No. of Committee Members | G5: Related sector | H5: Key roles
A6: No. of Committees
A7: No. of Sub-Committees
A8: No. of Committee Members | C8: Male
C9: Female
A10: Committee Operation Plan | E10: Please describe the committee organization plan including the belows.: • Membership criteria — who is eligible to join (e.g., religious leaders, village leaders, women leaders, youth representatives, school principals, village representative groups); • Representation & inclusion — how gender balance and the participation of vulnerable or marginalised groups will be secured; • Selection process — how members are nominated or elected, and how transparency is ensured; • Term & turnover — length of service and how replacement members will be recruited.
A11: No. of training sessions for committee or sub-committee members | E11: Please describe the capacity-building plan for committee and sub-committee members referring to the guidelines.
A12: No. of meetings held by committees and sub-committees | E12: Please describe the operation and participation plan for committees and sub-committees referring to the guidelines.
A13: No. of children’s, teens’ or youth clubs supported by GN | E13: Please describe the plan for children’s, teens’ or youth clubs supported by the project referring to the guidelines.
A14: No. of members in children’s, teens’ or youth clubs supported by GN
A15: Stakeholder Engagement & Collaboration Plan
A16: Stakeholder Group | C16: Attitude toward GN Projects | D16: Area of Technical Expertise | E16: Coverage in Project Area | F16: Partnership & Networking Plan
A20: Risk Management
A21: Risk | D21: Mitigation Plan
A22: Please provide the identified risks in the planned sectoral approach. | D22: Please describe the plan on how you will mitigate the identified risks.
A25: Evaluation Plan
A26: Please describe the plan for assessing Outcome-level results across the project cycle, including: - Evaluation approach — whether assessments will be conducted internally (e.g., pre/post surveys by project staff) or in partnership with an external agency (e.g., consultant engagement, development of standardized assessment tools); - Review cycle — frequency and timing of Outcome indicator tracking throughout the project period; - Other considerations — any additional elements relevant to the evaluation approach, such as data quality assurance measures, stakeholder involvement in the evaluation process, or plans for disseminating findings.
A27: Sustainability Plan
A28: Category | C28: Description
A29: Financial Sustainability | C29: Please describe how the project will secure continued funding and resources beyond the project period. This includes plans for local budget integration, strategies to reduce external donor dependency, and any income-generating mechanisms linked to the project.
A30: Transition & Local Ownership Plan | C30: Please describe how project responsibilities and operations will be gradually transferred to local governments, community organizations, or other local stakeholders. Include a phased handover timeline, capacity-building measures for local actors, and how community ownership will be ensured to sustain project outcomes beyond GN's involvement.
A31: Budget Management Plan
A32: Income Plan
A33: Related Support Country | F33: Remarks
A34: Category / Project Year | C34: Year 1 | D34: Year 2 | E34: Year 3 | F34: Year 4 | G34: Year 5 | H34: Total | I34: %
A35: GPC Subsidy | C35: =SUM(C36:C39) -> 0 | D35: =SUM(D36:D39) -> 0 | E35: =SUM(E36:E39) -> 0 | F35: =SUM(F36:F39) -> 0 | G35: =SUM(G36:G39) -> 0 | H35: =SUM(C35:G35) -> 0 | I35: =IFERROR(H35/H47,"")
A36: Child Sponsorship Fund | H36: =SUM(C36:G36) -> 0 | I36: =IFERROR(H36/H47,"")
A37: Project Sponsorship Fund | H37: =SUM(C37:G37) -> 0 | I37: =IFERROR(H37/H47,"")
A38: Designated | H38: =SUM(C38:G38) -> 0 | I38: =IFERROR(H38/H47,"")
A39: Government | H39: =SUM(C39:G39) -> 0 | I39: =IFERROR(H39/H47,"")
A40: Local Income | C40: =SUM(C41:C46) -> 0 | D40: =SUM(D41:D46) -> 0 | E40: =SUM(E41:E46) -> 0 | F40: =SUM(F41:F46) -> 0 | G40: =SUM(G41:G46) -> 0 | H40: =SUM(C40:G40) -> 0 | I40: =IFERROR(H40/H47,"")
A41: General (regular sponsorship) | H41: =SUM(C41:G41) -> 0 | I41: =IFERROR(H41/H47,"")
A42: Designated Fund (irregular; one-time donation) | H42: =SUM(C42:G42) -> 0 | I42: =IFERROR(H42/H47,"")
A43: Government Fund (national/local government) | H43: =SUM(C43:G43) -> 0 | I43: =IFERROR(H43/H47,"")
A44: International Organization | H44: =SUM(C44:G44) -> 0 | I44: =IFERROR(H44/H47,"")
A45: Gift in Kinds | H45: =SUM(C45:G45) -> 0 | I45: =IFERROR(H45/H47,"")
A46: Others | H46: =SUM(C46:G46) -> 0 | I46: =IFERROR(H46/H47,"")
A47: Income Total | C47: =C40+C35 -> 0 | D47: =D40+D35 -> 0 | E47: =E40+E35 -> 0 | F47: =F40+F35 -> 0 | G47: =G40+G35 -> 0 | H47: =H40+H35 -> 0
A48: Expense Plan
A49: Project Implementation | B49: Child Sponsorship Management | C49: ='4. Child Sponsorship Management'!M34+'4. Child Sponsorship Management'!M42 -> 0 | D49: ='4. Child Sponsorship Management'!N34+'4. Child Sponsorship Management'!N42 -> 0 | E49: ='4. Child Sponsorship Management'!O34+'4. Child Sponsorship Management'!O42 -> 0 | F49: ='4. Child Sponsorship Management'!P34+'4. Child Sponsorship Management'!P42 -> 0 | G49: ='4. Child Sponsorship Management'!Q34+'4. Child Sponsorship Management'!Q42 -> 0 | H49: ='4. Child Sponsorship Management'!R34+'4. Child Sponsorship Management'!R42 -> 0 | I49: =IFERROR(H49/H58,"")
B50: Education | C50: =IFERROR(INDEX('3. Sector_Education'!K:K,MATCH("Education Total",'3. Sector_Education'!$A:$A,0)),0) -> 0 | D50: =IFERROR(INDEX('3. Sector_Education'!L:L,MATCH("Education Total",'3. Sector_Education'!$A:$A,0)),0) -> 0 | E50: =IFERROR(INDEX('3. Sector_Education'!M:M,MATCH("Education Total",'3. Sector_Education'!$A:$A,0)),0) -> 0 | F50: =IFERROR(INDEX('3. Sector_Education'!N:N,MATCH("Education Total",'3. Sector_Education'!$A:$A,0)),0) -> 0 | G50: =IFERROR(INDEX('3. Sector_Education'!O:O,MATCH("Education Total",'3. Sector_Education'!$A:$A,0)),0) -> 0 | H50: =SUM(C50:G50) -> 0 | I50: =IFERROR(H50/H58,"")
B51: Health & Well-being | C51: =IFERROR(INDEX('3. Sector_Health & Well-being'!K:K,MATCH("Health & Well-being Total",'3. Sector_Health & Well-being'!$A:$A,0)),0) -> 0 | D51: =IFERROR(INDEX('3. Sector_Health & Well-being'!L:L,MATCH("Health & Well-being Total",'3. Sector_Health & Well-being'!$A:$A,0)),0) -> 0 | E51: =IFERROR(INDEX('3. Sector_Health & Well-being'!M:M,MATCH("Health & Well-being Total",'3. Sector_Health & Well-being'!$A:$A,0)),0) -> 0 | F51: =IFERROR(INDEX('3. Sector_Health & Well-being'!N:N,MATCH("Health & Well-being Total",'3. Sector_Health & Well-being'!$A:$A,0)),0) -> 0 | G51: =IFERROR(INDEX('3. Sector_Health & Well-being'!O:O,MATCH("Health & Well-being Total",'3. Sector_Health & Well-being'!$A:$A,0)),0) -> 0 | H51: =SUM(C51:G51) -> 0 | I51: =IFERROR(H51/H58,"")
B52: Economic Empowerment | C52: =IFERROR(INDEX('3. Sector_Economic Empowerment'!K:K,MATCH("Economic Empowerment Total",'3. Sector_Economic Empowerment'!$A:$A,0)),0) -> 0 | D52: =IFERROR(INDEX('3. Sector_Economic Empowerment'!L:L,MATCH("Economic Empowerment Total",'3. Sector_Economic Empowerment'!$A:$A,0)),0) -> 0 | E52: =IFERROR(INDEX('3. Sector_Economic Empowerment'!M:M,MATCH("Economic Empowerment Total",'3. Sector_Economic Empowerment'!$A:$A,0)),0) -> 0 | F52: =IFERROR(INDEX('3. Sector_Economic Empowerment'!N:N,MATCH("Economic Empowerment Total",'3. Sector_Economic Empowerment'!$A:$A,0)),0) -> 0 | G52: =IFERROR(INDEX('3. Sector_Economic Empowerment'!O:O,MATCH("Economic Empowerment Total",'3. Sector_Economic Empowerment'!$A:$A,0)),0) -> 0 | H52: =SUM(C52:G52) -> 0 | I52: =IFERROR(H52/H58,"")
B53: Child Protection | C53: =IFERROR(INDEX('3. Sector_Child Protection'!K:K,MATCH("Child Protection Total",'3. Sector_Child Protection'!$A:$A,0)),0) -> 0 | D53: =IFERROR(INDEX('3. Sector_Child Protection'!L:L,MATCH("Child Protection Total",'3. Sector_Child Protection'!$A:$A,0)),0) -> 0 | E53: =IFERROR(INDEX('3. Sector_Child Protection'!M:M,MATCH("Child Protection Total",'3. Sector_Child Protection'!$A:$A,0)),0) -> 0 | F53: =IFERROR(INDEX('3. Sector_Child Protection'!N:N,MATCH("Child Protection Total",'3. Sector_Child Protection'!$A:$A,0)),0) -> 0 | G53: =IFERROR(INDEX('3. Sector_Child Protection'!O:O,MATCH("Child Protection Total",'3. Sector_Child Protection'!$A:$A,0)),0) -> 0 | H53: =SUM(C53:G53) -> 0 | I53: =IFERROR(H53/H58,"")
B54: Others | C54: =IFERROR(INDEX('3. Sector_Others'!K:K,MATCH("Others Total",'3. Sector_Others'!$A:$A,0)),0) -> 0 | D54: =IFERROR(INDEX('3. Sector_Others'!L:L,MATCH("Others Total",'3. Sector_Others'!$A:$A,0)),0) -> 0 | E54: =IFERROR(INDEX('3. Sector_Others'!M:M,MATCH("Others Total",'3. Sector_Others'!$A:$A,0)),0) -> 0 | F54: =IFERROR(INDEX('3. Sector_Others'!N:N,MATCH("Others Total",'3. Sector_Others'!$A:$A,0)),0) -> 0 | G54: =IFERROR(INDEX('3. Sector_Others'!O:O,MATCH("Others Total",'3. Sector_Others'!$A:$A,0)),0) -> 0 | H54: =SUM(C54:G54) -> 0 | I54: =IFERROR(H54/H58,"")
A55: Project Management | B55: Research & Development | H55: =SUM(C55:G55) -> 0 | I55: =IFERROR(H55/H58,"")
B56: Fundraising | H56: =SUM(C56:G56) -> 0 | I56: =IFERROR(H56/H58,"")
B57: Project Management | H57: =SUM(C57:G57) -> 0 | I57: =IFERROR(H57/H58,"")
A58: Expense Total | C58: =SUM(C49:C57) -> 0 | D58: =SUM(D49:D57) -> 0 | E58: =SUM(E49:E57) -> 0 | F58: =SUM(F49:F57) -> 0 | G58: =SUM(G49:G57) -> 0 | H58: =SUM(C58:G58) -> 0 | I58: =IFERROR(H58/H58,"")
A59: Difference | C59: =C47-C58 -> 0 | D59: =C59+D47-D58 -> 0 | E59: =D59+E47-E58 -> 0 | F59: =E59+F47-F58 -> 0 | G59: =F59+G47-G58 -> 0 | H59: =H47-H58 -> 0
A60: HR Management
A61: Employee Name | C61: Department | D61: Position | E61: Year of Experience | F61: Responsibility | H61: Remarks

Sheet (Annex) Indicator Tracking Tool
A1: Indicator Tracking Tool
A3: Sector | B3: Level | C3: No. | D3: Objective | E3: Indicator | F3: Definition / Calculation Basis | G3: Baseline | H3: Target | I3: Y1 | O3: Y2 | U3: Y3 | AA3: Y4 | AG3: Y5
I4: Q1 | J4: Q2 | K4: Q3 | L4: Q4 | M4: % Achieved | N4: Comments on Variance | O4: Q1 | P4: Q2 | Q4: Q3 | R4: Q4 | S4: % Achieved | T4: Comments on Variance | U4: Q1 | V4: Q2 | W4: Q3 | X4: Q4 | Y4: % Achieved | Z4: Comments on Variance | AA4: Q1 | AB4: Q2 | AC4: Q3 | AD4: Q4 | AE4: % Achieved | AF4: Comments on Variance | AG4: Q1 | AH4: Q2 | AI4: Q3 | AJ4: Q4 | AK4: % Achieved | AL4: Comments on Variance
A5: Child Protection | B5: Outcome | C5: =IFERROR(IF(INDEX(ITT_ChildProtection_OC_A,MATCH("1",ITT_ChildProtection_OC_A,0))="","",INDEX(ITT_ChildProtection_OC_A,MATCH("1",ITT_ChildProtection_OC_A,0))),"") -> 1 | D5: =IFERROR(IF(INDEX(ITT_ChildProtection_OC_B,MATCH("1",ITT_ChildProtection_OC_A,0))="","",INDEX(ITT_ChildProtection_OC_B,MATCH("1",ITT_ChildProtection_OC_A,0))),"") | E5: =IFERROR(IF(INDEX(ITT_ChildProtection_OC_E,MATCH("1",ITT_ChildProtection_OC_A,0))="","",INDEX(ITT_ChildProtection_OC_E,MATCH("1",ITT_ChildProtection_OC_A,0))),"") | F5: =IFERROR(IF(INDEX(ITT_ChildProtection_OC_G,MATCH("1",ITT_ChildProtection_OC_A,0))="","",INDEX(ITT_ChildProtection_OC_G,MATCH("1",ITT_ChildProtection_OC_A,0))),"") | G5: =IFERROR(IF(INDEX(ITT_ChildProtection_OC_J,MATCH("1",ITT_ChildProtection_OC_A,0))="","",INDEX(ITT_ChildProtection_OC_J,MATCH("1",ITT_ChildProtection_OC_A,0))),"") | H5: =IFERROR(IF(INDEX(ITT_ChildProtection_OC_K,MATCH("1",ITT_ChildProtection_OC_A,0))="","",INDEX(ITT_ChildProtection_OC_K,MATCH("1",ITT_ChildProtection_OC_A,0))),"") | M5: =IF(OR(L5="",$G5="",$H5=""),"",IF($H5-$G5=0,"",(L5-$G5)/($H5-$G5))) | S5: =IF(OR(R5="",$G5="",$H5=""),"",IF($H5-$G5=0,"",(R5-$G5)/($H5-$G5))) | Y5: =IF(OR(X5="",$G5="",$H5=""),"",IF($H5-$G5=0,"",(X5-$G5)/($H5-$G5))) | AE5: =IF(OR(AD5="",$G5="",$H5=""),"",IF($H5-$G5=0,"",(AD5-$G5)/($H5-$G5))) | AK5: =IF(OR(AJ5="",$G5="",$H5=""),"",IF($H5-$G5=0,"",(AJ5-$G5)/($H5-$G5)))
C6: =IFERROR(IF(INDEX(ITT_ChildProtection_OC_A,MATCH("2",ITT_ChildProtection_OC_A,0))="","",INDEX(ITT_ChildProtection_OC_A,MATCH("2",ITT_ChildProtection_OC_A,0))),"") -> 2 | D6: =IFERROR(IF(INDEX(ITT_ChildProtection_OC_B,MATCH("2",ITT_ChildProtection_OC_A,0))="","",INDEX(ITT_ChildProtection_OC_B,MATCH("2",ITT_ChildProtection_OC_A,0))),"") | E6: =IFERROR(IF(INDEX(ITT_ChildProtection_OC_E,MATCH("2",ITT_ChildProtection_OC_A,0))="","",INDEX(ITT_ChildProtection_OC_E,MATCH("2",ITT_ChildProtection_OC_A,0))),"") | F6: =IFERROR(IF(INDEX(ITT_ChildProtection_OC_G,MATCH("2",ITT_ChildProtection_OC_A,0))="","",INDEX(ITT_ChildProtection_OC_G,MATCH("2",ITT_ChildProtection_OC_A,0))),"") | G6: =IFERROR(IF(INDEX(ITT_ChildProtection_OC_J,MATCH("2",ITT_ChildProtection_OC_A,0))="","",INDEX(ITT_ChildProtection_OC_J,MATCH("2",ITT_ChildProtection_OC_A,0))),"") | H6: =IFERROR(IF(INDEX(ITT_ChildProtection_OC_K,MATCH("2",ITT_ChildProtection_OC_A,0))="","",INDEX(ITT_ChildProtection_OC_K,MATCH("2",ITT_ChildProtection_OC_A,0))),"") | M6: =IF(OR(L6="",$G6="",$H6=""),"",IF($H6-$G6=0,"",(L6-$G6)/($H6-$G6))) | S6: =IF(OR(R6="",$G6="",$H6=""),"",IF($H6-$G6=0,"",(R6-$G6)/($H6-$G6))) | Y6: =IF(OR(X6="",$G6="",$H6=""),"",IF($H6-$G6=0,"",(X6-$G6)/($H6-$G6))) | AE6: =IF(OR(AD6="",$G6="",$H6=""),"",IF($H6-$G6=0,"",(AD6-$G6)/($H6-$G6))) | AK6: =IF(OR(AJ6="",$G6="",$H6=""),"",IF($H6-$G6=0,"",(AJ6-$G6)/($H6-$G6)))
C7: =IFERROR(IF(INDEX(ITT_ChildProtection_OC_A,MATCH("3",ITT_ChildProtection_OC_A,0))="","",INDEX(ITT_ChildProtection_OC_A,MATCH("3",ITT_ChildProtection_OC_A,0))),"") -> 3 | D7: =IFERROR(IF(INDEX(ITT_ChildProtection_OC_B,MATCH("3",ITT_ChildProtection_OC_A,0))="","",INDEX(ITT_ChildProtection_OC_B,MATCH("3",ITT_ChildProtection_OC_A,0))),"") | E7: =IFERROR(IF(INDEX(ITT_ChildProtection_OC_E,MATCH("3",ITT_ChildProtection_OC_A,0))="","",INDEX(ITT_ChildProtection_OC_E,MATCH("3",ITT_ChildProtection_OC_A,0))),"") | F7: =IFERROR(IF(INDEX(ITT_ChildProtection_OC_G,MATCH("3",ITT_ChildProtection_OC_A,0))="","",INDEX(ITT_ChildProtection_OC_G,MATCH("3",ITT_ChildProtection_OC_A,0))),"") | G7: =IFERROR(IF(INDEX(ITT_ChildProtection_OC_J,MATCH("3",ITT_ChildProtection_OC_A,0))="","",INDEX(ITT_ChildProtection_OC_J,MATCH("3",ITT_ChildProtection_OC_A,0))),"") | H7: =IFERROR(IF(INDEX(ITT_ChildProtection_OC_K,MATCH("3",ITT_ChildProtection_OC_A,0))="","",INDEX(ITT_ChildProtection_OC_K,MATCH("3",ITT_ChildProtection_OC_A,0))),"") | M7: =IF(OR(L7="",$G7="",$H7=""),"",IF($H7-$G7=0,"",(L7-$G7)/($H7-$G7))) | S7: =IF(OR(R7="",$G7="",$H7=""),"",IF($H7-$G7=0,"",(R7-$G7)/($H7-$G7))) | Y7: =IF(OR(X7="",$G7="",$H7=""),"",IF($H7-$G7=0,"",(X7-$G7)/($H7-$G7))) | AE7: =IF(OR(AD7="",$G7="",$H7=""),"",IF($H7-$G7=0,"",(AD7-$G7)/($H7-$G7))) | AK7: =IF(OR(AJ7="",$G7="",$H7=""),"",IF($H7-$G7=0,"",(AJ7-$G7)/($H7-$G7)))
C8: =IFERROR(IF(INDEX(ITT_ChildProtection_OC_A,MATCH("4",ITT_ChildProtection_OC_A,0))="","",INDEX(ITT_ChildProtection_OC_A,MATCH("4",ITT_ChildProtection_OC_A,0))),"") -> 4 | D8: =IFERROR(IF(INDEX(ITT_ChildProtection_OC_B,MATCH("4",ITT_ChildProtection_OC_A,0))="","",INDEX(ITT_ChildProtection_OC_B,MATCH("4",ITT_ChildProtection_OC_A,0))),"") | E8: =IFERROR(IF(INDEX(ITT_ChildProtection_OC_E,MATCH("4",ITT_ChildProtection_OC_A,0))="","",INDEX(ITT_ChildProtection_OC_E,MATCH("4",ITT_ChildProtection_OC_A,0))),"") | F8: =IFERROR(IF(INDEX(ITT_ChildProtection_OC_G,MATCH("4",ITT_ChildProtection_OC_A,0))="","",INDEX(ITT_ChildProtection_OC_G,MATCH("4",ITT_ChildProtection_OC_A,0))),"") | G8: =IFERROR(IF(INDEX(ITT_ChildProtection_OC_J,MATCH("4",ITT_ChildProtection_OC_A,0))="","",INDEX(ITT_ChildProtection_OC_J,MATCH("4",ITT_ChildProtection_OC_A,0))),"") | H8: =IFERROR(IF(INDEX(ITT_ChildProtection_OC_K,MATCH("4",ITT_ChildProtection_OC_A,0))="","",INDEX(ITT_ChildProtection_OC_K,MATCH("4",ITT_ChildProtection_OC_A,0))),"") | M8: =IF(OR(L8="",$G8="",$H8=""),"",IF($H8-$G8=0,"",(L8-$G8)/($H8-$G8))) | S8: =IF(OR(R8="",$G8="",$H8=""),"",IF($H8-$G8=0,"",(R8-$G8)/($H8-$G8))) | Y8: =IF(OR(X8="",$G8="",$H8=""),"",IF($H8-$G8=0,"",(X8-$G8)/($H8-$G8))) | AE8: =IF(OR(AD8="",$G8="",$H8=""),"",IF($H8-$G8=0,"",(AD8-$G8)/($H8-$G8))) | AK8: =IF(OR(AJ8="",$G8="",$H8=""),"",IF($H8-$G8=0,"",(AJ8-$G8)/($H8-$G8)))
C9: =IFERROR(IF(INDEX(ITT_ChildProtection_OC_A,MATCH("5",ITT_ChildProtection_OC_A,0))="","",INDEX(ITT_ChildProtection_OC_A,MATCH("5",ITT_ChildProtection_OC_A,0))),"") -> 5 | D9: =IFERROR(IF(INDEX(ITT_ChildProtection_OC_B,MATCH("5",ITT_ChildProtection_OC_A,0))="","",INDEX(ITT_ChildProtection_OC_B,MATCH("5",ITT_ChildProtection_OC_A,0))),"") | E9: =IFERROR(IF(INDEX(ITT_ChildProtection_OC_E,MATCH("5",ITT_ChildProtection_OC_A,0))="","",INDEX(ITT_ChildProtection_OC_E,MATCH("5",ITT_ChildProtection_OC_A,0))),"") | F9: =IFERROR(IF(INDEX(ITT_ChildProtection_OC_G,MATCH("5",ITT_ChildProtection_OC_A,0))="","",INDEX(ITT_ChildProtection_OC_G,MATCH("5",ITT_ChildProtection_OC_A,0))),"") | G9: =IFERROR(IF(INDEX(ITT_ChildProtection_OC_J,MATCH("5",ITT_ChildProtection_OC_A,0))="","",INDEX(ITT_ChildProtection_OC_J,MATCH("5",ITT_ChildProtection_OC_A,0))),"") | H9: =IFERROR(IF(INDEX(ITT_ChildProtection_OC_K,MATCH("5",ITT_ChildProtection_OC_A,0))="","",INDEX(ITT_ChildProtection_OC_K,MATCH("5",ITT_ChildProtection_OC_A,0))),"") | M9: =IF(OR(L9="",$G9="",$H9=""),"",IF($H9-$G9=0,"",(L9-$G9)/($H9-$G9))) | S9: =IF(OR(R9="",$G9="",$H9=""),"",IF($H9-$G9=0,"",(R9-$G9)/($H9-$G9))) | Y9: =IF(OR(X9="",$G9="",$H9=""),"",IF($H9-$G9=0,"",(X9-$G9)/($H9-$G9))) | AE9: =IF(OR(AD9="",$G9="",$H9=""),"",IF($H9-$G9=0,"",(AD9-$G9)/($H9-$G9))) | AK9: =IF(OR(AJ9="",$G9="",$H9=""),"",IF($H9-$G9=0,"",(AJ9-$G9)/($H9-$G9)))
B10: Output | C10: =IFERROR(IF(INDEX(ITT_ChildProtection_OP_A,MATCH("1.1",ITT_ChildProtection_OP_A,0))="","",INDEX(ITT_ChildProtection_OP_A,MATCH("1.1",ITT_ChildProtection_OP_A,0))),"") -> 1.1 | D10: =IFERROR(IF(INDEX(ITT_ChildProtection_OP_B,MATCH("1.1",ITT_ChildProtection_OP_A,0))="","",INDEX(ITT_ChildProtection_OP_B,MATCH("1.1",ITT_ChildProtection_OP_A,0))),"") | E10: =IFERROR(IF(INDEX(ITT_ChildProtection_OP_E,MATCH("1.1",ITT_ChildProtection_OP_A,0))="","",INDEX(ITT_ChildProtection_OP_E,MATCH("1.1",ITT_ChildProtection_OP_A,0))),"") | F10: =IFERROR(IF(INDEX(ITT_ChildProtection_OP_G,MATCH("1.1",ITT_ChildProtection_OP_A,0))="","",INDEX(ITT_ChildProtection_OP_G,MATCH("1.1",ITT_ChildProtection_OP_A,0))),"") | G10: =IFERROR(IF(INDEX(ITT_ChildProtection_OP_J,MATCH("1.1",ITT_ChildProtection_OP_A,0))="","",INDEX(ITT_ChildProtection_OP_J,MATCH("1.1",ITT_ChildProtection_OP_A,0))),"") | H10: =IFERROR(IF(INDEX(ITT_ChildProtection_OP_K,MATCH("1.1",ITT_ChildProtection_OP_A,0))="","",INDEX(ITT_ChildProtection_OP_K,MATCH("1.1",ITT_ChildProtection_OP_A,0))),"") | M10: =IF(OR(L10="",$G10="",$H10=""),"",IF($H10-$G10=0,"",(L10-$G10)/($H10-$G10))) | S10: =IF(OR(R10="",$G10="",$H10=""),"",IF($H10-$G10=0,"",(R10-$G10)/($H10-$G10))) | Y10: =IF(OR(X10="",$G10="",$H10=""),"",IF($H10-$G10=0,"",(X10-$G10)/($H10-$G10))) | AE10: =IF(OR(AD10="",$G10="",$H10=""),"",IF($H10-$G10=0,"",(AD10-$G10)/($H10-$G10))) | AK10: =IF(OR(AJ10="",$G10="",$H10=""),"",IF($H10-$G10=0,"",(AJ10-$G10)/($H10-$G10)))
C11: =IFERROR(IF(INDEX(ITT_ChildProtection_OP_A,MATCH("1.2",ITT_ChildProtection_OP_A,0))="","",INDEX(ITT_ChildProtection_OP_A,MATCH("1.2",ITT_ChildProtection_OP_A,0))),"") -> 1.2 | D11: =IFERROR(IF(INDEX(ITT_ChildProtection_OP_B,MATCH("1.2",ITT_ChildProtection_OP_A,0))="","",INDEX(ITT_ChildProtection_OP_B,MATCH("1.2",ITT_ChildProtection_OP_A,0))),"") | E11: =IFERROR(IF(INDEX(ITT_ChildProtection_OP_E,MATCH("1.2",ITT_ChildProtection_OP_A,0))="","",INDEX(ITT_ChildProtection_OP_E,MATCH("1.2",ITT_ChildProtection_OP_A,0))),"") | F11: =IFERROR(IF(INDEX(ITT_ChildProtection_OP_G,MATCH("1.2",ITT_ChildProtection_OP_A,0))="","",INDEX(ITT_ChildProtection_OP_G,MATCH("1.2",ITT_ChildProtection_OP_A,0))),"") | G11: =IFERROR(IF(INDEX(ITT_ChildProtection_OP_J,MATCH("1.2",ITT_ChildProtection_OP_A,0))="","",INDEX(ITT_ChildProtection_OP_J,MATCH("1.2",ITT_ChildProtection_OP_A,0))),"") | H11: =IFERROR(IF(INDEX(ITT_ChildProtection_OP_K,MATCH("1.2",ITT_ChildProtection_OP_A,0))="","",INDEX(ITT_ChildProtection_OP_K,MATCH("1.2",ITT_ChildProtection_OP_A,0))),"") | M11: =IF(OR(L11="",$G11="",$H11=""),"",IF($H11-$G11=0,"",(L11-$G11)/($H11-$G11))) | S11: =IF(OR(R11="",$G11="",$H11=""),"",IF($H11-$G11=0,"",(R11-$G11)/($H11-$G11))) | Y11: =IF(OR(X11="",$G11="",$H11=""),"",IF($H11-$G11=0,"",(X11-$G11)/($H11-$G11))) | AE11: =IF(OR(AD11="",$G11="",$H11=""),"",IF($H11-$G11=0,"",(AD11-$G11)/($H11-$G11))) | AK11: =IF(OR(AJ11="",$G11="",$H11=""),"",IF($H11-$G11=0,"",(AJ11-$G11)/($H11-$G11)))
C12: =IFERROR(IF(INDEX(ITT_ChildProtection_OP_A,MATCH("1.3",ITT_ChildProtection_OP_A,0))="","",INDEX(ITT_ChildProtection_OP_A,MATCH("1.3",ITT_ChildProtection_OP_A,0))),"") -> 1.3 | D12: =IFERROR(IF(INDEX(ITT_ChildProtection_OP_B,MATCH("1.3",ITT_ChildProtection_OP_A,0))="","",INDEX(ITT_ChildProtection_OP_B,MATCH("1.3",ITT_ChildProtection_OP_A,0))),"") | E12: =IFERROR(IF(INDEX(ITT_ChildProtection_OP_E,MATCH("1.3",ITT_ChildProtection_OP_A,0))="","",INDEX(ITT_ChildProtection_OP_E,MATCH("1.3",ITT_ChildProtection_OP_A,0))),"") | F12: =IFERROR(IF(INDEX(ITT_ChildProtection_OP_G,MATCH("1.3",ITT_ChildProtection_OP_A,0))="","",INDEX(ITT_ChildProtection_OP_G,MATCH("1.3",ITT_ChildProtection_OP_A,0))),"") | G12: =IFERROR(IF(INDEX(ITT_ChildProtection_OP_J,MATCH("1.3",ITT_ChildProtection_OP_A,0))="","",INDEX(ITT_ChildProtection_OP_J,MATCH("1.3",ITT_ChildProtection_OP_A,0))),"") | H12: =IFERROR(IF(INDEX(ITT_ChildProtection_OP_K,MATCH("1.3",ITT_ChildProtection_OP_A,0))="","",INDEX(ITT_ChildProtection_OP_K,MATCH("1.3",ITT_ChildProtection_OP_A,0))),"") | M12: =IF(OR(L12="",$G12="",$H12=""),"",IF($H12-$G12=0,"",(L12-$G12)/($H12-$G12))) | S12: =IF(OR(R12="",$G12="",$H12=""),"",IF($H12-$G12=0,"",(R12-$G12)/($H12-$G12))) | Y12: =IF(OR(X12="",$G12="",$H12=""),"",IF($H12-$G12=0,"",(X12-$G12)/($H12-$G12))) | AE12: =IF(OR(AD12="",$G12="",$H12=""),"",IF($H12-$G12=0,"",(AD12-$G12)/($H12-$G12))) | AK12: =IF(OR(AJ12="",$G12="",$H12=""),"",IF($H12-$G12=0,"",(AJ12-$G12)/($H12-$G12)))
C13: =IFERROR(IF(INDEX(ITT_ChildProtection_OP_A,MATCH("2.1",ITT_ChildProtection_OP_A,0))="","",INDEX(ITT_ChildProtection_OP_A,MATCH("2.1",ITT_ChildProtection_OP_A,0))),"") -> 2.1 | D13: =IFERROR(IF(INDEX(ITT_ChildProtection_OP_B,MATCH("2.1",ITT_ChildProtection_OP_A,0))="","",INDEX(ITT_ChildProtection_OP_B,MATCH("2.1",ITT_ChildProtection_OP_A,0))),"") | E13: =IFERROR(IF(INDEX(ITT_ChildProtection_OP_E,MATCH("2.1",ITT_ChildProtection_OP_A,0))="","",INDEX(ITT_ChildProtection_OP_E,MATCH("2.1",ITT_ChildProtection_OP_A,0))),"") | F13: =IFERROR(IF(INDEX(ITT_ChildProtection_OP_G,MATCH("2.1",ITT_ChildProtection_OP_A,0))="","",INDEX(ITT_ChildProtection_OP_G,MATCH("2.1",ITT_ChildProtection_OP_A,0))),"") | G13: =IFERROR(IF(INDEX(ITT_ChildProtection_OP_J,MATCH("2.1",ITT_ChildProtection_OP_A,0))="","",INDEX(ITT_ChildProtection_OP_J,MATCH("2.1",ITT_ChildProtection_OP_A,0))),"") | H13: =IFERROR(IF(INDEX(ITT_ChildProtection_OP_K,MATCH("2.1",ITT_ChildProtection_OP_A,0))="","",INDEX(ITT_ChildProtection_OP_K,MATCH("2.1",ITT_ChildProtection_OP_A,0))),"") | M13: =IF(OR(L13="",$G13="",$H13=""),"",IF($H13-$G13=0,"",(L13-$G13)/($H13-$G13))) | S13: =IF(OR(R13="",$G13="",$H13=""),"",IF($H13-$G13=0,"",(R13-$G13)/($H13-$G13))) | Y13: =IF(OR(X13="",$G13="",$H13=""),"",IF($H13-$G13=0,"",(X13-$G13)/($H13-$G13))) | AE13: =IF(OR(AD13="",$G13="",$H13=""),"",IF($H13-$G13=0,"",(AD13-$G13)/($H13-$G13))) | AK13: =IF(OR(AJ13="",$G13="",$H13=""),"",IF($H13-$G13=0,"",(AJ13-$G13)/($H13-$G13)))
C14: =IFERROR(IF(INDEX(ITT_ChildProtection_OP_A,MATCH("2.2",ITT_ChildProtection_OP_A,0))="","",INDEX(ITT_ChildProtection_OP_A,MATCH("2.2",ITT_ChildProtection_OP_A,0))),"") -> 2.2 | D14: =IFERROR(IF(INDEX(ITT_ChildProtection_OP_B,MATCH("2.2",ITT_ChildProtection_OP_A,0))="","",INDEX(ITT_ChildProtection_OP_B,MATCH("2.2",ITT_ChildProtection_OP_A,0))),"") | E14: =IFERROR(IF(INDEX(ITT_ChildProtection_OP_E,MATCH("2.2",ITT_ChildProtection_OP_A,0))="","",INDEX(ITT_ChildProtection_OP_E,MATCH("2.2",ITT_ChildProtection_OP_A,0))),"") | F14: =IFERROR(IF(INDEX(ITT_ChildProtection_OP_G,MATCH("2.2",ITT_ChildProtection_OP_A,0))="","",INDEX(ITT_ChildProtection_OP_G,MATCH("2.2",ITT_ChildProtection_OP_A,0))),"") | G14: =IFERROR(IF(INDEX(ITT_ChildProtection_OP_J,MATCH("2.2",ITT_ChildProtection_OP_A,0))="","",INDEX(ITT_ChildProtection_OP_J,MATCH("2.2",ITT_ChildProtection_OP_A,0))),"") | H14: =IFERROR(IF(INDEX(ITT_ChildProtection_OP_K,MATCH("2.2",ITT_ChildProtection_OP_A,0))="","",INDEX(ITT_ChildProtection_OP_K,MATCH("2.2",ITT_ChildProtection_OP_A,0))),"") | M14: =IF(OR(L14="",$G14="",$H14=""),"",IF($H14-$G14=0,"",(L14-$G14)/($H14-$G14))) | S14: =IF(OR(R14="",$G14="",$H14=""),"",IF($H14-$G14=0,"",(R14-$G14)/($H14-$G14))) | Y14: =IF(OR(X14="",$G14="",$H14=""),"",IF($H14-$G14=0,"",(X14-$G14)/($H14-$G14))) | AE14: =IF(OR(AD14="",$G14="",$H14=""),"",IF($H14-$G14=0,"",(AD14-$G14)/($H14-$G14))) | AK14: =IF(OR(AJ14="",$G14="",$H14=""),"",IF($H14-$G14=0,"",(AJ14-$G14)/($H14-$G14)))
C15: =IFERROR(IF(INDEX(ITT_ChildProtection_OP_A,MATCH("2.3",ITT_ChildProtection_OP_A,0))="","",INDEX(ITT_ChildProtection_OP_A,MATCH("2.3",ITT_ChildProtection_OP_A,0))),"") -> 2.3 | D15: =IFERROR(IF(INDEX(ITT_ChildProtection_OP_B,MATCH("2.3",ITT_ChildProtection_OP_A,0))="","",INDEX(ITT_ChildProtection_OP_B,MATCH("2.3",ITT_ChildProtection_OP_A,0))),"") | E15: =IFERROR(IF(INDEX(ITT_ChildProtection_OP_E,MATCH("2.3",ITT_ChildProtection_OP_A,0))="","",INDEX(ITT_ChildProtection_OP_E,MATCH("2.3",ITT_ChildProtection_OP_A,0))),"") | F15: =IFERROR(IF(INDEX(ITT_ChildProtection_OP_G,MATCH("2.3",ITT_ChildProtection_OP_A,0))="","",INDEX(ITT_ChildProtection_OP_G,MATCH("2.3",ITT_ChildProtection_OP_A,0))),"") | G15: =IFERROR(IF(INDEX(ITT_ChildProtection_OP_J,MATCH("2.3",ITT_ChildProtection_OP_A,0))="","",INDEX(ITT_ChildProtection_OP_J,MATCH("2.3",ITT_ChildProtection_OP_A,0))),"") | H15: =IFERROR(IF(INDEX(ITT_ChildProtection_OP_K,MATCH("2.3",ITT_ChildProtection_OP_A,0))="","",INDEX(ITT_ChildProtection_OP_K,MATCH("2.3",ITT_ChildProtection_OP_A,0))),"") | M15: =IF(OR(L15="",$G15="",$H15=""),"",IF($H15-$G15=0,"",(L15-$G15)/($H15-$G15))) | S15: =IF(OR(R15="",$G15="",$H15=""),"",IF($H15-$G15=0,"",(R15-$G15)/($H15-$G15))) | Y15: =IF(OR(X15="",$G15="",$H15=""),"",IF($H15-$G15=0,"",(X15-$G15)/($H15-$G15))) | AE15: =IF(OR(AD15="",$G15="",$H15=""),"",IF($H15-$G15=0,"",(AD15-$G15)/($H15-$G15))) | AK15: =IF(OR(AJ15="",$G15="",$H15=""),"",IF($H15-$G15=0,"",(AJ15-$G15)/($H15-$G15)))
C16: =IFERROR(IF(INDEX(ITT_ChildProtection_OP_A,MATCH("3.1",ITT_ChildProtection_OP_A,0))="","",INDEX(ITT_ChildProtection_OP_A,MATCH("3.1",ITT_ChildProtection_OP_A,0))),"") -> 3.1 | D16: =IFERROR(IF(INDEX(ITT_ChildProtection_OP_B,MATCH("3.1",ITT_ChildProtection_OP_A,0))="","",INDEX(ITT_ChildProtection_OP_B,MATCH("3.1",ITT_ChildProtection_OP_A,0))),"") | E16: =IFERROR(IF(INDEX(ITT_ChildProtection_OP_E,MATCH("3.1",ITT_ChildProtection_OP_A,0))="","",INDEX(ITT_ChildProtection_OP_E,MATCH("3.1",ITT_ChildProtection_OP_A,0))),"") | F16: =IFERROR(IF(INDEX(ITT_ChildProtection_OP_G,MATCH("3.1",ITT_ChildProtection_OP_A,0))="","",INDEX(ITT_ChildProtection_OP_G,MATCH("3.1",ITT_ChildProtection_OP_A,0))),"") | G16: =IFERROR(IF(INDEX(ITT_ChildProtection_OP_J,MATCH("3.1",ITT_ChildProtection_OP_A,0))="","",INDEX(ITT_ChildProtection_OP_J,MATCH("3.1",ITT_ChildProtection_OP_A,0))),"") | H16: =IFERROR(IF(INDEX(ITT_ChildProtection_OP_K,MATCH("3.1",ITT_ChildProtection_OP_A,0))="","",INDEX(ITT_ChildProtection_OP_K,MATCH("3.1",ITT_ChildProtection_OP_A,0))),"") | M16: =IF(OR(L16="",$G16="",$H16=""),"",IF($H16-$G16=0,"",(L16-$G16)/($H16-$G16))) | S16: =IF(OR(R16="",$G16="",$H16=""),"",IF($H16-$G16=0,"",(R16-$G16)/($H16-$G16))) | Y16: =IF(OR(X16="",$G16="",$H16=""),"",IF($H16-$G16=0,"",(X16-$G16)/($H16-$G16))) | AE16: =IF(OR(AD16="",$G16="",$H16=""),"",IF($H16-$G16=0,"",(AD16-$G16)/($H16-$G16))) | AK16: =IF(OR(AJ16="",$G16="",$H16=""),"",IF($H16-$G16=0,"",(AJ16-$G16)/($H16-$G16)))
C17: =IFERROR(IF(INDEX(ITT_ChildProtection_OP_A,MATCH("3.2",ITT_ChildProtection_OP_A,0))="","",INDEX(ITT_ChildProtection_OP_A,MATCH("3.2",ITT_ChildProtection_OP_A,0))),"") -> 3.2 | D17: =IFERROR(IF(INDEX(ITT_ChildProtection_OP_B,MATCH("3.2",ITT_ChildProtection_OP_A,0))="","",INDEX(ITT_ChildProtection_OP_B,MATCH("3.2",ITT_ChildProtection_OP_A,0))),"") | E17: =IFERROR(IF(INDEX(ITT_ChildProtection_OP_E,MATCH("3.2",ITT_ChildProtection_OP_A,0))="","",INDEX(ITT_ChildProtection_OP_E,MATCH("3.2",ITT_ChildProtection_OP_A,0))),"") | F17: =IFERROR(IF(INDEX(ITT_ChildProtection_OP_G,MATCH("3.2",ITT_ChildProtection_OP_A,0))="","",INDEX(ITT_ChildProtection_OP_G,MATCH("3.2",ITT_ChildProtection_OP_A,0))),"") | G17: =IFERROR(IF(INDEX(ITT_ChildProtection_OP_J,MATCH("3.2",ITT_ChildProtection_OP_A,0))="","",INDEX(ITT_ChildProtection_OP_J,MATCH("3.2",ITT_ChildProtection_OP_A,0))),"") | H17: =IFERROR(IF(INDEX(ITT_ChildProtection_OP_K,MATCH("3.2",ITT_ChildProtection_OP_A,0))="","",INDEX(ITT_ChildProtection_OP_K,MATCH("3.2",ITT_ChildProtection_OP_A,0))),"") | M17: =IF(OR(L17="",$G17="",$H17=""),"",IF($H17-$G17=0,"",(L17-$G17)/($H17-$G17))) | S17: =IF(OR(R17="",$G17="",$H17=""),"",IF($H17-$G17=0,"",(R17-$G17)/($H17-$G17))) | Y17: =IF(OR(X17="",$G17="",$H17=""),"",IF($H17-$G17=0,"",(X17-$G17)/($H17-$G17))) | AE17: =IF(OR(AD17="",$G17="",$H17=""),"",IF($H17-$G17=0,"",(AD17-$G17)/($H17-$G17))) | AK17: =IF(OR(AJ17="",$G17="",$H17=""),"",IF($H17-$G17=0,"",(AJ17-$G17)/($H17-$G17)))
C18: =IFERROR(IF(INDEX(ITT_ChildProtection_OP_A,MATCH("3.3",ITT_ChildProtection_OP_A,0))="","",INDEX(ITT_ChildProtection_OP_A,MATCH("3.3",ITT_ChildProtection_OP_A,0))),"") -> 3.3 | D18: =IFERROR(IF(INDEX(ITT_ChildProtection_OP_B,MATCH("3.3",ITT_ChildProtection_OP_A,0))="","",INDEX(ITT_ChildProtection_OP_B,MATCH("3.3",ITT_ChildProtection_OP_A,0))),"") | E18: =IFERROR(IF(INDEX(ITT_ChildProtection_OP_E,MATCH("3.3",ITT_ChildProtection_OP_A,0))="","",INDEX(ITT_ChildProtection_OP_E,MATCH("3.3",ITT_ChildProtection_OP_A,0))),"") | F18: =IFERROR(IF(INDEX(ITT_ChildProtection_OP_G,MATCH("3.3",ITT_ChildProtection_OP_A,0))="","",INDEX(ITT_ChildProtection_OP_G,MATCH("3.3",ITT_ChildProtection_OP_A,0))),"") | G18: =IFERROR(IF(INDEX(ITT_ChildProtection_OP_J,MATCH("3.3",ITT_ChildProtection_OP_A,0))="","",INDEX(ITT_ChildProtection_OP_J,MATCH("3.3",ITT_ChildProtection_OP_A,0))),"") | H18: =IFERROR(IF(INDEX(ITT_ChildProtection_OP_K,MATCH("3.3",ITT_ChildProtection_OP_A,0))="","",INDEX(ITT_ChildProtection_OP_K,MATCH("3.3",ITT_ChildProtection_OP_A,0))),"") | M18: =IF(OR(L18="",$G18="",$H18=""),"",IF($H18-$G18=0,"",(L18-$G18)/($H18-$G18))) | S18: =IF(OR(R18="",$G18="",$H18=""),"",IF($H18-$G18=0,"",(R18-$G18)/($H18-$G18))) | Y18: =IF(OR(X18="",$G18="",$H18=""),"",IF($H18-$G18=0,"",(X18-$G18)/($H18-$G18))) | AE18: =IF(OR(AD18="",$G18="",$H18=""),"",IF($H18-$G18=0,"",(AD18-$G18)/($H18-$G18))) | AK18: =IF(OR(AJ18="",$G18="",$H18=""),"",IF($H18-$G18=0,"",(AJ18-$G18)/($H18-$G18)))
C19: =IFERROR(IF(INDEX(ITT_ChildProtection_OP_A,MATCH("4.1",ITT_ChildProtection_OP_A,0))="","",INDEX(ITT_ChildProtection_OP_A,MATCH("4.1",ITT_ChildProtection_OP_A,0))),"") -> 4.1 | D19: =IFERROR(IF(INDEX(ITT_ChildProtection_OP_B,MATCH("4.1",ITT_ChildProtection_OP_A,0))="","",INDEX(ITT_ChildProtection_OP_B,MATCH("4.1",ITT_ChildProtection_OP_A,0))),"") | E19: =IFERROR(IF(INDEX(ITT_ChildProtection_OP_E,MATCH("4.1",ITT_ChildProtection_OP_A,0))="","",INDEX(ITT_ChildProtection_OP_E,MATCH("4.1",ITT_ChildProtection_OP_A,0))),"") | F19: =IFERROR(IF(INDEX(ITT_ChildProtection_OP_G,MATCH("4.1",ITT_ChildProtection_OP_A,0))="","",INDEX(ITT_ChildProtection_OP_G,MATCH("4.1",ITT_ChildProtection_OP_A,0))),"") | G19: =IFERROR(IF(INDEX(ITT_ChildProtection_OP_J,MATCH("4.1",ITT_ChildProtection_OP_A,0))="","",INDEX(ITT_ChildProtection_OP_J,MATCH("4.1",ITT_ChildProtection_OP_A,0))),"") | H19: =IFERROR(IF(INDEX(ITT_ChildProtection_OP_K,MATCH("4.1",ITT_ChildProtection_OP_A,0))="","",INDEX(ITT_ChildProtection_OP_K,MATCH("4.1",ITT_ChildProtection_OP_A,0))),"") | M19: =IF(OR(L19="",$G19="",$H19=""),"",IF($H19-$G19=0,"",(L19-$G19)/($H19-$G19))) | S19: =IF(OR(R19="",$G19="",$H19=""),"",IF($H19-$G19=0,"",(R19-$G19)/($H19-$G19))) | Y19: =IF(OR(X19="",$G19="",$H19=""),"",IF($H19-$G19=0,"",(X19-$G19)/($H19-$G19))) | AE19: =IF(OR(AD19="",$G19="",$H19=""),"",IF($H19-$G19=0,"",(AD19-$G19)/($H19-$G19))) | AK19: =IF(OR(AJ19="",$G19="",$H19=""),"",IF($H19-$G19=0,"",(AJ19-$G19)/($H19-$G19)))
C20: =IFERROR(IF(INDEX(ITT_ChildProtection_OP_A,MATCH("4.2",ITT_ChildProtection_OP_A,0))="","",INDEX(ITT_ChildProtection_OP_A,MATCH("4.2",ITT_ChildProtection_OP_A,0))),"") -> 4.2 | D20: =IFERROR(IF(INDEX(ITT_ChildProtection_OP_B,MATCH("4.2",ITT_ChildProtection_OP_A,0))="","",INDEX(ITT_ChildProtection_OP_B,MATCH("4.2",ITT_ChildProtection_OP_A,0))),"") | E20: =IFERROR(IF(INDEX(ITT_ChildProtection_OP_E,MATCH("4.2",ITT_ChildProtection_OP_A,0))="","",INDEX(ITT_ChildProtection_OP_E,MATCH("4.2",ITT_ChildProtection_OP_A,0))),"") | F20: =IFERROR(IF(INDEX(ITT_ChildProtection_OP_G,MATCH("4.2",ITT_ChildProtection_OP_A,0))="","",INDEX(ITT_ChildProtection_OP_G,MATCH("4.2",ITT_ChildProtection_OP_A,0))),"") | G20: =IFERROR(IF(INDEX(ITT_ChildProtection_OP_J,MATCH("4.2",ITT_ChildProtection_OP_A,0))="","",INDEX(ITT_ChildProtection_OP_J,MATCH("4.2",ITT_ChildProtection_OP_A,0))),"") | H20: =IFERROR(IF(INDEX(ITT_ChildProtection_OP_K,MATCH("4.2",ITT_ChildProtection_OP_A,0))="","",INDEX(ITT_ChildProtection_OP_K,MATCH("4.2",ITT_ChildProtection_OP_A,0))),"") | M20: =IF(OR(L20="",$G20="",$H20=""),"",IF($H20-$G20=0,"",(L20-$G20)/($H20-$G20))) | S20: =IF(OR(R20="",$G20="",$H20=""),"",IF($H20-$G20=0,"",(R20-$G20)/($H20-$G20))) | Y20: =IF(OR(X20="",$G20="",$H20=""),"",IF($H20-$G20=0,"",(X20-$G20)/($H20-$G20))) | AE20: =IF(OR(AD20="",$G20="",$H20=""),"",IF($H20-$G20=0,"",(AD20-$G20)/($H20-$G20))) | AK20: =IF(OR(AJ20="",$G20="",$H20=""),"",IF($H20-$G20=0,"",(AJ20-$G20)/($H20-$G20)))
C21: =IFERROR(IF(INDEX(ITT_ChildProtection_OP_A,MATCH("4.3",ITT_ChildProtection_OP_A,0))="","",INDEX(ITT_ChildProtection_OP_A,MATCH("4.3",ITT_ChildProtection_OP_A,0))),"") -> 4.3 | D21: =IFERROR(IF(INDEX(ITT_ChildProtection_OP_B,MATCH("4.3",ITT_ChildProtection_OP_A,0))="","",INDEX(ITT_ChildProtection_OP_B,MATCH("4.3",ITT_ChildProtection_OP_A,0))),"") | E21: =IFERROR(IF(INDEX(ITT_ChildProtection_OP_E,MATCH("4.3",ITT_ChildProtection_OP_A,0))="","",INDEX(ITT_ChildProtection_OP_E,MATCH("4.3",ITT_ChildProtection_OP_A,0))),"") | F21: =IFERROR(IF(INDEX(ITT_ChildProtection_OP_G,MATCH("4.3",ITT_ChildProtection_OP_A,0))="","",INDEX(ITT_ChildProtection_OP_G,MATCH("4.3",ITT_ChildProtection_OP_A,0))),"") | G21: =IFERROR(IF(INDEX(ITT_ChildProtection_OP_J,MATCH("4.3",ITT_ChildProtection_OP_A,0))="","",INDEX(ITT_ChildProtection_OP_J,MATCH("4.3",ITT_ChildProtection_OP_A,0))),"") | H21: =IFERROR(IF(INDEX(ITT_ChildProtection_OP_K,MATCH("4.3",ITT_ChildProtection_OP_A,0))="","",INDEX(ITT_ChildProtection_OP_K,MATCH("4.3",ITT_ChildProtection_OP_A,0))),"") | M21: =IF(OR(L21="",$G21="",$H21=""),"",IF($H21-$G21=0,"",(L21-$G21)/($H21-$G21))) | S21: =IF(OR(R21="",$G21="",$H21=""),"",IF($H21-$G21=0,"",(R21-$G21)/($H21-$G21))) | Y21: =IF(OR(X21="",$G21="",$H21=""),"",IF($H21-$G21=0,"",(X21-$G21)/($H21-$G21))) | AE21: =IF(OR(AD21="",$G21="",$H21=""),"",IF($H21-$G21=0,"",(AD21-$G21)/($H21-$G21))) | AK21: =IF(OR(AJ21="",$G21="",$H21=""),"",IF($H21-$G21=0,"",(AJ21-$G21)/($H21-$G21)))
C22: =IFERROR(IF(INDEX(ITT_ChildProtection_OP_A,MATCH("5.1",ITT_ChildProtection_OP_A,0))="","",INDEX(ITT_ChildProtection_OP_A,MATCH("5.1",ITT_ChildProtection_OP_A,0))),"") -> 5.1 | D22: =IFERROR(IF(INDEX(ITT_ChildProtection_OP_B,MATCH("5.1",ITT_ChildProtection_OP_A,0))="","",INDEX(ITT_ChildProtection_OP_B,MATCH("5.1",ITT_ChildProtection_OP_A,0))),"") | E22: =IFERROR(IF(INDEX(ITT_ChildProtection_OP_E,MATCH("5.1",ITT_ChildProtection_OP_A,0))="","",INDEX(ITT_ChildProtection_OP_E,MATCH("5.1",ITT_ChildProtection_OP_A,0))),"") | F22: =IFERROR(IF(INDEX(ITT_ChildProtection_OP_G,MATCH("5.1",ITT_ChildProtection_OP_A,0))="","",INDEX(ITT_ChildProtection_OP_G,MATCH("5.1",ITT_ChildProtection_OP_A,0))),"") | G22: =IFERROR(IF(INDEX(ITT_ChildProtection_OP_J,MATCH("5.1",ITT_ChildProtection_OP_A,0))="","",INDEX(ITT_ChildProtection_OP_J,MATCH("5.1",ITT_ChildProtection_OP_A,0))),"") | H22: =IFERROR(IF(INDEX(ITT_ChildProtection_OP_K,MATCH("5.1",ITT_ChildProtection_OP_A,0))="","",INDEX(ITT_ChildProtection_OP_K,MATCH("5.1",ITT_ChildProtection_OP_A,0))),"") | M22: =IF(OR(L22="",$G22="",$H22=""),"",IF($H22-$G22=0,"",(L22-$G22)/($H22-$G22))) | S22: =IF(OR(R22="",$G22="",$H22=""),"",IF($H22-$G22=0,"",(R22-$G22)/($H22-$G22))) | Y22: =IF(OR(X22="",$G22="",$H22=""),"",IF($H22-$G22=0,"",(X22-$G22)/($H22-$G22))) | AE22: =IF(OR(AD22="",$G22="",$H22=""),"",IF($H22-$G22=0,"",(AD22-$G22)/($H22-$G22))) | AK22: =IF(OR(AJ22="",$G22="",$H22=""),"",IF($H22-$G22=0,"",(AJ22-$G22)/($H22-$G22)))
C23: =IFERROR(IF(INDEX(ITT_ChildProtection_OP_A,MATCH("5.2",ITT_ChildProtection_OP_A,0))="","",INDEX(ITT_ChildProtection_OP_A,MATCH("5.2",ITT_ChildProtection_OP_A,0))),"") -> 5.2 | D23: =IFERROR(IF(INDEX(ITT_ChildProtection_OP_B,MATCH("5.2",ITT_ChildProtection_OP_A,0))="","",INDEX(ITT_ChildProtection_OP_B,MATCH("5.2",ITT_ChildProtection_OP_A,0))),"") | E23: =IFERROR(IF(INDEX(ITT_ChildProtection_OP_E,MATCH("5.2",ITT_ChildProtection_OP_A,0))="","",INDEX(ITT_ChildProtection_OP_E,MATCH("5.2",ITT_ChildProtection_OP_A,0))),"") | F23: =IFERROR(IF(INDEX(ITT_ChildProtection_OP_G,MATCH("5.2",ITT_ChildProtection_OP_A,0))="","",INDEX(ITT_ChildProtection_OP_G,MATCH("5.2",ITT_ChildProtection_OP_A,0))),"") | G23: =IFERROR(IF(INDEX(ITT_ChildProtection_OP_J,MATCH("5.2",ITT_ChildProtection_OP_A,0))="","",INDEX(ITT_ChildProtection_OP_J,MATCH("5.2",ITT_ChildProtection_OP_A,0))),"") | H23: =IFERROR(IF(INDEX(ITT_ChildProtection_OP_K,MATCH("5.2",ITT_ChildProtection_OP_A,0))="","",INDEX(ITT_ChildProtection_OP_K,MATCH("5.2",ITT_ChildProtection_OP_A,0))),"") | M23: =IF(OR(L23="",$G23="",$H23=""),"",IF($H23-$G23=0,"",(L23-$G23)/($H23-$G23))) | S23: =IF(OR(R23="",$G23="",$H23=""),"",IF($H23-$G23=0,"",(R23-$G23)/($H23-$G23))) | Y23: =IF(OR(X23="",$G23="",$H23=""),"",IF($H23-$G23=0,"",(X23-$G23)/($H23-$G23))) | AE23: =IF(OR(AD23="",$G23="",$H23=""),"",IF($H23-$G23=0,"",(AD23-$G23)/($H23-$G23))) | AK23: =IF(OR(AJ23="",$G23="",$H23=""),"",IF($H23-$G23=0,"",(AJ23-$G23)/($H23-$G23)))
C24: =IFERROR(IF(INDEX(ITT_ChildProtection_OP_A,MATCH("5.3",ITT_ChildProtection_OP_A,0))="","",INDEX(ITT_ChildProtection_OP_A,MATCH("5.3",ITT_ChildProtection_OP_A,0))),"") -> 5.3 | D24: =IFERROR(IF(INDEX(ITT_ChildProtection_OP_B,MATCH("5.3",ITT_ChildProtection_OP_A,0))="","",INDEX(ITT_ChildProtection_OP_B,MATCH("5.3",ITT_ChildProtection_OP_A,0))),"") | E24: =IFERROR(IF(INDEX(ITT_ChildProtection_OP_E,MATCH("5.3",ITT_ChildProtection_OP_A,0))="","",INDEX(ITT_ChildProtection_OP_E,MATCH("5.3",ITT_ChildProtection_OP_A,0))),"") | F24: =IFERROR(IF(INDEX(ITT_ChildProtection_OP_G,MATCH("5.3",ITT_ChildProtection_OP_A,0))="","",INDEX(ITT_ChildProtection_OP_G,MATCH("5.3",ITT_ChildProtection_OP_A,0))),"") | G24: =IFERROR(IF(INDEX(ITT_ChildProtection_OP_J,MATCH("5.3",ITT_ChildProtection_OP_A,0))="","",INDEX(ITT_ChildProtection_OP_J,MATCH("5.3",ITT_ChildProtection_OP_A,0))),"") | H24: =IFERROR(IF(INDEX(ITT_ChildProtection_OP_K,MATCH("5.3",ITT_ChildProtection_OP_A,0))="","",INDEX(ITT_ChildProtection_OP_K,MATCH("5.3",ITT_ChildProtection_OP_A,0))),"") | M24: =IF(OR(L24="",$G24="",$H24=""),"",IF($H24-$G24=0,"",(L24-$G24)/($H24-$G24))) | S24: =IF(OR(R24="",$G24="",$H24=""),"",IF($H24-$G24=0,"",(R24-$G24)/($H24-$G24))) | Y24: =IF(OR(X24="",$G24="",$H24=""),"",IF($H24-$G24=0,"",(X24-$G24)/($H24-$G24))) | AE24: =IF(OR(AD24="",$G24="",$H24=""),"",IF($H24-$G24=0,"",(AD24-$G24)/($H24-$G24))) | AK24: =IF(OR(AJ24="",$G24="",$H24=""),"",IF($H24-$G24=0,"",(AJ24-$G24)/($H24-$G24)))
A25: Education | B25: Outcome | C25: =IFERROR(IF(INDEX(ITT_Education_OC_A,MATCH("1",ITT_Education_OC_A,0))="","",INDEX(ITT_Education_OC_A,MATCH("1",ITT_Education_OC_A,0))),"") -> 1 | D25: =IFERROR(IF(INDEX(ITT_Education_OC_B,MATCH("1",ITT_Education_OC_A,0))="","",INDEX(ITT_Education_OC_B,MATCH("1",ITT_Education_OC_A,0))),"") | E25: =IFERROR(IF(INDEX(ITT_Education_OC_E,MATCH("1",ITT_Education_OC_A,0))="","",INDEX(ITT_Education_OC_E,MATCH("1",ITT_Education_OC_A,0))),"") | F25: =IFERROR(IF(INDEX(ITT_Education_OC_G,MATCH("1",ITT_Education_OC_A,0))="","",INDEX(ITT_Education_OC_G,MATCH("1",ITT_Education_OC_A,0))),"") | G25: =IFERROR(IF(INDEX(ITT_Education_OC_J,MATCH("1",ITT_Education_OC_A,0))="","",INDEX(ITT_Education_OC_J,MATCH("1",ITT_Education_OC_A,0))),"") | H25: =IFERROR(IF(INDEX(ITT_Education_OC_K,MATCH("1",ITT_Education_OC_A,0))="","",INDEX(ITT_Education_OC_K,MATCH("1",ITT_Education_OC_A,0))),"") | M25: =IF(OR(L25="",$G25="",$H25=""),"",IF($H25-$G25=0,"",(L25-$G25)/($H25-$G25))) | S25: =IF(OR(R25="",$G25="",$H25=""),"",IF($H25-$G25=0,"",(R25-$G25)/($H25-$G25))) | Y25: =IF(OR(X25="",$G25="",$H25=""),"",IF($H25-$G25=0,"",(X25-$G25)/($H25-$G25))) | AE25: =IF(OR(AD25="",$G25="",$H25=""),"",IF($H25-$G25=0,"",(AD25-$G25)/($H25-$G25))) | AK25: =IF(OR(AJ25="",$G25="",$H25=""),"",IF($H25-$G25=0,"",(AJ25-$G25)/($H25-$G25)))
C26: =IFERROR(IF(INDEX(ITT_Education_OC_A,MATCH("2",ITT_Education_OC_A,0))="","",INDEX(ITT_Education_OC_A,MATCH("2",ITT_Education_OC_A,0))),"") -> 2 | D26: =IFERROR(IF(INDEX(ITT_Education_OC_B,MATCH("2",ITT_Education_OC_A,0))="","",INDEX(ITT_Education_OC_B,MATCH("2",ITT_Education_OC_A,0))),"") | E26: =IFERROR(IF(INDEX(ITT_Education_OC_E,MATCH("2",ITT_Education_OC_A,0))="","",INDEX(ITT_Education_OC_E,MATCH("2",ITT_Education_OC_A,0))),"") | F26: =IFERROR(IF(INDEX(ITT_Education_OC_G,MATCH("2",ITT_Education_OC_A,0))="","",INDEX(ITT_Education_OC_G,MATCH("2",ITT_Education_OC_A,0))),"") | G26: =IFERROR(IF(INDEX(ITT_Education_OC_J,MATCH("2",ITT_Education_OC_A,0))="","",INDEX(ITT_Education_OC_J,MATCH("2",ITT_Education_OC_A,0))),"") | H26: =IFERROR(IF(INDEX(ITT_Education_OC_K,MATCH("2",ITT_Education_OC_A,0))="","",INDEX(ITT_Education_OC_K,MATCH("2",ITT_Education_OC_A,0))),"") | M26: =IF(OR(L26="",$G26="",$H26=""),"",IF($H26-$G26=0,"",(L26-$G26)/($H26-$G26))) | S26: =IF(OR(R26="",$G26="",$H26=""),"",IF($H26-$G26=0,"",(R26-$G26)/($H26-$G26))) | Y26: =IF(OR(X26="",$G26="",$H26=""),"",IF($H26-$G26=0,"",(X26-$G26)/($H26-$G26))) | AE26: =IF(OR(AD26="",$G26="",$H26=""),"",IF($H26-$G26=0,"",(AD26-$G26)/($H26-$G26))) | AK26: =IF(OR(AJ26="",$G26="",$H26=""),"",IF($H26-$G26=0,"",(AJ26-$G26)/($H26-$G26)))
C27: =IFERROR(IF(INDEX(ITT_Education_OC_A,MATCH("3",ITT_Education_OC_A,0))="","",INDEX(ITT_Education_OC_A,MATCH("3",ITT_Education_OC_A,0))),"") -> 3 | D27: =IFERROR(IF(INDEX(ITT_Education_OC_B,MATCH("3",ITT_Education_OC_A,0))="","",INDEX(ITT_Education_OC_B,MATCH("3",ITT_Education_OC_A,0))),"") | E27: =IFERROR(IF(INDEX(ITT_Education_OC_E,MATCH("3",ITT_Education_OC_A,0))="","",INDEX(ITT_Education_OC_E,MATCH("3",ITT_Education_OC_A,0))),"") | F27: =IFERROR(IF(INDEX(ITT_Education_OC_G,MATCH("3",ITT_Education_OC_A,0))="","",INDEX(ITT_Education_OC_G,MATCH("3",ITT_Education_OC_A,0))),"") | G27: =IFERROR(IF(INDEX(ITT_Education_OC_J,MATCH("3",ITT_Education_OC_A,0))="","",INDEX(ITT_Education_OC_J,MATCH("3",ITT_Education_OC_A,0))),"") | H27: =IFERROR(IF(INDEX(ITT_Education_OC_K,MATCH("3",ITT_Education_OC_A,0))="","",INDEX(ITT_Education_OC_K,MATCH("3",ITT_Education_OC_A,0))),"") | M27: =IF(OR(L27="",$G27="",$H27=""),"",IF($H27-$G27=0,"",(L27-$G27)/($H27-$G27))) | S27: =IF(OR(R27="",$G27="",$H27=""),"",IF($H27-$G27=0,"",(R27-$G27)/($H27-$G27))) | Y27: =IF(OR(X27="",$G27="",$H27=""),"",IF($H27-$G27=0,"",(X27-$G27)/($H27-$G27))) | AE27: =IF(OR(AD27="",$G27="",$H27=""),"",IF($H27-$G27=0,"",(AD27-$G27)/($H27-$G27))) | AK27: =IF(OR(AJ27="",$G27="",$H27=""),"",IF($H27-$G27=0,"",(AJ27-$G27)/($H27-$G27)))
C28: =IFERROR(IF(INDEX(ITT_Education_OC_A,MATCH("4",ITT_Education_OC_A,0))="","",INDEX(ITT_Education_OC_A,MATCH("4",ITT_Education_OC_A,0))),"") -> 4 | D28: =IFERROR(IF(INDEX(ITT_Education_OC_B,MATCH("4",ITT_Education_OC_A,0))="","",INDEX(ITT_Education_OC_B,MATCH("4",ITT_Education_OC_A,0))),"") | E28: =IFERROR(IF(INDEX(ITT_Education_OC_E,MATCH("4",ITT_Education_OC_A,0))="","",INDEX(ITT_Education_OC_E,MATCH("4",ITT_Education_OC_A,0))),"") | F28: =IFERROR(IF(INDEX(ITT_Education_OC_G,MATCH("4",ITT_Education_OC_A,0))="","",INDEX(ITT_Education_OC_G,MATCH("4",ITT_Education_OC_A,0))),"") | G28: =IFERROR(IF(INDEX(ITT_Education_OC_J,MATCH("4",ITT_Education_OC_A,0))="","",INDEX(ITT_Education_OC_J,MATCH("4",ITT_Education_OC_A,0))),"") | H28: =IFERROR(IF(INDEX(ITT_Education_OC_K,MATCH("4",ITT_Education_OC_A,0))="","",INDEX(ITT_Education_OC_K,MATCH("4",ITT_Education_OC_A,0))),"") | M28: =IF(OR(L28="",$G28="",$H28=""),"",IF($H28-$G28=0,"",(L28-$G28)/($H28-$G28))) | S28: =IF(OR(R28="",$G28="",$H28=""),"",IF($H28-$G28=0,"",(R28-$G28)/($H28-$G28))) | Y28: =IF(OR(X28="",$G28="",$H28=""),"",IF($H28-$G28=0,"",(X28-$G28)/($H28-$G28))) | AE28: =IF(OR(AD28="",$G28="",$H28=""),"",IF($H28-$G28=0,"",(AD28-$G28)/($H28-$G28))) | AK28: =IF(OR(AJ28="",$G28="",$H28=""),"",IF($H28-$G28=0,"",(AJ28-$G28)/($H28-$G28)))
C29: =IFERROR(IF(INDEX(ITT_Education_OC_A,MATCH("5",ITT_Education_OC_A,0))="","",INDEX(ITT_Education_OC_A,MATCH("5",ITT_Education_OC_A,0))),"") -> 5 | D29: =IFERROR(IF(INDEX(ITT_Education_OC_B,MATCH("5",ITT_Education_OC_A,0))="","",INDEX(ITT_Education_OC_B,MATCH("5",ITT_Education_OC_A,0))),"") | E29: =IFERROR(IF(INDEX(ITT_Education_OC_E,MATCH("5",ITT_Education_OC_A,0))="","",INDEX(ITT_Education_OC_E,MATCH("5",ITT_Education_OC_A,0))),"") | F29: =IFERROR(IF(INDEX(ITT_Education_OC_G,MATCH("5",ITT_Education_OC_A,0))="","",INDEX(ITT_Education_OC_G,MATCH("5",ITT_Education_OC_A,0))),"") | G29: =IFERROR(IF(INDEX(ITT_Education_OC_J,MATCH("5",ITT_Education_OC_A,0))="","",INDEX(ITT_Education_OC_J,MATCH("5",ITT_Education_OC_A,0))),"") | H29: =IFERROR(IF(INDEX(ITT_Education_OC_K,MATCH("5",ITT_Education_OC_A,0))="","",INDEX(ITT_Education_OC_K,MATCH("5",ITT_Education_OC_A,0))),"") | M29: =IF(OR(L29="",$G29="",$H29=""),"",IF($H29-$G29=0,"",(L29-$G29)/($H29-$G29))) | S29: =IF(OR(R29="",$G29="",$H29=""),"",IF($H29-$G29=0,"",(R29-$G29)/($H29-$G29))) | Y29: =IF(OR(X29="",$G29="",$H29=""),"",IF($H29-$G29=0,"",(X29-$G29)/($H29-$G29))) | AE29: =IF(OR(AD29="",$G29="",$H29=""),"",IF($H29-$G29=0,"",(AD29-$G29)/($H29-$G29))) | AK29: =IF(OR(AJ29="",$G29="",$H29=""),"",IF($H29-$G29=0,"",(AJ29-$G29)/($H29-$G29)))
B30: Output | C30: =IFERROR(IF(INDEX(ITT_Education_OP_A,MATCH("1.1",ITT_Education_OP_A,0))="","",INDEX(ITT_Education_OP_A,MATCH("1.1",ITT_Education_OP_A,0))),"") -> 1.1 | D30: =IFERROR(IF(INDEX(ITT_Education_OP_B,MATCH("1.1",ITT_Education_OP_A,0))="","",INDEX(ITT_Education_OP_B,MATCH("1.1",ITT_Education_OP_A,0))),"") | E30: =IFERROR(IF(INDEX(ITT_Education_OP_E,MATCH("1.1",ITT_Education_OP_A,0))="","",INDEX(ITT_Education_OP_E,MATCH("1.1",ITT_Education_OP_A,0))),"") | F30: =IFERROR(IF(INDEX(ITT_Education_OP_G,MATCH("1.1",ITT_Education_OP_A,0))="","",INDEX(ITT_Education_OP_G,MATCH("1.1",ITT_Education_OP_A,0))),"") | G30: =IFERROR(IF(INDEX(ITT_Education_OP_J,MATCH("1.1",ITT_Education_OP_A,0))="","",INDEX(ITT_Education_OP_J,MATCH("1.1",ITT_Education_OP_A,0))),"") | H30: =IFERROR(IF(INDEX(ITT_Education_OP_K,MATCH("1.1",ITT_Education_OP_A,0))="","",INDEX(ITT_Education_OP_K,MATCH("1.1",ITT_Education_OP_A,0))),"") | M30: =IF(OR(L30="",$G30="",$H30=""),"",IF($H30-$G30=0,"",(L30-$G30)/($H30-$G30))) | S30: =IF(OR(R30="",$G30="",$H30=""),"",IF($H30-$G30=0,"",(R30-$G30)/($H30-$G30))) | Y30: =IF(OR(X30="",$G30="",$H30=""),"",IF($H30-$G30=0,"",(X30-$G30)/($H30-$G30))) | AE30: =IF(OR(AD30="",$G30="",$H30=""),"",IF($H30-$G30=0,"",(AD30-$G30)/($H30-$G30))) | AK30: =IF(OR(AJ30="",$G30="",$H30=""),"",IF($H30-$G30=0,"",(AJ30-$G30)/($H30-$G30)))
C31: =IFERROR(IF(INDEX(ITT_Education_OP_A,MATCH("1.2",ITT_Education_OP_A,0))="","",INDEX(ITT_Education_OP_A,MATCH("1.2",ITT_Education_OP_A,0))),"") -> 1.2 | D31: =IFERROR(IF(INDEX(ITT_Education_OP_B,MATCH("1.2",ITT_Education_OP_A,0))="","",INDEX(ITT_Education_OP_B,MATCH("1.2",ITT_Education_OP_A,0))),"") | E31: =IFERROR(IF(INDEX(ITT_Education_OP_E,MATCH("1.2",ITT_Education_OP_A,0))="","",INDEX(ITT_Education_OP_E,MATCH("1.2",ITT_Education_OP_A,0))),"") | F31: =IFERROR(IF(INDEX(ITT_Education_OP_G,MATCH("1.2",ITT_Education_OP_A,0))="","",INDEX(ITT_Education_OP_G,MATCH("1.2",ITT_Education_OP_A,0))),"") | G31: =IFERROR(IF(INDEX(ITT_Education_OP_J,MATCH("1.2",ITT_Education_OP_A,0))="","",INDEX(ITT_Education_OP_J,MATCH("1.2",ITT_Education_OP_A,0))),"") | H31: =IFERROR(IF(INDEX(ITT_Education_OP_K,MATCH("1.2",ITT_Education_OP_A,0))="","",INDEX(ITT_Education_OP_K,MATCH("1.2",ITT_Education_OP_A,0))),"") | M31: =IF(OR(L31="",$G31="",$H31=""),"",IF($H31-$G31=0,"",(L31-$G31)/($H31-$G31))) | S31: =IF(OR(R31="",$G31="",$H31=""),"",IF($H31-$G31=0,"",(R31-$G31)/($H31-$G31))) | Y31: =IF(OR(X31="",$G31="",$H31=""),"",IF($H31-$G31=0,"",(X31-$G31)/($H31-$G31))) | AE31: =IF(OR(AD31="",$G31="",$H31=""),"",IF($H31-$G31=0,"",(AD31-$G31)/($H31-$G31))) | AK31: =IF(OR(AJ31="",$G31="",$H31=""),"",IF($H31-$G31=0,"",(AJ31-$G31)/($H31-$G31)))
C32: =IFERROR(IF(INDEX(ITT_Education_OP_A,MATCH("1.3",ITT_Education_OP_A,0))="","",INDEX(ITT_Education_OP_A,MATCH("1.3",ITT_Education_OP_A,0))),"") -> 1.3 | D32: =IFERROR(IF(INDEX(ITT_Education_OP_B,MATCH("1.3",ITT_Education_OP_A,0))="","",INDEX(ITT_Education_OP_B,MATCH("1.3",ITT_Education_OP_A,0))),"") | E32: =IFERROR(IF(INDEX(ITT_Education_OP_E,MATCH("1.3",ITT_Education_OP_A,0))="","",INDEX(ITT_Education_OP_E,MATCH("1.3",ITT_Education_OP_A,0))),"") | F32: =IFERROR(IF(INDEX(ITT_Education_OP_G,MATCH("1.3",ITT_Education_OP_A,0))="","",INDEX(ITT_Education_OP_G,MATCH("1.3",ITT_Education_OP_A,0))),"") | G32: =IFERROR(IF(INDEX(ITT_Education_OP_J,MATCH("1.3",ITT_Education_OP_A,0))="","",INDEX(ITT_Education_OP_J,MATCH("1.3",ITT_Education_OP_A,0))),"") | H32: =IFERROR(IF(INDEX(ITT_Education_OP_K,MATCH("1.3",ITT_Education_OP_A,0))="","",INDEX(ITT_Education_OP_K,MATCH("1.3",ITT_Education_OP_A,0))),"") | M32: =IF(OR(L32="",$G32="",$H32=""),"",IF($H32-$G32=0,"",(L32-$G32)/($H32-$G32))) | S32: =IF(OR(R32="",$G32="",$H32=""),"",IF($H32-$G32=0,"",(R32-$G32)/($H32-$G32))) | Y32: =IF(OR(X32="",$G32="",$H32=""),"",IF($H32-$G32=0,"",(X32-$G32)/($H32-$G32))) | AE32: =IF(OR(AD32="",$G32="",$H32=""),"",IF($H32-$G32=0,"",(AD32-$G32)/($H32-$G32))) | AK32: =IF(OR(AJ32="",$G32="",$H32=""),"",IF($H32-$G32=0,"",(AJ32-$G32)/($H32-$G32)))
C33: =IFERROR(IF(INDEX(ITT_Education_OP_A,MATCH("2.1",ITT_Education_OP_A,0))="","",INDEX(ITT_Education_OP_A,MATCH("2.1",ITT_Education_OP_A,0))),"") -> 2.1 | D33: =IFERROR(IF(INDEX(ITT_Education_OP_B,MATCH("2.1",ITT_Education_OP_A,0))="","",INDEX(ITT_Education_OP_B,MATCH("2.1",ITT_Education_OP_A,0))),"") | E33: =IFERROR(IF(INDEX(ITT_Education_OP_E,MATCH("2.1",ITT_Education_OP_A,0))="","",INDEX(ITT_Education_OP_E,MATCH("2.1",ITT_Education_OP_A,0))),"") | F33: =IFERROR(IF(INDEX(ITT_Education_OP_G,MATCH("2.1",ITT_Education_OP_A,0))="","",INDEX(ITT_Education_OP_G,MATCH("2.1",ITT_Education_OP_A,0))),"") | G33: =IFERROR(IF(INDEX(ITT_Education_OP_J,MATCH("2.1",ITT_Education_OP_A,0))="","",INDEX(ITT_Education_OP_J,MATCH("2.1",ITT_Education_OP_A,0))),"") | H33: =IFERROR(IF(INDEX(ITT_Education_OP_K,MATCH("2.1",ITT_Education_OP_A,0))="","",INDEX(ITT_Education_OP_K,MATCH("2.1",ITT_Education_OP_A,0))),"") | M33: =IF(OR(L33="",$G33="",$H33=""),"",IF($H33-$G33=0,"",(L33-$G33)/($H33-$G33))) | S33: =IF(OR(R33="",$G33="",$H33=""),"",IF($H33-$G33=0,"",(R33-$G33)/($H33-$G33))) | Y33: =IF(OR(X33="",$G33="",$H33=""),"",IF($H33-$G33=0,"",(X33-$G33)/($H33-$G33))) | AE33: =IF(OR(AD33="",$G33="",$H33=""),"",IF($H33-$G33=0,"",(AD33-$G33)/($H33-$G33))) | AK33: =IF(OR(AJ33="",$G33="",$H33=""),"",IF($H33-$G33=0,"",(AJ33-$G33)/($H33-$G33)))
C34: =IFERROR(IF(INDEX(ITT_Education_OP_A,MATCH("2.2",ITT_Education_OP_A,0))="","",INDEX(ITT_Education_OP_A,MATCH("2.2",ITT_Education_OP_A,0))),"") -> 2.2 | D34: =IFERROR(IF(INDEX(ITT_Education_OP_B,MATCH("2.2",ITT_Education_OP_A,0))="","",INDEX(ITT_Education_OP_B,MATCH("2.2",ITT_Education_OP_A,0))),"") | E34: =IFERROR(IF(INDEX(ITT_Education_OP_E,MATCH("2.2",ITT_Education_OP_A,0))="","",INDEX(ITT_Education_OP_E,MATCH("2.2",ITT_Education_OP_A,0))),"") | F34: =IFERROR(IF(INDEX(ITT_Education_OP_G,MATCH("2.2",ITT_Education_OP_A,0))="","",INDEX(ITT_Education_OP_G,MATCH("2.2",ITT_Education_OP_A,0))),"") | G34: =IFERROR(IF(INDEX(ITT_Education_OP_J,MATCH("2.2",ITT_Education_OP_A,0))="","",INDEX(ITT_Education_OP_J,MATCH("2.2",ITT_Education_OP_A,0))),"") | H34: =IFERROR(IF(INDEX(ITT_Education_OP_K,MATCH("2.2",ITT_Education_OP_A,0))="","",INDEX(ITT_Education_OP_K,MATCH("2.2",ITT_Education_OP_A,0))),"") | M34: =IF(OR(L34="",$G34="",$H34=""),"",IF($H34-$G34=0,"",(L34-$G34)/($H34-$G34))) | S34: =IF(OR(R34="",$G34="",$H34=""),"",IF($H34-$G34=0,"",(R34-$G34)/($H34-$G34))) | Y34: =IF(OR(X34="",$G34="",$H34=""),"",IF($H34-$G34=0,"",(X34-$G34)/($H34-$G34))) | AE34: =IF(OR(AD34="",$G34="",$H34=""),"",IF($H34-$G34=0,"",(AD34-$G34)/($H34-$G34))) | AK34: =IF(OR(AJ34="",$G34="",$H34=""),"",IF($H34-$G34=0,"",(AJ34-$G34)/($H34-$G34)))
C35: =IFERROR(IF(INDEX(ITT_Education_OP_A,MATCH("2.3",ITT_Education_OP_A,0))="","",INDEX(ITT_Education_OP_A,MATCH("2.3",ITT_Education_OP_A,0))),"") -> 2.3 | D35: =IFERROR(IF(INDEX(ITT_Education_OP_B,MATCH("2.3",ITT_Education_OP_A,0))="","",INDEX(ITT_Education_OP_B,MATCH("2.3",ITT_Education_OP_A,0))),"") | E35: =IFERROR(IF(INDEX(ITT_Education_OP_E,MATCH("2.3",ITT_Education_OP_A,0))="","",INDEX(ITT_Education_OP_E,MATCH("2.3",ITT_Education_OP_A,0))),"") | F35: =IFERROR(IF(INDEX(ITT_Education_OP_G,MATCH("2.3",ITT_Education_OP_A,0))="","",INDEX(ITT_Education_OP_G,MATCH("2.3",ITT_Education_OP_A,0))),"") | G35: =IFERROR(IF(INDEX(ITT_Education_OP_J,MATCH("2.3",ITT_Education_OP_A,0))="","",INDEX(ITT_Education_OP_J,MATCH("2.3",ITT_Education_OP_A,0))),"") | H35: =IFERROR(IF(INDEX(ITT_Education_OP_K,MATCH("2.3",ITT_Education_OP_A,0))="","",INDEX(ITT_Education_OP_K,MATCH("2.3",ITT_Education_OP_A,0))),"") | M35: =IF(OR(L35="",$G35="",$H35=""),"",IF($H35-$G35=0,"",(L35-$G35)/($H35-$G35))) | S35: =IF(OR(R35="",$G35="",$H35=""),"",IF($H35-$G35=0,"",(R35-$G35)/($H35-$G35))) | Y35: =IF(OR(X35="",$G35="",$H35=""),"",IF($H35-$G35=0,"",(X35-$G35)/($H35-$G35))) | AE35: =IF(OR(AD35="",$G35="",$H35=""),"",IF($H35-$G35=0,"",(AD35-$G35)/($H35-$G35))) | AK35: =IF(OR(AJ35="",$G35="",$H35=""),"",IF($H35-$G35=0,"",(AJ35-$G35)/($H35-$G35)))
C36: =IFERROR(IF(INDEX(ITT_Education_OP_A,MATCH("3.1",ITT_Education_OP_A,0))="","",INDEX(ITT_Education_OP_A,MATCH("3.1",ITT_Education_OP_A,0))),"") -> 3.1 | D36: =IFERROR(IF(INDEX(ITT_Education_OP_B,MATCH("3.1",ITT_Education_OP_A,0))="","",INDEX(ITT_Education_OP_B,MATCH("3.1",ITT_Education_OP_A,0))),"") | E36: =IFERROR(IF(INDEX(ITT_Education_OP_E,MATCH("3.1",ITT_Education_OP_A,0))="","",INDEX(ITT_Education_OP_E,MATCH("3.1",ITT_Education_OP_A,0))),"") | F36: =IFERROR(IF(INDEX(ITT_Education_OP_G,MATCH("3.1",ITT_Education_OP_A,0))="","",INDEX(ITT_Education_OP_G,MATCH("3.1",ITT_Education_OP_A,0))),"") | G36: =IFERROR(IF(INDEX(ITT_Education_OP_J,MATCH("3.1",ITT_Education_OP_A,0))="","",INDEX(ITT_Education_OP_J,MATCH("3.1",ITT_Education_OP_A,0))),"") | H36: =IFERROR(IF(INDEX(ITT_Education_OP_K,MATCH("3.1",ITT_Education_OP_A,0))="","",INDEX(ITT_Education_OP_K,MATCH("3.1",ITT_Education_OP_A,0))),"") | M36: =IF(OR(L36="",$G36="",$H36=""),"",IF($H36-$G36=0,"",(L36-$G36)/($H36-$G36))) | S36: =IF(OR(R36="",$G36="",$H36=""),"",IF($H36-$G36=0,"",(R36-$G36)/($H36-$G36))) | Y36: =IF(OR(X36="",$G36="",$H36=""),"",IF($H36-$G36=0,"",(X36-$G36)/($H36-$G36))) | AE36: =IF(OR(AD36="",$G36="",$H36=""),"",IF($H36-$G36=0,"",(AD36-$G36)/($H36-$G36))) | AK36: =IF(OR(AJ36="",$G36="",$H36=""),"",IF($H36-$G36=0,"",(AJ36-$G36)/($H36-$G36)))
C37: =IFERROR(IF(INDEX(ITT_Education_OP_A,MATCH("3.2",ITT_Education_OP_A,0))="","",INDEX(ITT_Education_OP_A,MATCH("3.2",ITT_Education_OP_A,0))),"") -> 3.2 | D37: =IFERROR(IF(INDEX(ITT_Education_OP_B,MATCH("3.2",ITT_Education_OP_A,0))="","",INDEX(ITT_Education_OP_B,MATCH("3.2",ITT_Education_OP_A,0))),"") | E37: =IFERROR(IF(INDEX(ITT_Education_OP_E,MATCH("3.2",ITT_Education_OP_A,0))="","",INDEX(ITT_Education_OP_E,MATCH("3.2",ITT_Education_OP_A,0))),"") | F37: =IFERROR(IF(INDEX(ITT_Education_OP_G,MATCH("3.2",ITT_Education_OP_A,0))="","",INDEX(ITT_Education_OP_G,MATCH("3.2",ITT_Education_OP_A,0))),"") | G37: =IFERROR(IF(INDEX(ITT_Education_OP_J,MATCH("3.2",ITT_Education_OP_A,0))="","",INDEX(ITT_Education_OP_J,MATCH("3.2",ITT_Education_OP_A,0))),"") | H37: =IFERROR(IF(INDEX(ITT_Education_OP_K,MATCH("3.2",ITT_Education_OP_A,0))="","",INDEX(ITT_Education_OP_K,MATCH("3.2",ITT_Education_OP_A,0))),"") | M37: =IF(OR(L37="",$G37="",$H37=""),"",IF($H37-$G37=0,"",(L37-$G37)/($H37-$G37))) | S37: =IF(OR(R37="",$G37="",$H37=""),"",IF($H37-$G37=0,"",(R37-$G37)/($H37-$G37))) | Y37: =IF(OR(X37="",$G37="",$H37=""),"",IF($H37-$G37=0,"",(X37-$G37)/($H37-$G37))) | AE37: =IF(OR(AD37="",$G37="",$H37=""),"",IF($H37-$G37=0,"",(AD37-$G37)/($H37-$G37))) | AK37: =IF(OR(AJ37="",$G37="",$H37=""),"",IF($H37-$G37=0,"",(AJ37-$G37)/($H37-$G37)))
C38: =IFERROR(IF(INDEX(ITT_Education_OP_A,MATCH("3.3",ITT_Education_OP_A,0))="","",INDEX(ITT_Education_OP_A,MATCH("3.3",ITT_Education_OP_A,0))),"") -> 3.3 | D38: =IFERROR(IF(INDEX(ITT_Education_OP_B,MATCH("3.3",ITT_Education_OP_A,0))="","",INDEX(ITT_Education_OP_B,MATCH("3.3",ITT_Education_OP_A,0))),"") | E38: =IFERROR(IF(INDEX(ITT_Education_OP_E,MATCH("3.3",ITT_Education_OP_A,0))="","",INDEX(ITT_Education_OP_E,MATCH("3.3",ITT_Education_OP_A,0))),"") | F38: =IFERROR(IF(INDEX(ITT_Education_OP_G,MATCH("3.3",ITT_Education_OP_A,0))="","",INDEX(ITT_Education_OP_G,MATCH("3.3",ITT_Education_OP_A,0))),"") | G38: =IFERROR(IF(INDEX(ITT_Education_OP_J,MATCH("3.3",ITT_Education_OP_A,0))="","",INDEX(ITT_Education_OP_J,MATCH("3.3",ITT_Education_OP_A,0))),"") | H38: =IFERROR(IF(INDEX(ITT_Education_OP_K,MATCH("3.3",ITT_Education_OP_A,0))="","",INDEX(ITT_Education_OP_K,MATCH("3.3",ITT_Education_OP_A,0))),"") | M38: =IF(OR(L38="",$G38="",$H38=""),"",IF($H38-$G38=0,"",(L38-$G38)/($H38-$G38))) | S38: =IF(OR(R38="",$G38="",$H38=""),"",IF($H38-$G38=0,"",(R38-$G38)/($H38-$G38))) | Y38: =IF(OR(X38="",$G38="",$H38=""),"",IF($H38-$G38=0,"",(X38-$G38)/($H38-$G38))) | AE38: =IF(OR(AD38="",$G38="",$H38=""),"",IF($H38-$G38=0,"",(AD38-$G38)/($H38-$G38))) | AK38: =IF(OR(AJ38="",$G38="",$H38=""),"",IF($H38-$G38=0,"",(AJ38-$G38)/($H38-$G38)))
C39: =IFERROR(IF(INDEX(ITT_Education_OP_A,MATCH("4.1",ITT_Education_OP_A,0))="","",INDEX(ITT_Education_OP_A,MATCH("4.1",ITT_Education_OP_A,0))),"") -> 4.1 | D39: =IFERROR(IF(INDEX(ITT_Education_OP_B,MATCH("4.1",ITT_Education_OP_A,0))="","",INDEX(ITT_Education_OP_B,MATCH("4.1",ITT_Education_OP_A,0))),"") | E39: =IFERROR(IF(INDEX(ITT_Education_OP_E,MATCH("4.1",ITT_Education_OP_A,0))="","",INDEX(ITT_Education_OP_E,MATCH("4.1",ITT_Education_OP_A,0))),"") | F39: =IFERROR(IF(INDEX(ITT_Education_OP_G,MATCH("4.1",ITT_Education_OP_A,0))="","",INDEX(ITT_Education_OP_G,MATCH("4.1",ITT_Education_OP_A,0))),"") | G39: =IFERROR(IF(INDEX(ITT_Education_OP_J,MATCH("4.1",ITT_Education_OP_A,0))="","",INDEX(ITT_Education_OP_J,MATCH("4.1",ITT_Education_OP_A,0))),"") | H39: =IFERROR(IF(INDEX(ITT_Education_OP_K,MATCH("4.1",ITT_Education_OP_A,0))="","",INDEX(ITT_Education_OP_K,MATCH("4.1",ITT_Education_OP_A,0))),"") | M39: =IF(OR(L39="",$G39="",$H39=""),"",IF($H39-$G39=0,"",(L39-$G39)/($H39-$G39))) | S39: =IF(OR(R39="",$G39="",$H39=""),"",IF($H39-$G39=0,"",(R39-$G39)/($H39-$G39))) | Y39: =IF(OR(X39="",$G39="",$H39=""),"",IF($H39-$G39=0,"",(X39-$G39)/($H39-$G39))) | AE39: =IF(OR(AD39="",$G39="",$H39=""),"",IF($H39-$G39=0,"",(AD39-$G39)/($H39-$G39))) | AK39: =IF(OR(AJ39="",$G39="",$H39=""),"",IF($H39-$G39=0,"",(AJ39-$G39)/($H39-$G39)))
C40: =IFERROR(IF(INDEX(ITT_Education_OP_A,MATCH("4.2",ITT_Education_OP_A,0))="","",INDEX(ITT_Education_OP_A,MATCH("4.2",ITT_Education_OP_A,0))),"") -> 4.2 | D40: =IFERROR(IF(INDEX(ITT_Education_OP_B,MATCH("4.2",ITT_Education_OP_A,0))="","",INDEX(ITT_Education_OP_B,MATCH("4.2",ITT_Education_OP_A,0))),"") | E40: =IFERROR(IF(INDEX(ITT_Education_OP_E,MATCH("4.2",ITT_Education_OP_A,0))="","",INDEX(ITT_Education_OP_E,MATCH("4.2",ITT_Education_OP_A,0))),"") | F40: =IFERROR(IF(INDEX(ITT_Education_OP_G,MATCH("4.2",ITT_Education_OP_A,0))="","",INDEX(ITT_Education_OP_G,MATCH("4.2",ITT_Education_OP_A,0))),"") | G40: =IFERROR(IF(INDEX(ITT_Education_OP_J,MATCH("4.2",ITT_Education_OP_A,0))="","",INDEX(ITT_Education_OP_J,MATCH("4.2",ITT_Education_OP_A,0))),"") | H40: =IFERROR(IF(INDEX(ITT_Education_OP_K,MATCH("4.2",ITT_Education_OP_A,0))="","",INDEX(ITT_Education_OP_K,MATCH("4.2",ITT_Education_OP_A,0))),"") | M40: =IF(OR(L40="",$G40="",$H40=""),"",IF($H40-$G40=0,"",(L40-$G40)/($H40-$G40))) | S40: =IF(OR(R40="",$G40="",$H40=""),"",IF($H40-$G40=0,"",(R40-$G40)/($H40-$G40))) | Y40: =IF(OR(X40="",$G40="",$H40=""),"",IF($H40-$G40=0,"",(X40-$G40)/($H40-$G40))) | AE40: =IF(OR(AD40="",$G40="",$H40=""),"",IF($H40-$G40=0,"",(AD40-$G40)/($H40-$G40))) | AK40: =IF(OR(AJ40="",$G40="",$H40=""),"",IF($H40-$G40=0,"",(AJ40-$G40)/($H40-$G40)))
C41: =IFERROR(IF(INDEX(ITT_Education_OP_A,MATCH("4.3",ITT_Education_OP_A,0))="","",INDEX(ITT_Education_OP_A,MATCH("4.3",ITT_Education_OP_A,0))),"") -> 4.3 | D41: =IFERROR(IF(INDEX(ITT_Education_OP_B,MATCH("4.3",ITT_Education_OP_A,0))="","",INDEX(ITT_Education_OP_B,MATCH("4.3",ITT_Education_OP_A,0))),"") | E41: =IFERROR(IF(INDEX(ITT_Education_OP_E,MATCH("4.3",ITT_Education_OP_A,0))="","",INDEX(ITT_Education_OP_E,MATCH("4.3",ITT_Education_OP_A,0))),"") | F41: =IFERROR(IF(INDEX(ITT_Education_OP_G,MATCH("4.3",ITT_Education_OP_A,0))="","",INDEX(ITT_Education_OP_G,MATCH("4.3",ITT_Education_OP_A,0))),"") | G41: =IFERROR(IF(INDEX(ITT_Education_OP_J,MATCH("4.3",ITT_Education_OP_A,0))="","",INDEX(ITT_Education_OP_J,MATCH("4.3",ITT_Education_OP_A,0))),"") | H41: =IFERROR(IF(INDEX(ITT_Education_OP_K,MATCH("4.3",ITT_Education_OP_A,0))="","",INDEX(ITT_Education_OP_K,MATCH("4.3",ITT_Education_OP_A,0))),"") | M41: =IF(OR(L41="",$G41="",$H41=""),"",IF($H41-$G41=0,"",(L41-$G41)/($H41-$G41))) | S41: =IF(OR(R41="",$G41="",$H41=""),"",IF($H41-$G41=0,"",(R41-$G41)/($H41-$G41))) | Y41: =IF(OR(X41="",$G41="",$H41=""),"",IF($H41-$G41=0,"",(X41-$G41)/($H41-$G41))) | AE41: =IF(OR(AD41="",$G41="",$H41=""),"",IF($H41-$G41=0,"",(AD41-$G41)/($H41-$G41))) | AK41: =IF(OR(AJ41="",$G41="",$H41=""),"",IF($H41-$G41=0,"",(AJ41-$G41)/($H41-$G41)))
C42: =IFERROR(IF(INDEX(ITT_Education_OP_A,MATCH("5.1",ITT_Education_OP_A,0))="","",INDEX(ITT_Education_OP_A,MATCH("5.1",ITT_Education_OP_A,0))),"") -> 5.1 | D42: =IFERROR(IF(INDEX(ITT_Education_OP_B,MATCH("5.1",ITT_Education_OP_A,0))="","",INDEX(ITT_Education_OP_B,MATCH("5.1",ITT_Education_OP_A,0))),"") | E42: =IFERROR(IF(INDEX(ITT_Education_OP_E,MATCH("5.1",ITT_Education_OP_A,0))="","",INDEX(ITT_Education_OP_E,MATCH("5.1",ITT_Education_OP_A,0))),"") | F42: =IFERROR(IF(INDEX(ITT_Education_OP_G,MATCH("5.1",ITT_Education_OP_A,0))="","",INDEX(ITT_Education_OP_G,MATCH("5.1",ITT_Education_OP_A,0))),"") | G42: =IFERROR(IF(INDEX(ITT_Education_OP_J,MATCH("5.1",ITT_Education_OP_A,0))="","",INDEX(ITT_Education_OP_J,MATCH("5.1",ITT_Education_OP_A,0))),"") | H42: =IFERROR(IF(INDEX(ITT_Education_OP_K,MATCH("5.1",ITT_Education_OP_A,0))="","",INDEX(ITT_Education_OP_K,MATCH("5.1",ITT_Education_OP_A,0))),"") | M42: =IF(OR(L42="",$G42="",$H42=""),"",IF($H42-$G42=0,"",(L42-$G42)/($H42-$G42))) | S42: =IF(OR(R42="",$G42="",$H42=""),"",IF($H42-$G42=0,"",(R42-$G42)/($H42-$G42))) | Y42: =IF(OR(X42="",$G42="",$H42=""),"",IF($H42-$G42=0,"",(X42-$G42)/($H42-$G42))) | AE42: =IF(OR(AD42="",$G42="",$H42=""),"",IF($H42-$G42=0,"",(AD42-$G42)/($H42-$G42))) | AK42: =IF(OR(AJ42="",$G42="",$H42=""),"",IF($H42-$G42=0,"",(AJ42-$G42)/($H42-$G42)))
C43: =IFERROR(IF(INDEX(ITT_Education_OP_A,MATCH("5.2",ITT_Education_OP_A,0))="","",INDEX(ITT_Education_OP_A,MATCH("5.2",ITT_Education_OP_A,0))),"") -> 5.2 | D43: =IFERROR(IF(INDEX(ITT_Education_OP_B,MATCH("5.2",ITT_Education_OP_A,0))="","",INDEX(ITT_Education_OP_B,MATCH("5.2",ITT_Education_OP_A,0))),"") | E43: =IFERROR(IF(INDEX(ITT_Education_OP_E,MATCH("5.2",ITT_Education_OP_A,0))="","",INDEX(ITT_Education_OP_E,MATCH("5.2",ITT_Education_OP_A,0))),"") | F43: =IFERROR(IF(INDEX(ITT_Education_OP_G,MATCH("5.2",ITT_Education_OP_A,0))="","",INDEX(ITT_Education_OP_G,MATCH("5.2",ITT_Education_OP_A,0))),"") | G43: =IFERROR(IF(INDEX(ITT_Education_OP_J,MATCH("5.2",ITT_Education_OP_A,0))="","",INDEX(ITT_Education_OP_J,MATCH("5.2",ITT_Education_OP_A,0))),"") | H43: =IFERROR(IF(INDEX(ITT_Education_OP_K,MATCH("5.2",ITT_Education_OP_A,0))="","",INDEX(ITT_Education_OP_K,MATCH("5.2",ITT_Education_OP_A,0))),"") | M43: =IF(OR(L43="",$G43="",$H43=""),"",IF($H43-$G43=0,"",(L43-$G43)/($H43-$G43))) | S43: =IF(OR(R43="",$G43="",$H43=""),"",IF($H43-$G43=0,"",(R43-$G43)/($H43-$G43))) | Y43: =IF(OR(X43="",$G43="",$H43=""),"",IF($H43-$G43=0,"",(X43-$G43)/($H43-$G43))) | AE43: =IF(OR(AD43="",$G43="",$H43=""),"",IF($H43-$G43=0,"",(AD43-$G43)/($H43-$G43))) | AK43: =IF(OR(AJ43="",$G43="",$H43=""),"",IF($H43-$G43=0,"",(AJ43-$G43)/($H43-$G43)))
C44: =IFERROR(IF(INDEX(ITT_Education_OP_A,MATCH("5.3",ITT_Education_OP_A,0))="","",INDEX(ITT_Education_OP_A,MATCH("5.3",ITT_Education_OP_A,0))),"") -> 5.3 | D44: =IFERROR(IF(INDEX(ITT_Education_OP_B,MATCH("5.3",ITT_Education_OP_A,0))="","",INDEX(ITT_Education_OP_B,MATCH("5.3",ITT_Education_OP_A,0))),"") | E44: =IFERROR(IF(INDEX(ITT_Education_OP_E,MATCH("5.3",ITT_Education_OP_A,0))="","",INDEX(ITT_Education_OP_E,MATCH("5.3",ITT_Education_OP_A,0))),"") | F44: =IFERROR(IF(INDEX(ITT_Education_OP_G,MATCH("5.3",ITT_Education_OP_A,0))="","",INDEX(ITT_Education_OP_G,MATCH("5.3",ITT_Education_OP_A,0))),"") | G44: =IFERROR(IF(INDEX(ITT_Education_OP_J,MATCH("5.3",ITT_Education_OP_A,0))="","",INDEX(ITT_Education_OP_J,MATCH("5.3",ITT_Education_OP_A,0))),"") | H44: =IFERROR(IF(INDEX(ITT_Education_OP_K,MATCH("5.3",ITT_Education_OP_A,0))="","",INDEX(ITT_Education_OP_K,MATCH("5.3",ITT_Education_OP_A,0))),"") | M44: =IF(OR(L44="",$G44="",$H44=""),"",IF($H44-$G44=0,"",(L44-$G44)/($H44-$G44))) | S44: =IF(OR(R44="",$G44="",$H44=""),"",IF($H44-$G44=0,"",(R44-$G44)/($H44-$G44))) | Y44: =IF(OR(X44="",$G44="",$H44=""),"",IF($H44-$G44=0,"",(X44-$G44)/($H44-$G44))) | AE44: =IF(OR(AD44="",$G44="",$H44=""),"",IF($H44-$G44=0,"",(AD44-$G44)/($H44-$G44))) | AK44: =IF(OR(AJ44="",$G44="",$H44=""),"",IF($H44-$G44=0,"",(AJ44-$G44)/($H44-$G44)))
A45: Health & Well-being | B45: Outcome | C45: =IFERROR(IF(INDEX(ITT_HealthWellbeing_OC_A,MATCH("1",ITT_HealthWellbeing_OC_A,0))="","",INDEX(ITT_HealthWellbeing_OC_A,MATCH("1",ITT_HealthWellbeing_OC_A,0))),"") -> 1 | D45: =IFERROR(IF(INDEX(ITT_HealthWellbeing_OC_B,MATCH("1",ITT_HealthWellbeing_OC_A,0))="","",INDEX(ITT_HealthWellbeing_OC_B,MATCH("1",ITT_HealthWellbeing_OC_A,0))),"") | E45: =IFERROR(IF(INDEX(ITT_HealthWellbeing_OC_E,MATCH("1",ITT_HealthWellbeing_OC_A,0))="","",INDEX(ITT_HealthWellbeing_OC_E,MATCH("1",ITT_HealthWellbeing_OC_A,0))),"") | F45: =IFERROR(IF(INDEX(ITT_HealthWellbeing_OC_G,MATCH("1",ITT_HealthWellbeing_OC_A,0))="","",INDEX(ITT_HealthWellbeing_OC_G,MATCH("1",ITT_HealthWellbeing_OC_A,0))),"") | G45: =IFERROR(IF(INDEX(ITT_HealthWellbeing_OC_J,MATCH("1",ITT_HealthWellbeing_OC_A,0))="","",INDEX(ITT_HealthWellbeing_OC_J,MATCH("1",ITT_HealthWellbeing_OC_A,0))),"") | H45: =IFERROR(IF(INDEX(ITT_HealthWellbeing_OC_K,MATCH("1",ITT_HealthWellbeing_OC_A,0))="","",INDEX(ITT_HealthWellbeing_OC_K,MATCH("1",ITT_HealthWellbeing_OC_A,0))),"") | M45: =IF(OR(L45="",$G45="",$H45=""),"",IF($H45-$G45=0,"",(L45-$G45)/($H45-$G45))) | S45: =IF(OR(R45="",$G45="",$H45=""),"",IF($H45-$G45=0,"",(R45-$G45)/($H45-$G45))) | Y45: =IF(OR(X45="",$G45="",$H45=""),"",IF($H45-$G45=0,"",(X45-$G45)/($H45-$G45))) | AE45: =IF(OR(AD45="",$G45="",$H45=""),"",IF($H45-$G45=0,"",(AD45-$G45)/($H45-$G45))) | AK45: =IF(OR(AJ45="",$G45="",$H45=""),"",IF($H45-$G45=0,"",(AJ45-$G45)/($H45-$G45)))
C46: =IFERROR(IF(INDEX(ITT_HealthWellbeing_OC_A,MATCH("2",ITT_HealthWellbeing_OC_A,0))="","",INDEX(ITT_HealthWellbeing_OC_A,MATCH("2",ITT_HealthWellbeing_OC_A,0))),"") -> 2 | D46: =IFERROR(IF(INDEX(ITT_HealthWellbeing_OC_B,MATCH("2",ITT_HealthWellbeing_OC_A,0))="","",INDEX(ITT_HealthWellbeing_OC_B,MATCH("2",ITT_HealthWellbeing_OC_A,0))),"") | E46: =IFERROR(IF(INDEX(ITT_HealthWellbeing_OC_E,MATCH("2",ITT_HealthWellbeing_OC_A,0))="","",INDEX(ITT_HealthWellbeing_OC_E,MATCH("2",ITT_HealthWellbeing_OC_A,0))),"") | F46: =IFERROR(IF(INDEX(ITT_HealthWellbeing_OC_G,MATCH("2",ITT_HealthWellbeing_OC_A,0))="","",INDEX(ITT_HealthWellbeing_OC_G,MATCH("2",ITT_HealthWellbeing_OC_A,0))),"") | G46: =IFERROR(IF(INDEX(ITT_HealthWellbeing_OC_J,MATCH("2",ITT_HealthWellbeing_OC_A,0))="","",INDEX(ITT_HealthWellbeing_OC_J,MATCH("2",ITT_HealthWellbeing_OC_A,0))),"") | H46: =IFERROR(IF(INDEX(ITT_HealthWellbeing_OC_K,MATCH("2",ITT_HealthWellbeing_OC_A,0))="","",INDEX(ITT_HealthWellbeing_OC_K,MATCH("2",ITT_HealthWellbeing_OC_A,0))),"") | M46: =IF(OR(L46="",$G46="",$H46=""),"",IF($H46-$G46=0,"",(L46-$G46)/($H46-$G46))) | S46: =IF(OR(R46="",$G46="",$H46=""),"",IF($H46-$G46=0,"",(R46-$G46)/($H46-$G46))) | Y46: =IF(OR(X46="",$G46="",$H46=""),"",IF($H46-$G46=0,"",(X46-$G46)/($H46-$G46))) | AE46: =IF(OR(AD46="",$G46="",$H46=""),"",IF($H46-$G46=0,"",(AD46-$G46)/($H46-$G46))) | AK46: =IF(OR(AJ46="",$G46="",$H46=""),"",IF($H46-$G46=0,"",(AJ46-$G46)/($H46-$G46)))
C47: =IFERROR(IF(INDEX(ITT_HealthWellbeing_OC_A,MATCH("3",ITT_HealthWellbeing_OC_A,0))="","",INDEX(ITT_HealthWellbeing_OC_A,MATCH("3",ITT_HealthWellbeing_OC_A,0))),"") -> 3 | D47: =IFERROR(IF(INDEX(ITT_HealthWellbeing_OC_B,MATCH("3",ITT_HealthWellbeing_OC_A,0))="","",INDEX(ITT_HealthWellbeing_OC_B,MATCH("3",ITT_HealthWellbeing_OC_A,0))),"") | E47: =IFERROR(IF(INDEX(ITT_HealthWellbeing_OC_E,MATCH("3",ITT_HealthWellbeing_OC_A,0))="","",INDEX(ITT_HealthWellbeing_OC_E,MATCH("3",ITT_HealthWellbeing_OC_A,0))),"") | F47: =IFERROR(IF(INDEX(ITT_HealthWellbeing_OC_G,MATCH("3",ITT_HealthWellbeing_OC_A,0))="","",INDEX(ITT_HealthWellbeing_OC_G,MATCH("3",ITT_HealthWellbeing_OC_A,0))),"") | G47: =IFERROR(IF(INDEX(ITT_HealthWellbeing_OC_J,MATCH("3",ITT_HealthWellbeing_OC_A,0))="","",INDEX(ITT_HealthWellbeing_OC_J,MATCH("3",ITT_HealthWellbeing_OC_A,0))),"") | H47: =IFERROR(IF(INDEX(ITT_HealthWellbeing_OC_K,MATCH("3",ITT_HealthWellbeing_OC_A,0))="","",INDEX(ITT_HealthWellbeing_OC_K,MATCH("3",ITT_HealthWellbeing_OC_A,0))),"") | M47: =IF(OR(L47="",$G47="",$H47=""),"",IF($H47-$G47=0,"",(L47-$G47)/($H47-$G47))) | S47: =IF(OR(R47="",$G47="",$H47=""),"",IF($H47-$G47=0,"",(R47-$G47)/($H47-$G47))) | Y47: =IF(OR(X47="",$G47="",$H47=""),"",IF($H47-$G47=0,"",(X47-$G47)/($H47-$G47))) | AE47: =IF(OR(AD47="",$G47="",$H47=""),"",IF($H47-$G47=0,"",(AD47-$G47)/($H47-$G47))) | AK47: =IF(OR(AJ47="",$G47="",$H47=""),"",IF($H47-$G47=0,"",(AJ47-$G47)/($H47-$G47)))
C48: =IFERROR(IF(INDEX(ITT_HealthWellbeing_OC_A,MATCH("4",ITT_HealthWellbeing_OC_A,0))="","",INDEX(ITT_HealthWellbeing_OC_A,MATCH("4",ITT_HealthWellbeing_OC_A,0))),"") -> 4 | D48: =IFERROR(IF(INDEX(ITT_HealthWellbeing_OC_B,MATCH("4",ITT_HealthWellbeing_OC_A,0))="","",INDEX(ITT_HealthWellbeing_OC_B,MATCH("4",ITT_HealthWellbeing_OC_A,0))),"") | E48: =IFERROR(IF(INDEX(ITT_HealthWellbeing_OC_E,MATCH("4",ITT_HealthWellbeing_OC_A,0))="","",INDEX(ITT_HealthWellbeing_OC_E,MATCH("4",ITT_HealthWellbeing_OC_A,0))),"") | F48: =IFERROR(IF(INDEX(ITT_HealthWellbeing_OC_G,MATCH("4",ITT_HealthWellbeing_OC_A,0))="","",INDEX(ITT_HealthWellbeing_OC_G,MATCH("4",ITT_HealthWellbeing_OC_A,0))),"") | G48: =IFERROR(IF(INDEX(ITT_HealthWellbeing_OC_J,MATCH("4",ITT_HealthWellbeing_OC_A,0))="","",INDEX(ITT_HealthWellbeing_OC_J,MATCH("4",ITT_HealthWellbeing_OC_A,0))),"") | H48: =IFERROR(IF(INDEX(ITT_HealthWellbeing_OC_K,MATCH("4",ITT_HealthWellbeing_OC_A,0))="","",INDEX(ITT_HealthWellbeing_OC_K,MATCH("4",ITT_HealthWellbeing_OC_A,0))),"") | M48: =IF(OR(L48="",$G48="",$H48=""),"",IF($H48-$G48=0,"",(L48-$G48)/($H48-$G48))) | S48: =IF(OR(R48="",$G48="",$H48=""),"",IF($H48-$G48=0,"",(R48-$G48)/($H48-$G48))) | Y48: =IF(OR(X48="",$G48="",$H48=""),"",IF($H48-$G48=0,"",(X48-$G48)/($H48-$G48))) | AE48: =IF(OR(AD48="",$G48="",$H48=""),"",IF($H48-$G48=0,"",(AD48-$G48)/($H48-$G48))) | AK48: =IF(OR(AJ48="",$G48="",$H48=""),"",IF($H48-$G48=0,"",(AJ48-$G48)/($H48-$G48)))
C49: =IFERROR(IF(INDEX(ITT_HealthWellbeing_OC_A,MATCH("5",ITT_HealthWellbeing_OC_A,0))="","",INDEX(ITT_HealthWellbeing_OC_A,MATCH("5",ITT_HealthWellbeing_OC_A,0))),"") -> 5 | D49: =IFERROR(IF(INDEX(ITT_HealthWellbeing_OC_B,MATCH("5",ITT_HealthWellbeing_OC_A,0))="","",INDEX(ITT_HealthWellbeing_OC_B,MATCH("5",ITT_HealthWellbeing_OC_A,0))),"") | E49: =IFERROR(IF(INDEX(ITT_HealthWellbeing_OC_E,MATCH("5",ITT_HealthWellbeing_OC_A,0))="","",INDEX(ITT_HealthWellbeing_OC_E,MATCH("5",ITT_HealthWellbeing_OC_A,0))),"") | F49: =IFERROR(IF(INDEX(ITT_HealthWellbeing_OC_G,MATCH("5",ITT_HealthWellbeing_OC_A,0))="","",INDEX(ITT_HealthWellbeing_OC_G,MATCH("5",ITT_HealthWellbeing_OC_A,0))),"") | G49: =IFERROR(IF(INDEX(ITT_HealthWellbeing_OC_J,MATCH("5",ITT_HealthWellbeing_OC_A,0))="","",INDEX(ITT_HealthWellbeing_OC_J,MATCH("5",ITT_HealthWellbeing_OC_A,0))),"") | H49: =IFERROR(IF(INDEX(ITT_HealthWellbeing_OC_K,MATCH("5",ITT_HealthWellbeing_OC_A,0))="","",INDEX(ITT_HealthWellbeing_OC_K,MATCH("5",ITT_HealthWellbeing_OC_A,0))),"") | M49: =IF(OR(L49="",$G49="",$H49=""),"",IF($H49-$G49=0,"",(L49-$G49)/($H49-$G49))) | S49: =IF(OR(R49="",$G49="",$H49=""),"",IF($H49-$G49=0,"",(R49-$G49)/($H49-$G49))) | Y49: =IF(OR(X49="",$G49="",$H49=""),"",IF($H49-$G49=0,"",(X49-$G49)/($H49-$G49))) | AE49: =IF(OR(AD49="",$G49="",$H49=""),"",IF($H49-$G49=0,"",(AD49-$G49)/($H49-$G49))) | AK49: =IF(OR(AJ49="",$G49="",$H49=""),"",IF($H49-$G49=0,"",(AJ49-$G49)/($H49-$G49)))
B50: Output | C50: =IFERROR(IF(INDEX(ITT_HealthWellbeing_OP_A,MATCH("1.1",ITT_HealthWellbeing_OP_A,0))="","",INDEX(ITT_HealthWellbeing_OP_A,MATCH("1.1",ITT_HealthWellbeing_OP_A,0))),"") -> 1.1 | D50: =IFERROR(IF(INDEX(ITT_HealthWellbeing_OP_B,MATCH("1.1",ITT_HealthWellbeing_OP_A,0))="","",INDEX(ITT_HealthWellbeing_OP_B,MATCH("1.1",ITT_HealthWellbeing_OP_A,0))),"") | E50: =IFERROR(IF(INDEX(ITT_HealthWellbeing_OP_E,MATCH("1.1",ITT_HealthWellbeing_OP_A,0))="","",INDEX(ITT_HealthWellbeing_OP_E,MATCH("1.1",ITT_HealthWellbeing_OP_A,0))),"") | F50: =IFERROR(IF(INDEX(ITT_HealthWellbeing_OP_G,MATCH("1.1",ITT_HealthWellbeing_OP_A,0))="","",INDEX(ITT_HealthWellbeing_OP_G,MATCH("1.1",ITT_HealthWellbeing_OP_A,0))),"") | G50: =IFERROR(IF(INDEX(ITT_HealthWellbeing_OP_J,MATCH("1.1",ITT_HealthWellbeing_OP_A,0))="","",INDEX(ITT_HealthWellbeing_OP_J,MATCH("1.1",ITT_HealthWellbeing_OP_A,0))),"") | H50: =IFERROR(IF(INDEX(ITT_HealthWellbeing_OP_K,MATCH("1.1",ITT_HealthWellbeing_OP_A,0))="","",INDEX(ITT_HealthWellbeing_OP_K,MATCH("1.1",ITT_HealthWellbeing_OP_A,0))),"") | M50: =IF(OR(L50="",$G50="",$H50=""),"",IF($H50-$G50=0,"",(L50-$G50)/($H50-$G50))) | S50: =IF(OR(R50="",$G50="",$H50=""),"",IF($H50-$G50=0,"",(R50-$G50)/($H50-$G50))) | Y50: =IF(OR(X50="",$G50="",$H50=""),"",IF($H50-$G50=0,"",(X50-$G50)/($H50-$G50))) | AE50: =IF(OR(AD50="",$G50="",$H50=""),"",IF($H50-$G50=0,"",(AD50-$G50)/($H50-$G50))) | AK50: =IF(OR(AJ50="",$G50="",$H50=""),"",IF($H50-$G50=0,"",(AJ50-$G50)/($H50-$G50)))
C51: =IFERROR(IF(INDEX(ITT_HealthWellbeing_OP_A,MATCH("1.2",ITT_HealthWellbeing_OP_A,0))="","",INDEX(ITT_HealthWellbeing_OP_A,MATCH("1.2",ITT_HealthWellbeing_OP_A,0))),"") -> 1.2 | D51: =IFERROR(IF(INDEX(ITT_HealthWellbeing_OP_B,MATCH("1.2",ITT_HealthWellbeing_OP_A,0))="","",INDEX(ITT_HealthWellbeing_OP_B,MATCH("1.2",ITT_HealthWellbeing_OP_A,0))),"") | E51: =IFERROR(IF(INDEX(ITT_HealthWellbeing_OP_E,MATCH("1.2",ITT_HealthWellbeing_OP_A,0))="","",INDEX(ITT_HealthWellbeing_OP_E,MATCH("1.2",ITT_HealthWellbeing_OP_A,0))),"") | F51: =IFERROR(IF(INDEX(ITT_HealthWellbeing_OP_G,MATCH("1.2",ITT_HealthWellbeing_OP_A,0))="","",INDEX(ITT_HealthWellbeing_OP_G,MATCH("1.2",ITT_HealthWellbeing_OP_A,0))),"") | G51: =IFERROR(IF(INDEX(ITT_HealthWellbeing_OP_J,MATCH("1.2",ITT_HealthWellbeing_OP_A,0))="","",INDEX(ITT_HealthWellbeing_OP_J,MATCH("1.2",ITT_HealthWellbeing_OP_A,0))),"") | H51: =IFERROR(IF(INDEX(ITT_HealthWellbeing_OP_K,MATCH("1.2",ITT_HealthWellbeing_OP_A,0))="","",INDEX(ITT_HealthWellbeing_OP_K,MATCH("1.2",ITT_HealthWellbeing_OP_A,0))),"") | M51: =IF(OR(L51="",$G51="",$H51=""),"",IF($H51-$G51=0,"",(L51-$G51)/($H51-$G51))) | S51: =IF(OR(R51="",$G51="",$H51=""),"",IF($H51-$G51=0,"",(R51-$G51)/($H51-$G51))) | Y51: =IF(OR(X51="",$G51="",$H51=""),"",IF($H51-$G51=0,"",(X51-$G51)/($H51-$G51))) | AE51: =IF(OR(AD51="",$G51="",$H51=""),"",IF($H51-$G51=0,"",(AD51-$G51)/($H51-$G51))) | AK51: =IF(OR(AJ51="",$G51="",$H51=""),"",IF($H51-$G51=0,"",(AJ51-$G51)/($H51-$G51)))
C52: =IFERROR(IF(INDEX(ITT_HealthWellbeing_OP_A,MATCH("1.3",ITT_HealthWellbeing_OP_A,0))="","",INDEX(ITT_HealthWellbeing_OP_A,MATCH("1.3",ITT_HealthWellbeing_OP_A,0))),"") -> 1.3 | D52: =IFERROR(IF(INDEX(ITT_HealthWellbeing_OP_B,MATCH("1.3",ITT_HealthWellbeing_OP_A,0))="","",INDEX(ITT_HealthWellbeing_OP_B,MATCH("1.3",ITT_HealthWellbeing_OP_A,0))),"") | E52: =IFERROR(IF(INDEX(ITT_HealthWellbeing_OP_E,MATCH("1.3",ITT_HealthWellbeing_OP_A,0))="","",INDEX(ITT_HealthWellbeing_OP_E,MATCH("1.3",ITT_HealthWellbeing_OP_A,0))),"") | F52: =IFERROR(IF(INDEX(ITT_HealthWellbeing_OP_G,MATCH("1.3",ITT_HealthWellbeing_OP_A,0))="","",INDEX(ITT_HealthWellbeing_OP_G,MATCH("1.3",ITT_HealthWellbeing_OP_A,0))),"") | G52: =IFERROR(IF(INDEX(ITT_HealthWellbeing_OP_J,MATCH("1.3",ITT_HealthWellbeing_OP_A,0))="","",INDEX(ITT_HealthWellbeing_OP_J,MATCH("1.3",ITT_HealthWellbeing_OP_A,0))),"") | H52: =IFERROR(IF(INDEX(ITT_HealthWellbeing_OP_K,MATCH("1.3",ITT_HealthWellbeing_OP_A,0))="","",INDEX(ITT_HealthWellbeing_OP_K,MATCH("1.3",ITT_HealthWellbeing_OP_A,0))),"") | M52: =IF(OR(L52="",$G52="",$H52=""),"",IF($H52-$G52=0,"",(L52-$G52)/($H52-$G52))) | S52: =IF(OR(R52="",$G52="",$H52=""),"",IF($H52-$G52=0,"",(R52-$G52)/($H52-$G52))) | Y52: =IF(OR(X52="",$G52="",$H52=""),"",IF($H52-$G52=0,"",(X52-$G52)/($H52-$G52))) | AE52: =IF(OR(AD52="",$G52="",$H52=""),"",IF($H52-$G52=0,"",(AD52-$G52)/($H52-$G52))) | AK52: =IF(OR(AJ52="",$G52="",$H52=""),"",IF($H52-$G52=0,"",(AJ52-$G52)/($H52-$G52)))
C53: =IFERROR(IF(INDEX(ITT_HealthWellbeing_OP_A,MATCH("2.1",ITT_HealthWellbeing_OP_A,0))="","",INDEX(ITT_HealthWellbeing_OP_A,MATCH("2.1",ITT_HealthWellbeing_OP_A,0))),"") -> 2.1 | D53: =IFERROR(IF(INDEX(ITT_HealthWellbeing_OP_B,MATCH("2.1",ITT_HealthWellbeing_OP_A,0))="","",INDEX(ITT_HealthWellbeing_OP_B,MATCH("2.1",ITT_HealthWellbeing_OP_A,0))),"") | E53: =IFERROR(IF(INDEX(ITT_HealthWellbeing_OP_E,MATCH("2.1",ITT_HealthWellbeing_OP_A,0))="","",INDEX(ITT_HealthWellbeing_OP_E,MATCH("2.1",ITT_HealthWellbeing_OP_A,0))),"") | F53: =IFERROR(IF(INDEX(ITT_HealthWellbeing_OP_G,MATCH("2.1",ITT_HealthWellbeing_OP_A,0))="","",INDEX(ITT_HealthWellbeing_OP_G,MATCH("2.1",ITT_HealthWellbeing_OP_A,0))),"") | G53: =IFERROR(IF(INDEX(ITT_HealthWellbeing_OP_J,MATCH("2.1",ITT_HealthWellbeing_OP_A,0))="","",INDEX(ITT_HealthWellbeing_OP_J,MATCH("2.1",ITT_HealthWellbeing_OP_A,0))),"") | H53: =IFERROR(IF(INDEX(ITT_HealthWellbeing_OP_K,MATCH("2.1",ITT_HealthWellbeing_OP_A,0))="","",INDEX(ITT_HealthWellbeing_OP_K,MATCH("2.1",ITT_HealthWellbeing_OP_A,0))),"") | M53: =IF(OR(L53="",$G53="",$H53=""),"",IF($H53-$G53=0,"",(L53-$G53)/($H53-$G53))) | S53: =IF(OR(R53="",$G53="",$H53=""),"",IF($H53-$G53=0,"",(R53-$G53)/($H53-$G53))) | Y53: =IF(OR(X53="",$G53="",$H53=""),"",IF($H53-$G53=0,"",(X53-$G53)/($H53-$G53))) | AE53: =IF(OR(AD53="",$G53="",$H53=""),"",IF($H53-$G53=0,"",(AD53-$G53)/($H53-$G53))) | AK53: =IF(OR(AJ53="",$G53="",$H53=""),"",IF($H53-$G53=0,"",(AJ53-$G53)/($H53-$G53)))
C54: =IFERROR(IF(INDEX(ITT_HealthWellbeing_OP_A,MATCH("2.2",ITT_HealthWellbeing_OP_A,0))="","",INDEX(ITT_HealthWellbeing_OP_A,MATCH("2.2",ITT_HealthWellbeing_OP_A,0))),"") -> 2.2 | D54: =IFERROR(IF(INDEX(ITT_HealthWellbeing_OP_B,MATCH("2.2",ITT_HealthWellbeing_OP_A,0))="","",INDEX(ITT_HealthWellbeing_OP_B,MATCH("2.2",ITT_HealthWellbeing_OP_A,0))),"") | E54: =IFERROR(IF(INDEX(ITT_HealthWellbeing_OP_E,MATCH("2.2",ITT_HealthWellbeing_OP_A,0))="","",INDEX(ITT_HealthWellbeing_OP_E,MATCH("2.2",ITT_HealthWellbeing_OP_A,0))),"") | F54: =IFERROR(IF(INDEX(ITT_HealthWellbeing_OP_G,MATCH("2.2",ITT_HealthWellbeing_OP_A,0))="","",INDEX(ITT_HealthWellbeing_OP_G,MATCH("2.2",ITT_HealthWellbeing_OP_A,0))),"") | G54: =IFERROR(IF(INDEX(ITT_HealthWellbeing_OP_J,MATCH("2.2",ITT_HealthWellbeing_OP_A,0))="","",INDEX(ITT_HealthWellbeing_OP_J,MATCH("2.2",ITT_HealthWellbeing_OP_A,0))),"") | H54: =IFERROR(IF(INDEX(ITT_HealthWellbeing_OP_K,MATCH("2.2",ITT_HealthWellbeing_OP_A,0))="","",INDEX(ITT_HealthWellbeing_OP_K,MATCH("2.2",ITT_HealthWellbeing_OP_A,0))),"") | M54: =IF(OR(L54="",$G54="",$H54=""),"",IF($H54-$G54=0,"",(L54-$G54)/($H54-$G54))) | S54: =IF(OR(R54="",$G54="",$H54=""),"",IF($H54-$G54=0,"",(R54-$G54)/($H54-$G54))) | Y54: =IF(OR(X54="",$G54="",$H54=""),"",IF($H54-$G54=0,"",(X54-$G54)/($H54-$G54))) | AE54: =IF(OR(AD54="",$G54="",$H54=""),"",IF($H54-$G54=0,"",(AD54-$G54)/($H54-$G54))) | AK54: =IF(OR(AJ54="",$G54="",$H54=""),"",IF($H54-$G54=0,"",(AJ54-$G54)/($H54-$G54)))
C55: =IFERROR(IF(INDEX(ITT_HealthWellbeing_OP_A,MATCH("2.3",ITT_HealthWellbeing_OP_A,0))="","",INDEX(ITT_HealthWellbeing_OP_A,MATCH("2.3",ITT_HealthWellbeing_OP_A,0))),"") -> 2.3 | D55: =IFERROR(IF(INDEX(ITT_HealthWellbeing_OP_B,MATCH("2.3",ITT_HealthWellbeing_OP_A,0))="","",INDEX(ITT_HealthWellbeing_OP_B,MATCH("2.3",ITT_HealthWellbeing_OP_A,0))),"") | E55: =IFERROR(IF(INDEX(ITT_HealthWellbeing_OP_E,MATCH("2.3",ITT_HealthWellbeing_OP_A,0))="","",INDEX(ITT_HealthWellbeing_OP_E,MATCH("2.3",ITT_HealthWellbeing_OP_A,0))),"") | F55: =IFERROR(IF(INDEX(ITT_HealthWellbeing_OP_G,MATCH("2.3",ITT_HealthWellbeing_OP_A,0))="","",INDEX(ITT_HealthWellbeing_OP_G,MATCH("2.3",ITT_HealthWellbeing_OP_A,0))),"") | G55: =IFERROR(IF(INDEX(ITT_HealthWellbeing_OP_J,MATCH("2.3",ITT_HealthWellbeing_OP_A,0))="","",INDEX(ITT_HealthWellbeing_OP_J,MATCH("2.3",ITT_HealthWellbeing_OP_A,0))),"") | H55: =IFERROR(IF(INDEX(ITT_HealthWellbeing_OP_K,MATCH("2.3",ITT_HealthWellbeing_OP_A,0))="","",INDEX(ITT_HealthWellbeing_OP_K,MATCH("2.3",ITT_HealthWellbeing_OP_A,0))),"") | M55: =IF(OR(L55="",$G55="",$H55=""),"",IF($H55-$G55=0,"",(L55-$G55)/($H55-$G55))) | S55: =IF(OR(R55="",$G55="",$H55=""),"",IF($H55-$G55=0,"",(R55-$G55)/($H55-$G55))) | Y55: =IF(OR(X55="",$G55="",$H55=""),"",IF($H55-$G55=0,"",(X55-$G55)/($H55-$G55))) | AE55: =IF(OR(AD55="",$G55="",$H55=""),"",IF($H55-$G55=0,"",(AD55-$G55)/($H55-$G55))) | AK55: =IF(OR(AJ55="",$G55="",$H55=""),"",IF($H55-$G55=0,"",(AJ55-$G55)/($H55-$G55)))
C56: =IFERROR(IF(INDEX(ITT_HealthWellbeing_OP_A,MATCH("3.1",ITT_HealthWellbeing_OP_A,0))="","",INDEX(ITT_HealthWellbeing_OP_A,MATCH("3.1",ITT_HealthWellbeing_OP_A,0))),"") -> 3.1 | D56: =IFERROR(IF(INDEX(ITT_HealthWellbeing_OP_B,MATCH("3.1",ITT_HealthWellbeing_OP_A,0))="","",INDEX(ITT_HealthWellbeing_OP_B,MATCH("3.1",ITT_HealthWellbeing_OP_A,0))),"") | E56: =IFERROR(IF(INDEX(ITT_HealthWellbeing_OP_E,MATCH("3.1",ITT_HealthWellbeing_OP_A,0))="","",INDEX(ITT_HealthWellbeing_OP_E,MATCH("3.1",ITT_HealthWellbeing_OP_A,0))),"") | F56: =IFERROR(IF(INDEX(ITT_HealthWellbeing_OP_G,MATCH("3.1",ITT_HealthWellbeing_OP_A,0))="","",INDEX(ITT_HealthWellbeing_OP_G,MATCH("3.1",ITT_HealthWellbeing_OP_A,0))),"") | G56: =IFERROR(IF(INDEX(ITT_HealthWellbeing_OP_J,MATCH("3.1",ITT_HealthWellbeing_OP_A,0))="","",INDEX(ITT_HealthWellbeing_OP_J,MATCH("3.1",ITT_HealthWellbeing_OP_A,0))),"") | H56: =IFERROR(IF(INDEX(ITT_HealthWellbeing_OP_K,MATCH("3.1",ITT_HealthWellbeing_OP_A,0))="","",INDEX(ITT_HealthWellbeing_OP_K,MATCH("3.1",ITT_HealthWellbeing_OP_A,0))),"") | M56: =IF(OR(L56="",$G56="",$H56=""),"",IF($H56-$G56=0,"",(L56-$G56)/($H56-$G56))) | S56: =IF(OR(R56="",$G56="",$H56=""),"",IF($H56-$G56=0,"",(R56-$G56)/($H56-$G56))) | Y56: =IF(OR(X56="",$G56="",$H56=""),"",IF($H56-$G56=0,"",(X56-$G56)/($H56-$G56))) | AE56: =IF(OR(AD56="",$G56="",$H56=""),"",IF($H56-$G56=0,"",(AD56-$G56)/($H56-$G56))) | AK56: =IF(OR(AJ56="",$G56="",$H56=""),"",IF($H56-$G56=0,"",(AJ56-$G56)/($H56-$G56)))
C57: =IFERROR(IF(INDEX(ITT_HealthWellbeing_OP_A,MATCH("3.2",ITT_HealthWellbeing_OP_A,0))="","",INDEX(ITT_HealthWellbeing_OP_A,MATCH("3.2",ITT_HealthWellbeing_OP_A,0))),"") -> 3.2 | D57: =IFERROR(IF(INDEX(ITT_HealthWellbeing_OP_B,MATCH("3.2",ITT_HealthWellbeing_OP_A,0))="","",INDEX(ITT_HealthWellbeing_OP_B,MATCH("3.2",ITT_HealthWellbeing_OP_A,0))),"") | E57: =IFERROR(IF(INDEX(ITT_HealthWellbeing_OP_E,MATCH("3.2",ITT_HealthWellbeing_OP_A,0))="","",INDEX(ITT_HealthWellbeing_OP_E,MATCH("3.2",ITT_HealthWellbeing_OP_A,0))),"") | F57: =IFERROR(IF(INDEX(ITT_HealthWellbeing_OP_G,MATCH("3.2",ITT_HealthWellbeing_OP_A,0))="","",INDEX(ITT_HealthWellbeing_OP_G,MATCH("3.2",ITT_HealthWellbeing_OP_A,0))),"") | G57: =IFERROR(IF(INDEX(ITT_HealthWellbeing_OP_J,MATCH("3.2",ITT_HealthWellbeing_OP_A,0))="","",INDEX(ITT_HealthWellbeing_OP_J,MATCH("3.2",ITT_HealthWellbeing_OP_A,0))),"") | H57: =IFERROR(IF(INDEX(ITT_HealthWellbeing_OP_K,MATCH("3.2",ITT_HealthWellbeing_OP_A,0))="","",INDEX(ITT_HealthWellbeing_OP_K,MATCH("3.2",ITT_HealthWellbeing_OP_A,0))),"") | M57: =IF(OR(L57="",$G57="",$H57=""),"",IF($H57-$G57=0,"",(L57-$G57)/($H57-$G57))) | S57: =IF(OR(R57="",$G57="",$H57=""),"",IF($H57-$G57=0,"",(R57-$G57)/($H57-$G57))) | Y57: =IF(OR(X57="",$G57="",$H57=""),"",IF($H57-$G57=0,"",(X57-$G57)/($H57-$G57))) | AE57: =IF(OR(AD57="",$G57="",$H57=""),"",IF($H57-$G57=0,"",(AD57-$G57)/($H57-$G57))) | AK57: =IF(OR(AJ57="",$G57="",$H57=""),"",IF($H57-$G57=0,"",(AJ57-$G57)/($H57-$G57)))
C58: =IFERROR(IF(INDEX(ITT_HealthWellbeing_OP_A,MATCH("3.3",ITT_HealthWellbeing_OP_A,0))="","",INDEX(ITT_HealthWellbeing_OP_A,MATCH("3.3",ITT_HealthWellbeing_OP_A,0))),"") -> 3.3 | D58: =IFERROR(IF(INDEX(ITT_HealthWellbeing_OP_B,MATCH("3.3",ITT_HealthWellbeing_OP_A,0))="","",INDEX(ITT_HealthWellbeing_OP_B,MATCH("3.3",ITT_HealthWellbeing_OP_A,0))),"") | E58: =IFERROR(IF(INDEX(ITT_HealthWellbeing_OP_E,MATCH("3.3",ITT_HealthWellbeing_OP_A,0))="","",INDEX(ITT_HealthWellbeing_OP_E,MATCH("3.3",ITT_HealthWellbeing_OP_A,0))),"") | F58: =IFERROR(IF(INDEX(ITT_HealthWellbeing_OP_G,MATCH("3.3",ITT_HealthWellbeing_OP_A,0))="","",INDEX(ITT_HealthWellbeing_OP_G,MATCH("3.3",ITT_HealthWellbeing_OP_A,0))),"") | G58: =IFERROR(IF(INDEX(ITT_HealthWellbeing_OP_J,MATCH("3.3",ITT_HealthWellbeing_OP_A,0))="","",INDEX(ITT_HealthWellbeing_OP_J,MATCH("3.3",ITT_HealthWellbeing_OP_A,0))),"") | H58: =IFERROR(IF(INDEX(ITT_HealthWellbeing_OP_K,MATCH("3.3",ITT_HealthWellbeing_OP_A,0))="","",INDEX(ITT_HealthWellbeing_OP_K,MATCH("3.3",ITT_HealthWellbeing_OP_A,0))),"") | M58: =IF(OR(L58="",$G58="",$H58=""),"",IF($H58-$G58=0,"",(L58-$G58)/($H58-$G58))) | S58: =IF(OR(R58="",$G58="",$H58=""),"",IF($H58-$G58=0,"",(R58-$G58)/($H58-$G58))) | Y58: =IF(OR(X58="",$G58="",$H58=""),"",IF($H58-$G58=0,"",(X58-$G58)/($H58-$G58))) | AE58: =IF(OR(AD58="",$G58="",$H58=""),"",IF($H58-$G58=0,"",(AD58-$G58)/($H58-$G58))) | AK58: =IF(OR(AJ58="",$G58="",$H58=""),"",IF($H58-$G58=0,"",(AJ58-$G58)/($H58-$G58)))
C59: =IFERROR(IF(INDEX(ITT_HealthWellbeing_OP_A,MATCH("4.1",ITT_HealthWellbeing_OP_A,0))="","",INDEX(ITT_HealthWellbeing_OP_A,MATCH("4.1",ITT_HealthWellbeing_OP_A,0))),"") -> 4.1 | D59: =IFERROR(IF(INDEX(ITT_HealthWellbeing_OP_B,MATCH("4.1",ITT_HealthWellbeing_OP_A,0))="","",INDEX(ITT_HealthWellbeing_OP_B,MATCH("4.1",ITT_HealthWellbeing_OP_A,0))),"") | E59: =IFERROR(IF(INDEX(ITT_HealthWellbeing_OP_E,MATCH("4.1",ITT_HealthWellbeing_OP_A,0))="","",INDEX(ITT_HealthWellbeing_OP_E,MATCH("4.1",ITT_HealthWellbeing_OP_A,0))),"") | F59: =IFERROR(IF(INDEX(ITT_HealthWellbeing_OP_G,MATCH("4.1",ITT_HealthWellbeing_OP_A,0))="","",INDEX(ITT_HealthWellbeing_OP_G,MATCH("4.1",ITT_HealthWellbeing_OP_A,0))),"") | G59: =IFERROR(IF(INDEX(ITT_HealthWellbeing_OP_J,MATCH("4.1",ITT_HealthWellbeing_OP_A,0))="","",INDEX(ITT_HealthWellbeing_OP_J,MATCH("4.1",ITT_HealthWellbeing_OP_A,0))),"") | H59: =IFERROR(IF(INDEX(ITT_HealthWellbeing_OP_K,MATCH("4.1",ITT_HealthWellbeing_OP_A,0))="","",INDEX(ITT_HealthWellbeing_OP_K,MATCH("4.1",ITT_HealthWellbeing_OP_A,0))),"") | M59: =IF(OR(L59="",$G59="",$H59=""),"",IF($H59-$G59=0,"",(L59-$G59)/($H59-$G59))) | S59: =IF(OR(R59="",$G59="",$H59=""),"",IF($H59-$G59=0,"",(R59-$G59)/($H59-$G59))) | Y59: =IF(OR(X59="",$G59="",$H59=""),"",IF($H59-$G59=0,"",(X59-$G59)/($H59-$G59))) | AE59: =IF(OR(AD59="",$G59="",$H59=""),"",IF($H59-$G59=0,"",(AD59-$G59)/($H59-$G59))) | AK59: =IF(OR(AJ59="",$G59="",$H59=""),"",IF($H59-$G59=0,"",(AJ59-$G59)/($H59-$G59)))
C60: =IFERROR(IF(INDEX(ITT_HealthWellbeing_OP_A,MATCH("4.2",ITT_HealthWellbeing_OP_A,0))="","",INDEX(ITT_HealthWellbeing_OP_A,MATCH("4.2",ITT_HealthWellbeing_OP_A,0))),"") -> 4.2 | D60: =IFERROR(IF(INDEX(ITT_HealthWellbeing_OP_B,MATCH("4.2",ITT_HealthWellbeing_OP_A,0))="","",INDEX(ITT_HealthWellbeing_OP_B,MATCH("4.2",ITT_HealthWellbeing_OP_A,0))),"") | E60: =IFERROR(IF(INDEX(ITT_HealthWellbeing_OP_E,MATCH("4.2",ITT_HealthWellbeing_OP_A,0))="","",INDEX(ITT_HealthWellbeing_OP_E,MATCH("4.2",ITT_HealthWellbeing_OP_A,0))),"") | F60: =IFERROR(IF(INDEX(ITT_HealthWellbeing_OP_G,MATCH("4.2",ITT_HealthWellbeing_OP_A,0))="","",INDEX(ITT_HealthWellbeing_OP_G,MATCH("4.2",ITT_HealthWellbeing_OP_A,0))),"") | G60: =IFERROR(IF(INDEX(ITT_HealthWellbeing_OP_J,MATCH("4.2",ITT_HealthWellbeing_OP_A,0))="","",INDEX(ITT_HealthWellbeing_OP_J,MATCH("4.2",ITT_HealthWellbeing_OP_A,0))),"") | H60: =IFERROR(IF(INDEX(ITT_HealthWellbeing_OP_K,MATCH("4.2",ITT_HealthWellbeing_OP_A,0))="","",INDEX(ITT_HealthWellbeing_OP_K,MATCH("4.2",ITT_HealthWellbeing_OP_A,0))),"") | M60: =IF(OR(L60="",$G60="",$H60=""),"",IF($H60-$G60=0,"",(L60-$G60)/($H60-$G60))) | S60: =IF(OR(R60="",$G60="",$H60=""),"",IF($H60-$G60=0,"",(R60-$G60)/($H60-$G60))) | Y60: =IF(OR(X60="",$G60="",$H60=""),"",IF($H60-$G60=0,"",(X60-$G60)/($H60-$G60))) | AE60: =IF(OR(AD60="",$G60="",$H60=""),"",IF($H60-$G60=0,"",(AD60-$G60)/($H60-$G60))) | AK60: =IF(OR(AJ60="",$G60="",$H60=""),"",IF($H60-$G60=0,"",(AJ60-$G60)/($H60-$G60)))
C61: =IFERROR(IF(INDEX(ITT_HealthWellbeing_OP_A,MATCH("4.3",ITT_HealthWellbeing_OP_A,0))="","",INDEX(ITT_HealthWellbeing_OP_A,MATCH("4.3",ITT_HealthWellbeing_OP_A,0))),"") -> 4.3 | D61: =IFERROR(IF(INDEX(ITT_HealthWellbeing_OP_B,MATCH("4.3",ITT_HealthWellbeing_OP_A,0))="","",INDEX(ITT_HealthWellbeing_OP_B,MATCH("4.3",ITT_HealthWellbeing_OP_A,0))),"") | E61: =IFERROR(IF(INDEX(ITT_HealthWellbeing_OP_E,MATCH("4.3",ITT_HealthWellbeing_OP_A,0))="","",INDEX(ITT_HealthWellbeing_OP_E,MATCH("4.3",ITT_HealthWellbeing_OP_A,0))),"") | F61: =IFERROR(IF(INDEX(ITT_HealthWellbeing_OP_G,MATCH("4.3",ITT_HealthWellbeing_OP_A,0))="","",INDEX(ITT_HealthWellbeing_OP_G,MATCH("4.3",ITT_HealthWellbeing_OP_A,0))),"") | G61: =IFERROR(IF(INDEX(ITT_HealthWellbeing_OP_J,MATCH("4.3",ITT_HealthWellbeing_OP_A,0))="","",INDEX(ITT_HealthWellbeing_OP_J,MATCH("4.3",ITT_HealthWellbeing_OP_A,0))),"") | H61: =IFERROR(IF(INDEX(ITT_HealthWellbeing_OP_K,MATCH("4.3",ITT_HealthWellbeing_OP_A,0))="","",INDEX(ITT_HealthWellbeing_OP_K,MATCH("4.3",ITT_HealthWellbeing_OP_A,0))),"") | M61: =IF(OR(L61="",$G61="",$H61=""),"",IF($H61-$G61=0,"",(L61-$G61)/($H61-$G61))) | S61: =IF(OR(R61="",$G61="",$H61=""),"",IF($H61-$G61=0,"",(R61-$G61)/($H61-$G61))) | Y61: =IF(OR(X61="",$G61="",$H61=""),"",IF($H61-$G61=0,"",(X61-$G61)/($H61-$G61))) | AE61: =IF(OR(AD61="",$G61="",$H61=""),"",IF($H61-$G61=0,"",(AD61-$G61)/($H61-$G61))) | AK61: =IF(OR(AJ61="",$G61="",$H61=""),"",IF($H61-$G61=0,"",(AJ61-$G61)/($H61-$G61)))
C62: =IFERROR(IF(INDEX(ITT_HealthWellbeing_OP_A,MATCH("5.1",ITT_HealthWellbeing_OP_A,0))="","",INDEX(ITT_HealthWellbeing_OP_A,MATCH("5.1",ITT_HealthWellbeing_OP_A,0))),"") -> 5.1 | D62: =IFERROR(IF(INDEX(ITT_HealthWellbeing_OP_B,MATCH("5.1",ITT_HealthWellbeing_OP_A,0))="","",INDEX(ITT_HealthWellbeing_OP_B,MATCH("5.1",ITT_HealthWellbeing_OP_A,0))),"") | E62: =IFERROR(IF(INDEX(ITT_HealthWellbeing_OP_E,MATCH("5.1",ITT_HealthWellbeing_OP_A,0))="","",INDEX(ITT_HealthWellbeing_OP_E,MATCH("5.1",ITT_HealthWellbeing_OP_A,0))),"") | F62: =IFERROR(IF(INDEX(ITT_HealthWellbeing_OP_G,MATCH("5.1",ITT_HealthWellbeing_OP_A,0))="","",INDEX(ITT_HealthWellbeing_OP_G,MATCH("5.1",ITT_HealthWellbeing_OP_A,0))),"") | G62: =IFERROR(IF(INDEX(ITT_HealthWellbeing_OP_J,MATCH("5.1",ITT_HealthWellbeing_OP_A,0))="","",INDEX(ITT_HealthWellbeing_OP_J,MATCH("5.1",ITT_HealthWellbeing_OP_A,0))),"") | H62: =IFERROR(IF(INDEX(ITT_HealthWellbeing_OP_K,MATCH("5.1",ITT_HealthWellbeing_OP_A,0))="","",INDEX(ITT_HealthWellbeing_OP_K,MATCH("5.1",ITT_HealthWellbeing_OP_A,0))),"") | M62: =IF(OR(L62="",$G62="",$H62=""),"",IF($H62-$G62=0,"",(L62-$G62)/($H62-$G62))) | S62: =IF(OR(R62="",$G62="",$H62=""),"",IF($H62-$G62=0,"",(R62-$G62)/($H62-$G62))) | Y62: =IF(OR(X62="",$G62="",$H62=""),"",IF($H62-$G62=0,"",(X62-$G62)/($H62-$G62))) | AE62: =IF(OR(AD62="",$G62="",$H62=""),"",IF($H62-$G62=0,"",(AD62-$G62)/($H62-$G62))) | AK62: =IF(OR(AJ62="",$G62="",$H62=""),"",IF($H62-$G62=0,"",(AJ62-$G62)/($H62-$G62)))
C63: =IFERROR(IF(INDEX(ITT_HealthWellbeing_OP_A,MATCH("5.2",ITT_HealthWellbeing_OP_A,0))="","",INDEX(ITT_HealthWellbeing_OP_A,MATCH("5.2",ITT_HealthWellbeing_OP_A,0))),"") -> 5.2 | D63: =IFERROR(IF(INDEX(ITT_HealthWellbeing_OP_B,MATCH("5.2",ITT_HealthWellbeing_OP_A,0))="","",INDEX(ITT_HealthWellbeing_OP_B,MATCH("5.2",ITT_HealthWellbeing_OP_A,0))),"") | E63: =IFERROR(IF(INDEX(ITT_HealthWellbeing_OP_E,MATCH("5.2",ITT_HealthWellbeing_OP_A,0))="","",INDEX(ITT_HealthWellbeing_OP_E,MATCH("5.2",ITT_HealthWellbeing_OP_A,0))),"") | F63: =IFERROR(IF(INDEX(ITT_HealthWellbeing_OP_G,MATCH("5.2",ITT_HealthWellbeing_OP_A,0))="","",INDEX(ITT_HealthWellbeing_OP_G,MATCH("5.2",ITT_HealthWellbeing_OP_A,0))),"") | G63: =IFERROR(IF(INDEX(ITT_HealthWellbeing_OP_J,MATCH("5.2",ITT_HealthWellbeing_OP_A,0))="","",INDEX(ITT_HealthWellbeing_OP_J,MATCH("5.2",ITT_HealthWellbeing_OP_A,0))),"") | H63: =IFERROR(IF(INDEX(ITT_HealthWellbeing_OP_K,MATCH("5.2",ITT_HealthWellbeing_OP_A,0))="","",INDEX(ITT_HealthWellbeing_OP_K,MATCH("5.2",ITT_HealthWellbeing_OP_A,0))),"") | M63: =IF(OR(L63="",$G63="",$H63=""),"",IF($H63-$G63=0,"",(L63-$G63)/($H63-$G63))) | S63: =IF(OR(R63="",$G63="",$H63=""),"",IF($H63-$G63=0,"",(R63-$G63)/($H63-$G63))) | Y63: =IF(OR(X63="",$G63="",$H63=""),"",IF($H63-$G63=0,"",(X63-$G63)/($H63-$G63))) | AE63: =IF(OR(AD63="",$G63="",$H63=""),"",IF($H63-$G63=0,"",(AD63-$G63)/($H63-$G63))) | AK63: =IF(OR(AJ63="",$G63="",$H63=""),"",IF($H63-$G63=0,"",(AJ63-$G63)/($H63-$G63)))
C64: =IFERROR(IF(INDEX(ITT_HealthWellbeing_OP_A,MATCH("5.3",ITT_HealthWellbeing_OP_A,0))="","",INDEX(ITT_HealthWellbeing_OP_A,MATCH("5.3",ITT_HealthWellbeing_OP_A,0))),"") -> 5.3 | D64: =IFERROR(IF(INDEX(ITT_HealthWellbeing_OP_B,MATCH("5.3",ITT_HealthWellbeing_OP_A,0))="","",INDEX(ITT_HealthWellbeing_OP_B,MATCH("5.3",ITT_HealthWellbeing_OP_A,0))),"") | E64: =IFERROR(IF(INDEX(ITT_HealthWellbeing_OP_E,MATCH("5.3",ITT_HealthWellbeing_OP_A,0))="","",INDEX(ITT_HealthWellbeing_OP_E,MATCH("5.3",ITT_HealthWellbeing_OP_A,0))),"") | F64: =IFERROR(IF(INDEX(ITT_HealthWellbeing_OP_G,MATCH("5.3",ITT_HealthWellbeing_OP_A,0))="","",INDEX(ITT_HealthWellbeing_OP_G,MATCH("5.3",ITT_HealthWellbeing_OP_A,0))),"") | G64: =IFERROR(IF(INDEX(ITT_HealthWellbeing_OP_J,MATCH("5.3",ITT_HealthWellbeing_OP_A,0))="","",INDEX(ITT_HealthWellbeing_OP_J,MATCH("5.3",ITT_HealthWellbeing_OP_A,0))),"") | H64: =IFERROR(IF(INDEX(ITT_HealthWellbeing_OP_K,MATCH("5.3",ITT_HealthWellbeing_OP_A,0))="","",INDEX(ITT_HealthWellbeing_OP_K,MATCH("5.3",ITT_HealthWellbeing_OP_A,0))),"") | M64: =IF(OR(L64="",$G64="",$H64=""),"",IF($H64-$G64=0,"",(L64-$G64)/($H64-$G64))) | S64: =IF(OR(R64="",$G64="",$H64=""),"",IF($H64-$G64=0,"",(R64-$G64)/($H64-$G64))) | Y64: =IF(OR(X64="",$G64="",$H64=""),"",IF($H64-$G64=0,"",(X64-$G64)/($H64-$G64))) | AE64: =IF(OR(AD64="",$G64="",$H64=""),"",IF($H64-$G64=0,"",(AD64-$G64)/($H64-$G64))) | AK64: =IF(OR(AJ64="",$G64="",$H64=""),"",IF($H64-$G64=0,"",(AJ64-$G64)/($H64-$G64)))
A65: Economic Empowerment | B65: Outcome | C65: =IFERROR(IF(INDEX(ITT_EconomicEmpowerment_OC_A,MATCH("1",ITT_EconomicEmpowerment_OC_A,0))="","",INDEX(ITT_EconomicEmpowerment_OC_A,MATCH("1",ITT_EconomicEmpowerment_OC_A,0))),"") -> 1 | D65: =IFERROR(IF(INDEX(ITT_EconomicEmpowerment_OC_B,MATCH("1",ITT_EconomicEmpowerment_OC_A,0))="","",INDEX(ITT_EconomicEmpowerment_OC_B,MATCH("1",ITT_EconomicEmpowerment_OC_A,0))),"") | E65: =IFERROR(IF(INDEX(ITT_EconomicEmpowerment_OC_E,MATCH("1",ITT_EconomicEmpowerment_OC_A,0))="","",INDEX(ITT_EconomicEmpowerment_OC_E,MATCH("1",ITT_EconomicEmpowerment_OC_A,0))),"") | F65: =IFERROR(IF(INDEX(ITT_EconomicEmpowerment_OC_G,MATCH("1",ITT_EconomicEmpowerment_OC_A,0))="","",INDEX(ITT_EconomicEmpowerment_OC_G,MATCH("1",ITT_EconomicEmpowerment_OC_A,0))),"") | G65: =IFERROR(IF(INDEX(ITT_EconomicEmpowerment_OC_J,MATCH("1",ITT_EconomicEmpowerment_OC_A,0))="","",INDEX(ITT_EconomicEmpowerment_OC_J,MATCH("1",ITT_EconomicEmpowerment_OC_A,0))),"") | H65: =IFERROR(IF(INDEX(ITT_EconomicEmpowerment_OC_K,MATCH("1",ITT_EconomicEmpowerment_OC_A,0))="","",INDEX(ITT_EconomicEmpowerment_OC_K,MATCH("1",ITT_EconomicEmpowerment_OC_A,0))),"") | M65: =IF(OR(L65="",$G65="",$H65=""),"",IF($H65-$G65=0,"",(L65-$G65)/($H65-$G65))) | S65: =IF(OR(R65="",$G65="",$H65=""),"",IF($H65-$G65=0,"",(R65-$G65)/($H65-$G65))) | Y65: =IF(OR(X65="",$G65="",$H65=""),"",IF($H65-$G65=0,"",(X65-$G65)/($H65-$G65))) | AE65: =IF(OR(AD65="",$G65="",$H65=""),"",IF($H65-$G65=0,"",(AD65-$G65)/($H65-$G65))) | AK65: =IF(OR(AJ65="",$G65="",$H65=""),"",IF($H65-$G65=0,"",(AJ65-$G65)/($H65-$G65)))
C66: =IFERROR(IF(INDEX(ITT_EconomicEmpowerment_OC_A,MATCH("2",ITT_EconomicEmpowerment_OC_A,0))="","",INDEX(ITT_EconomicEmpowerment_OC_A,MATCH("2",ITT_EconomicEmpowerment_OC_A,0))),"") -> 2 | D66: =IFERROR(IF(INDEX(ITT_EconomicEmpowerment_OC_B,MATCH("2",ITT_EconomicEmpowerment_OC_A,0))="","",INDEX(ITT_EconomicEmpowerment_OC_B,MATCH("2",ITT_EconomicEmpowerment_OC_A,0))),"") | E66: =IFERROR(IF(INDEX(ITT_EconomicEmpowerment_OC_E,MATCH("2",ITT_EconomicEmpowerment_OC_A,0))="","",INDEX(ITT_EconomicEmpowerment_OC_E,MATCH("2",ITT_EconomicEmpowerment_OC_A,0))),"") | F66: =IFERROR(IF(INDEX(ITT_EconomicEmpowerment_OC_G,MATCH("2",ITT_EconomicEmpowerment_OC_A,0))="","",INDEX(ITT_EconomicEmpowerment_OC_G,MATCH("2",ITT_EconomicEmpowerment_OC_A,0))),"") | G66: =IFERROR(IF(INDEX(ITT_EconomicEmpowerment_OC_J,MATCH("2",ITT_EconomicEmpowerment_OC_A,0))="","",INDEX(ITT_EconomicEmpowerment_OC_J,MATCH("2",ITT_EconomicEmpowerment_OC_A,0))),"") | H66: =IFERROR(IF(INDEX(ITT_EconomicEmpowerment_OC_K,MATCH("2",ITT_EconomicEmpowerment_OC_A,0))="","",INDEX(ITT_EconomicEmpowerment_OC_K,MATCH("2",ITT_EconomicEmpowerment_OC_A,0))),"") | M66: =IF(OR(L66="",$G66="",$H66=""),"",IF($H66-$G66=0,"",(L66-$G66)/($H66-$G66))) | S66: =IF(OR(R66="",$G66="",$H66=""),"",IF($H66-$G66=0,"",(R66-$G66)/($H66-$G66))) | Y66: =IF(OR(X66="",$G66="",$H66=""),"",IF($H66-$G66=0,"",(X66-$G66)/($H66-$G66))) | AE66: =IF(OR(AD66="",$G66="",$H66=""),"",IF($H66-$G66=0,"",(AD66-$G66)/($H66-$G66))) | AK66: =IF(OR(AJ66="",$G66="",$H66=""),"",IF($H66-$G66=0,"",(AJ66-$G66)/($H66-$G66)))
C67: =IFERROR(IF(INDEX(ITT_EconomicEmpowerment_OC_A,MATCH("3",ITT_EconomicEmpowerment_OC_A,0))="","",INDEX(ITT_EconomicEmpowerment_OC_A,MATCH("3",ITT_EconomicEmpowerment_OC_A,0))),"") -> 3 | D67: =IFERROR(IF(INDEX(ITT_EconomicEmpowerment_OC_B,MATCH("3",ITT_EconomicEmpowerment_OC_A,0))="","",INDEX(ITT_EconomicEmpowerment_OC_B,MATCH("3",ITT_EconomicEmpowerment_OC_A,0))),"") | E67: =IFERROR(IF(INDEX(ITT_EconomicEmpowerment_OC_E,MATCH("3",ITT_EconomicEmpowerment_OC_A,0))="","",INDEX(ITT_EconomicEmpowerment_OC_E,MATCH("3",ITT_EconomicEmpowerment_OC_A,0))),"") | F67: =IFERROR(IF(INDEX(ITT_EconomicEmpowerment_OC_G,MATCH("3",ITT_EconomicEmpowerment_OC_A,0))="","",INDEX(ITT_EconomicEmpowerment_OC_G,MATCH("3",ITT_EconomicEmpowerment_OC_A,0))),"") | G67: =IFERROR(IF(INDEX(ITT_EconomicEmpowerment_OC_J,MATCH("3",ITT_EconomicEmpowerment_OC_A,0))="","",INDEX(ITT_EconomicEmpowerment_OC_J,MATCH("3",ITT_EconomicEmpowerment_OC_A,0))),"") | H67: =IFERROR(IF(INDEX(ITT_EconomicEmpowerment_OC_K,MATCH("3",ITT_EconomicEmpowerment_OC_A,0))="","",INDEX(ITT_EconomicEmpowerment_OC_K,MATCH("3",ITT_EconomicEmpowerment_OC_A,0))),"") | M67: =IF(OR(L67="",$G67="",$H67=""),"",IF($H67-$G67=0,"",(L67-$G67)/($H67-$G67))) | S67: =IF(OR(R67="",$G67="",$H67=""),"",IF($H67-$G67=0,"",(R67-$G67)/($H67-$G67))) | Y67: =IF(OR(X67="",$G67="",$H67=""),"",IF($H67-$G67=0,"",(X67-$G67)/($H67-$G67))) | AE67: =IF(OR(AD67="",$G67="",$H67=""),"",IF($H67-$G67=0,"",(AD67-$G67)/($H67-$G67))) | AK67: =IF(OR(AJ67="",$G67="",$H67=""),"",IF($H67-$G67=0,"",(AJ67-$G67)/($H67-$G67)))
C68: =IFERROR(IF(INDEX(ITT_EconomicEmpowerment_OC_A,MATCH("4",ITT_EconomicEmpowerment_OC_A,0))="","",INDEX(ITT_EconomicEmpowerment_OC_A,MATCH("4",ITT_EconomicEmpowerment_OC_A,0))),"") -> 4 | D68: =IFERROR(IF(INDEX(ITT_EconomicEmpowerment_OC_B,MATCH("4",ITT_EconomicEmpowerment_OC_A,0))="","",INDEX(ITT_EconomicEmpowerment_OC_B,MATCH("4",ITT_EconomicEmpowerment_OC_A,0))),"") | E68: =IFERROR(IF(INDEX(ITT_EconomicEmpowerment_OC_E,MATCH("4",ITT_EconomicEmpowerment_OC_A,0))="","",INDEX(ITT_EconomicEmpowerment_OC_E,MATCH("4",ITT_EconomicEmpowerment_OC_A,0))),"") | F68: =IFERROR(IF(INDEX(ITT_EconomicEmpowerment_OC_G,MATCH("4",ITT_EconomicEmpowerment_OC_A,0))="","",INDEX(ITT_EconomicEmpowerment_OC_G,MATCH("4",ITT_EconomicEmpowerment_OC_A,0))),"") | G68: =IFERROR(IF(INDEX(ITT_EconomicEmpowerment_OC_J,MATCH("4",ITT_EconomicEmpowerment_OC_A,0))="","",INDEX(ITT_EconomicEmpowerment_OC_J,MATCH("4",ITT_EconomicEmpowerment_OC_A,0))),"") | H68: =IFERROR(IF(INDEX(ITT_EconomicEmpowerment_OC_K,MATCH("4",ITT_EconomicEmpowerment_OC_A,0))="","",INDEX(ITT_EconomicEmpowerment_OC_K,MATCH("4",ITT_EconomicEmpowerment_OC_A,0))),"") | M68: =IF(OR(L68="",$G68="",$H68=""),"",IF($H68-$G68=0,"",(L68-$G68)/($H68-$G68))) | S68: =IF(OR(R68="",$G68="",$H68=""),"",IF($H68-$G68=0,"",(R68-$G68)/($H68-$G68))) | Y68: =IF(OR(X68="",$G68="",$H68=""),"",IF($H68-$G68=0,"",(X68-$G68)/($H68-$G68))) | AE68: =IF(OR(AD68="",$G68="",$H68=""),"",IF($H68-$G68=0,"",(AD68-$G68)/($H68-$G68))) | AK68: =IF(OR(AJ68="",$G68="",$H68=""),"",IF($H68-$G68=0,"",(AJ68-$G68)/($H68-$G68)))
C69: =IFERROR(IF(INDEX(ITT_EconomicEmpowerment_OC_A,MATCH("5",ITT_EconomicEmpowerment_OC_A,0))="","",INDEX(ITT_EconomicEmpowerment_OC_A,MATCH("5",ITT_EconomicEmpowerment_OC_A,0))),"") -> 5 | D69: =IFERROR(IF(INDEX(ITT_EconomicEmpowerment_OC_B,MATCH("5",ITT_EconomicEmpowerment_OC_A,0))="","",INDEX(ITT_EconomicEmpowerment_OC_B,MATCH("5",ITT_EconomicEmpowerment_OC_A,0))),"") | E69: =IFERROR(IF(INDEX(ITT_EconomicEmpowerment_OC_E,MATCH("5",ITT_EconomicEmpowerment_OC_A,0))="","",INDEX(ITT_EconomicEmpowerment_OC_E,MATCH("5",ITT_EconomicEmpowerment_OC_A,0))),"") | F69: =IFERROR(IF(INDEX(ITT_EconomicEmpowerment_OC_G,MATCH("5",ITT_EconomicEmpowerment_OC_A,0))="","",INDEX(ITT_EconomicEmpowerment_OC_G,MATCH("5",ITT_EconomicEmpowerment_OC_A,0))),"") | G69: =IFERROR(IF(INDEX(ITT_EconomicEmpowerment_OC_J,MATCH("5",ITT_EconomicEmpowerment_OC_A,0))="","",INDEX(ITT_EconomicEmpowerment_OC_J,MATCH("5",ITT_EconomicEmpowerment_OC_A,0))),"") | H69: =IFERROR(IF(INDEX(ITT_EconomicEmpowerment_OC_K,MATCH("5",ITT_EconomicEmpowerment_OC_A,0))="","",INDEX(ITT_EconomicEmpowerment_OC_K,MATCH("5",ITT_EconomicEmpowerment_OC_A,0))),"") | M69: =IF(OR(L69="",$G69="",$H69=""),"",IF($H69-$G69=0,"",(L69-$G69)/($H69-$G69))) | S69: =IF(OR(R69="",$G69="",$H69=""),"",IF($H69-$G69=0,"",(R69-$G69)/($H69-$G69))) | Y69: =IF(OR(X69="",$G69="",$H69=""),"",IF($H69-$G69=0,"",(X69-$G69)/($H69-$G69))) | AE69: =IF(OR(AD69="",$G69="",$H69=""),"",IF($H69-$G69=0,"",(AD69-$G69)/($H69-$G69))) | AK69: =IF(OR(AJ69="",$G69="",$H69=""),"",IF($H69-$G69=0,"",(AJ69-$G69)/($H69-$G69)))
B70: Output | C70: =IFERROR(IF(INDEX(ITT_EconomicEmpowerment_OP_A,MATCH("1.1",ITT_EconomicEmpowerment_OP_A,0))="","",INDEX(ITT_EconomicEmpowerment_OP_A,MATCH("1.1",ITT_EconomicEmpowerment_OP_A,0))),"") -> 1.1 | D70: =IFERROR(IF(INDEX(ITT_EconomicEmpowerment_OP_B,MATCH("1.1",ITT_EconomicEmpowerment_OP_A,0))="","",INDEX(ITT_EconomicEmpowerment_OP_B,MATCH("1.1",ITT_EconomicEmpowerment_OP_A,0))),"") | E70: =IFERROR(IF(INDEX(ITT_EconomicEmpowerment_OP_E,MATCH("1.1",ITT_EconomicEmpowerment_OP_A,0))="","",INDEX(ITT_EconomicEmpowerment_OP_E,MATCH("1.1",ITT_EconomicEmpowerment_OP_A,0))),"") | F70: =IFERROR(IF(INDEX(ITT_EconomicEmpowerment_OP_G,MATCH("1.1",ITT_EconomicEmpowerment_OP_A,0))="","",INDEX(ITT_EconomicEmpowerment_OP_G,MATCH("1.1",ITT_EconomicEmpowerment_OP_A,0))),"") | G70: =IFERROR(IF(INDEX(ITT_EconomicEmpowerment_OP_J,MATCH("1.1",ITT_EconomicEmpowerment_OP_A,0))="","",INDEX(ITT_EconomicEmpowerment_OP_J,MATCH("1.1",ITT_EconomicEmpowerment_OP_A,0))),"") | H70: =IFERROR(IF(INDEX(ITT_EconomicEmpowerment_OP_K,MATCH("1.1",ITT_EconomicEmpowerment_OP_A,0))="","",INDEX(ITT_EconomicEmpowerment_OP_K,MATCH("1.1",ITT_EconomicEmpowerment_OP_A,0))),"") | M70: =IF(OR(L70="",$G70="",$H70=""),"",IF($H70-$G70=0,"",(L70-$G70)/($H70-$G70))) | S70: =IF(OR(R70="",$G70="",$H70=""),"",IF($H70-$G70=0,"",(R70-$G70)/($H70-$G70))) | Y70: =IF(OR(X70="",$G70="",$H70=""),"",IF($H70-$G70=0,"",(X70-$G70)/($H70-$G70))) | AE70: =IF(OR(AD70="",$G70="",$H70=""),"",IF($H70-$G70=0,"",(AD70-$G70)/($H70-$G70))) | AK70: =IF(OR(AJ70="",$G70="",$H70=""),"",IF($H70-$G70=0,"",(AJ70-$G70)/($H70-$G70)))
C71: =IFERROR(IF(INDEX(ITT_EconomicEmpowerment_OP_A,MATCH("1.2",ITT_EconomicEmpowerment_OP_A,0))="","",INDEX(ITT_EconomicEmpowerment_OP_A,MATCH("1.2",ITT_EconomicEmpowerment_OP_A,0))),"") -> 1.2 | D71: =IFERROR(IF(INDEX(ITT_EconomicEmpowerment_OP_B,MATCH("1.2",ITT_EconomicEmpowerment_OP_A,0))="","",INDEX(ITT_EconomicEmpowerment_OP_B,MATCH("1.2",ITT_EconomicEmpowerment_OP_A,0))),"") | E71: =IFERROR(IF(INDEX(ITT_EconomicEmpowerment_OP_E,MATCH("1.2",ITT_EconomicEmpowerment_OP_A,0))="","",INDEX(ITT_EconomicEmpowerment_OP_E,MATCH("1.2",ITT_EconomicEmpowerment_OP_A,0))),"") | F71: =IFERROR(IF(INDEX(ITT_EconomicEmpowerment_OP_G,MATCH("1.2",ITT_EconomicEmpowerment_OP_A,0))="","",INDEX(ITT_EconomicEmpowerment_OP_G,MATCH("1.2",ITT_EconomicEmpowerment_OP_A,0))),"") | G71: =IFERROR(IF(INDEX(ITT_EconomicEmpowerment_OP_J,MATCH("1.2",ITT_EconomicEmpowerment_OP_A,0))="","",INDEX(ITT_EconomicEmpowerment_OP_J,MATCH("1.2",ITT_EconomicEmpowerment_OP_A,0))),"") | H71: =IFERROR(IF(INDEX(ITT_EconomicEmpowerment_OP_K,MATCH("1.2",ITT_EconomicEmpowerment_OP_A,0))="","",INDEX(ITT_EconomicEmpowerment_OP_K,MATCH("1.2",ITT_EconomicEmpowerment_OP_A,0))),"") | M71: =IF(OR(L71="",$G71="",$H71=""),"",IF($H71-$G71=0,"",(L71-$G71)/($H71-$G71))) | S71: =IF(OR(R71="",$G71="",$H71=""),"",IF($H71-$G71=0,"",(R71-$G71)/($H71-$G71))) | Y71: =IF(OR(X71="",$G71="",$H71=""),"",IF($H71-$G71=0,"",(X71-$G71)/($H71-$G71))) | AE71: =IF(OR(AD71="",$G71="",$H71=""),"",IF($H71-$G71=0,"",(AD71-$G71)/($H71-$G71))) | AK71: =IF(OR(AJ71="",$G71="",$H71=""),"",IF($H71-$G71=0,"",(AJ71-$G71)/($H71-$G71)))
C72: =IFERROR(IF(INDEX(ITT_EconomicEmpowerment_OP_A,MATCH("1.3",ITT_EconomicEmpowerment_OP_A,0))="","",INDEX(ITT_EconomicEmpowerment_OP_A,MATCH("1.3",ITT_EconomicEmpowerment_OP_A,0))),"") -> 1.3 | D72: =IFERROR(IF(INDEX(ITT_EconomicEmpowerment_OP_B,MATCH("1.3",ITT_EconomicEmpowerment_OP_A,0))="","",INDEX(ITT_EconomicEmpowerment_OP_B,MATCH("1.3",ITT_EconomicEmpowerment_OP_A,0))),"") | E72: =IFERROR(IF(INDEX(ITT_EconomicEmpowerment_OP_E,MATCH("1.3",ITT_EconomicEmpowerment_OP_A,0))="","",INDEX(ITT_EconomicEmpowerment_OP_E,MATCH("1.3",ITT_EconomicEmpowerment_OP_A,0))),"") | F72: =IFERROR(IF(INDEX(ITT_EconomicEmpowerment_OP_G,MATCH("1.3",ITT_EconomicEmpowerment_OP_A,0))="","",INDEX(ITT_EconomicEmpowerment_OP_G,MATCH("1.3",ITT_EconomicEmpowerment_OP_A,0))),"") | G72: =IFERROR(IF(INDEX(ITT_EconomicEmpowerment_OP_J,MATCH("1.3",ITT_EconomicEmpowerment_OP_A,0))="","",INDEX(ITT_EconomicEmpowerment_OP_J,MATCH("1.3",ITT_EconomicEmpowerment_OP_A,0))),"") | H72: =IFERROR(IF(INDEX(ITT_EconomicEmpowerment_OP_K,MATCH("1.3",ITT_EconomicEmpowerment_OP_A,0))="","",INDEX(ITT_EconomicEmpowerment_OP_K,MATCH("1.3",ITT_EconomicEmpowerment_OP_A,0))),"") | M72: =IF(OR(L72="",$G72="",$H72=""),"",IF($H72-$G72=0,"",(L72-$G72)/($H72-$G72))) | S72: =IF(OR(R72="",$G72="",$H72=""),"",IF($H72-$G72=0,"",(R72-$G72)/($H72-$G72))) | Y72: =IF(OR(X72="",$G72="",$H72=""),"",IF($H72-$G72=0,"",(X72-$G72)/($H72-$G72))) | AE72: =IF(OR(AD72="",$G72="",$H72=""),"",IF($H72-$G72=0,"",(AD72-$G72)/($H72-$G72))) | AK72: =IF(OR(AJ72="",$G72="",$H72=""),"",IF($H72-$G72=0,"",(AJ72-$G72)/($H72-$G72)))
C73: =IFERROR(IF(INDEX(ITT_EconomicEmpowerment_OP_A,MATCH("2.1",ITT_EconomicEmpowerment_OP_A,0))="","",INDEX(ITT_EconomicEmpowerment_OP_A,MATCH("2.1",ITT_EconomicEmpowerment_OP_A,0))),"") -> 2.1 | D73: =IFERROR(IF(INDEX(ITT_EconomicEmpowerment_OP_B,MATCH("2.1",ITT_EconomicEmpowerment_OP_A,0))="","",INDEX(ITT_EconomicEmpowerment_OP_B,MATCH("2.1",ITT_EconomicEmpowerment_OP_A,0))),"") | E73: =IFERROR(IF(INDEX(ITT_EconomicEmpowerment_OP_E,MATCH("2.1",ITT_EconomicEmpowerment_OP_A,0))="","",INDEX(ITT_EconomicEmpowerment_OP_E,MATCH("2.1",ITT_EconomicEmpowerment_OP_A,0))),"") | F73: =IFERROR(IF(INDEX(ITT_EconomicEmpowerment_OP_G,MATCH("2.1",ITT_EconomicEmpowerment_OP_A,0))="","",INDEX(ITT_EconomicEmpowerment_OP_G,MATCH("2.1",ITT_EconomicEmpowerment_OP_A,0))),"") | G73: =IFERROR(IF(INDEX(ITT_EconomicEmpowerment_OP_J,MATCH("2.1",ITT_EconomicEmpowerment_OP_A,0))="","",INDEX(ITT_EconomicEmpowerment_OP_J,MATCH("2.1",ITT_EconomicEmpowerment_OP_A,0))),"") | H73: =IFERROR(IF(INDEX(ITT_EconomicEmpowerment_OP_K,MATCH("2.1",ITT_EconomicEmpowerment_OP_A,0))="","",INDEX(ITT_EconomicEmpowerment_OP_K,MATCH("2.1",ITT_EconomicEmpowerment_OP_A,0))),"") | M73: =IF(OR(L73="",$G73="",$H73=""),"",IF($H73-$G73=0,"",(L73-$G73)/($H73-$G73))) | S73: =IF(OR(R73="",$G73="",$H73=""),"",IF($H73-$G73=0,"",(R73-$G73)/($H73-$G73))) | Y73: =IF(OR(X73="",$G73="",$H73=""),"",IF($H73-$G73=0,"",(X73-$G73)/($H73-$G73))) | AE73: =IF(OR(AD73="",$G73="",$H73=""),"",IF($H73-$G73=0,"",(AD73-$G73)/($H73-$G73))) | AK73: =IF(OR(AJ73="",$G73="",$H73=""),"",IF($H73-$G73=0,"",(AJ73-$G73)/($H73-$G73)))
C74: =IFERROR(IF(INDEX(ITT_EconomicEmpowerment_OP_A,MATCH("2.2",ITT_EconomicEmpowerment_OP_A,0))="","",INDEX(ITT_EconomicEmpowerment_OP_A,MATCH("2.2",ITT_EconomicEmpowerment_OP_A,0))),"") -> 2.2 | D74: =IFERROR(IF(INDEX(ITT_EconomicEmpowerment_OP_B,MATCH("2.2",ITT_EconomicEmpowerment_OP_A,0))="","",INDEX(ITT_EconomicEmpowerment_OP_B,MATCH("2.2",ITT_EconomicEmpowerment_OP_A,0))),"") | E74: =IFERROR(IF(INDEX(ITT_EconomicEmpowerment_OP_E,MATCH("2.2",ITT_EconomicEmpowerment_OP_A,0))="","",INDEX(ITT_EconomicEmpowerment_OP_E,MATCH("2.2",ITT_EconomicEmpowerment_OP_A,0))),"") | F74: =IFERROR(IF(INDEX(ITT_EconomicEmpowerment_OP_G,MATCH("2.2",ITT_EconomicEmpowerment_OP_A,0))="","",INDEX(ITT_EconomicEmpowerment_OP_G,MATCH("2.2",ITT_EconomicEmpowerment_OP_A,0))),"") | G74: =IFERROR(IF(INDEX(ITT_EconomicEmpowerment_OP_J,MATCH("2.2",ITT_EconomicEmpowerment_OP_A,0))="","",INDEX(ITT_EconomicEmpowerment_OP_J,MATCH("2.2",ITT_EconomicEmpowerment_OP_A,0))),"") | H74: =IFERROR(IF(INDEX(ITT_EconomicEmpowerment_OP_K,MATCH("2.2",ITT_EconomicEmpowerment_OP_A,0))="","",INDEX(ITT_EconomicEmpowerment_OP_K,MATCH("2.2",ITT_EconomicEmpowerment_OP_A,0))),"") | M74: =IF(OR(L74="",$G74="",$H74=""),"",IF($H74-$G74=0,"",(L74-$G74)/($H74-$G74))) | S74: =IF(OR(R74="",$G74="",$H74=""),"",IF($H74-$G74=0,"",(R74-$G74)/($H74-$G74))) | Y74: =IF(OR(X74="",$G74="",$H74=""),"",IF($H74-$G74=0,"",(X74-$G74)/($H74-$G74))) | AE74: =IF(OR(AD74="",$G74="",$H74=""),"",IF($H74-$G74=0,"",(AD74-$G74)/($H74-$G74))) | AK74: =IF(OR(AJ74="",$G74="",$H74=""),"",IF($H74-$G74=0,"",(AJ74-$G74)/($H74-$G74)))
C75: =IFERROR(IF(INDEX(ITT_EconomicEmpowerment_OP_A,MATCH("2.3",ITT_EconomicEmpowerment_OP_A,0))="","",INDEX(ITT_EconomicEmpowerment_OP_A,MATCH("2.3",ITT_EconomicEmpowerment_OP_A,0))),"") -> 2.3 | D75: =IFERROR(IF(INDEX(ITT_EconomicEmpowerment_OP_B,MATCH("2.3",ITT_EconomicEmpowerment_OP_A,0))="","",INDEX(ITT_EconomicEmpowerment_OP_B,MATCH("2.3",ITT_EconomicEmpowerment_OP_A,0))),"") | E75: =IFERROR(IF(INDEX(ITT_EconomicEmpowerment_OP_E,MATCH("2.3",ITT_EconomicEmpowerment_OP_A,0))="","",INDEX(ITT_EconomicEmpowerment_OP_E,MATCH("2.3",ITT_EconomicEmpowerment_OP_A,0))),"") | F75: =IFERROR(IF(INDEX(ITT_EconomicEmpowerment_OP_G,MATCH("2.3",ITT_EconomicEmpowerment_OP_A,0))="","",INDEX(ITT_EconomicEmpowerment_OP_G,MATCH("2.3",ITT_EconomicEmpowerment_OP_A,0))),"") | G75: =IFERROR(IF(INDEX(ITT_EconomicEmpowerment_OP_J,MATCH("2.3",ITT_EconomicEmpowerment_OP_A,0))="","",INDEX(ITT_EconomicEmpowerment_OP_J,MATCH("2.3",ITT_EconomicEmpowerment_OP_A,0))),"") | H75: =IFERROR(IF(INDEX(ITT_EconomicEmpowerment_OP_K,MATCH("2.3",ITT_EconomicEmpowerment_OP_A,0))="","",INDEX(ITT_EconomicEmpowerment_OP_K,MATCH("2.3",ITT_EconomicEmpowerment_OP_A,0))),"") | M75: =IF(OR(L75="",$G75="",$H75=""),"",IF($H75-$G75=0,"",(L75-$G75)/($H75-$G75))) | S75: =IF(OR(R75="",$G75="",$H75=""),"",IF($H75-$G75=0,"",(R75-$G75)/($H75-$G75))) | Y75: =IF(OR(X75="",$G75="",$H75=""),"",IF($H75-$G75=0,"",(X75-$G75)/($H75-$G75))) | AE75: =IF(OR(AD75="",$G75="",$H75=""),"",IF($H75-$G75=0,"",(AD75-$G75)/($H75-$G75))) | AK75: =IF(OR(AJ75="",$G75="",$H75=""),"",IF($H75-$G75=0,"",(AJ75-$G75)/($H75-$G75)))
C76: =IFERROR(IF(INDEX(ITT_EconomicEmpowerment_OP_A,MATCH("3.1",ITT_EconomicEmpowerment_OP_A,0))="","",INDEX(ITT_EconomicEmpowerment_OP_A,MATCH("3.1",ITT_EconomicEmpowerment_OP_A,0))),"") -> 3.1 | D76: =IFERROR(IF(INDEX(ITT_EconomicEmpowerment_OP_B,MATCH("3.1",ITT_EconomicEmpowerment_OP_A,0))="","",INDEX(ITT_EconomicEmpowerment_OP_B,MATCH("3.1",ITT_EconomicEmpowerment_OP_A,0))),"") | E76: =IFERROR(IF(INDEX(ITT_EconomicEmpowerment_OP_E,MATCH("3.1",ITT_EconomicEmpowerment_OP_A,0))="","",INDEX(ITT_EconomicEmpowerment_OP_E,MATCH("3.1",ITT_EconomicEmpowerment_OP_A,0))),"") | F76: =IFERROR(IF(INDEX(ITT_EconomicEmpowerment_OP_G,MATCH("3.1",ITT_EconomicEmpowerment_OP_A,0))="","",INDEX(ITT_EconomicEmpowerment_OP_G,MATCH("3.1",ITT_EconomicEmpowerment_OP_A,0))),"") | G76: =IFERROR(IF(INDEX(ITT_EconomicEmpowerment_OP_J,MATCH("3.1",ITT_EconomicEmpowerment_OP_A,0))="","",INDEX(ITT_EconomicEmpowerment_OP_J,MATCH("3.1",ITT_EconomicEmpowerment_OP_A,0))),"") | H76: =IFERROR(IF(INDEX(ITT_EconomicEmpowerment_OP_K,MATCH("3.1",ITT_EconomicEmpowerment_OP_A,0))="","",INDEX(ITT_EconomicEmpowerment_OP_K,MATCH("3.1",ITT_EconomicEmpowerment_OP_A,0))),"") | M76: =IF(OR(L76="",$G76="",$H76=""),"",IF($H76-$G76=0,"",(L76-$G76)/($H76-$G76))) | S76: =IF(OR(R76="",$G76="",$H76=""),"",IF($H76-$G76=0,"",(R76-$G76)/($H76-$G76))) | Y76: =IF(OR(X76="",$G76="",$H76=""),"",IF($H76-$G76=0,"",(X76-$G76)/($H76-$G76))) | AE76: =IF(OR(AD76="",$G76="",$H76=""),"",IF($H76-$G76=0,"",(AD76-$G76)/($H76-$G76))) | AK76: =IF(OR(AJ76="",$G76="",$H76=""),"",IF($H76-$G76=0,"",(AJ76-$G76)/($H76-$G76)))
C77: =IFERROR(IF(INDEX(ITT_EconomicEmpowerment_OP_A,MATCH("3.2",ITT_EconomicEmpowerment_OP_A,0))="","",INDEX(ITT_EconomicEmpowerment_OP_A,MATCH("3.2",ITT_EconomicEmpowerment_OP_A,0))),"") -> 3.2 | D77: =IFERROR(IF(INDEX(ITT_EconomicEmpowerment_OP_B,MATCH("3.2",ITT_EconomicEmpowerment_OP_A,0))="","",INDEX(ITT_EconomicEmpowerment_OP_B,MATCH("3.2",ITT_EconomicEmpowerment_OP_A,0))),"") | E77: =IFERROR(IF(INDEX(ITT_EconomicEmpowerment_OP_E,MATCH("3.2",ITT_EconomicEmpowerment_OP_A,0))="","",INDEX(ITT_EconomicEmpowerment_OP_E,MATCH("3.2",ITT_EconomicEmpowerment_OP_A,0))),"") | F77: =IFERROR(IF(INDEX(ITT_EconomicEmpowerment_OP_G,MATCH("3.2",ITT_EconomicEmpowerment_OP_A,0))="","",INDEX(ITT_EconomicEmpowerment_OP_G,MATCH("3.2",ITT_EconomicEmpowerment_OP_A,0))),"") | G77: =IFERROR(IF(INDEX(ITT_EconomicEmpowerment_OP_J,MATCH("3.2",ITT_EconomicEmpowerment_OP_A,0))="","",INDEX(ITT_EconomicEmpowerment_OP_J,MATCH("3.2",ITT_EconomicEmpowerment_OP_A,0))),"") | H77: =IFERROR(IF(INDEX(ITT_EconomicEmpowerment_OP_K,MATCH("3.2",ITT_EconomicEmpowerment_OP_A,0))="","",INDEX(ITT_EconomicEmpowerment_OP_K,MATCH("3.2",ITT_EconomicEmpowerment_OP_A,0))),"") | M77: =IF(OR(L77="",$G77="",$H77=""),"",IF($H77-$G77=0,"",(L77-$G77)/($H77-$G77))) | S77: =IF(OR(R77="",$G77="",$H77=""),"",IF($H77-$G77=0,"",(R77-$G77)/($H77-$G77))) | Y77: =IF(OR(X77="",$G77="",$H77=""),"",IF($H77-$G77=0,"",(X77-$G77)/($H77-$G77))) | AE77: =IF(OR(AD77="",$G77="",$H77=""),"",IF($H77-$G77=0,"",(AD77-$G77)/($H77-$G77))) | AK77: =IF(OR(AJ77="",$G77="",$H77=""),"",IF($H77-$G77=0,"",(AJ77-$G77)/($H77-$G77)))
C78: =IFERROR(IF(INDEX(ITT_EconomicEmpowerment_OP_A,MATCH("3.3",ITT_EconomicEmpowerment_OP_A,0))="","",INDEX(ITT_EconomicEmpowerment_OP_A,MATCH("3.3",ITT_EconomicEmpowerment_OP_A,0))),"") -> 3.3 | D78: =IFERROR(IF(INDEX(ITT_EconomicEmpowerment_OP_B,MATCH("3.3",ITT_EconomicEmpowerment_OP_A,0))="","",INDEX(ITT_EconomicEmpowerment_OP_B,MATCH("3.3",ITT_EconomicEmpowerment_OP_A,0))),"") | E78: =IFERROR(IF(INDEX(ITT_EconomicEmpowerment_OP_E,MATCH("3.3",ITT_EconomicEmpowerment_OP_A,0))="","",INDEX(ITT_EconomicEmpowerment_OP_E,MATCH("3.3",ITT_EconomicEmpowerment_OP_A,0))),"") | F78: =IFERROR(IF(INDEX(ITT_EconomicEmpowerment_OP_G,MATCH("3.3",ITT_EconomicEmpowerment_OP_A,0))="","",INDEX(ITT_EconomicEmpowerment_OP_G,MATCH("3.3",ITT_EconomicEmpowerment_OP_A,0))),"") | G78: =IFERROR(IF(INDEX(ITT_EconomicEmpowerment_OP_J,MATCH("3.3",ITT_EconomicEmpowerment_OP_A,0))="","",INDEX(ITT_EconomicEmpowerment_OP_J,MATCH("3.3",ITT_EconomicEmpowerment_OP_A,0))),"") | H78: =IFERROR(IF(INDEX(ITT_EconomicEmpowerment_OP_K,MATCH("3.3",ITT_EconomicEmpowerment_OP_A,0))="","",INDEX(ITT_EconomicEmpowerment_OP_K,MATCH("3.3",ITT_EconomicEmpowerment_OP_A,0))),"") | M78: =IF(OR(L78="",$G78="",$H78=""),"",IF($H78-$G78=0,"",(L78-$G78)/($H78-$G78))) | S78: =IF(OR(R78="",$G78="",$H78=""),"",IF($H78-$G78=0,"",(R78-$G78)/($H78-$G78))) | Y78: =IF(OR(X78="",$G78="",$H78=""),"",IF($H78-$G78=0,"",(X78-$G78)/($H78-$G78))) | AE78: =IF(OR(AD78="",$G78="",$H78=""),"",IF($H78-$G78=0,"",(AD78-$G78)/($H78-$G78))) | AK78: =IF(OR(AJ78="",$G78="",$H78=""),"",IF($H78-$G78=0,"",(AJ78-$G78)/($H78-$G78)))
C79: =IFERROR(IF(INDEX(ITT_EconomicEmpowerment_OP_A,MATCH("4.1",ITT_EconomicEmpowerment_OP_A,0))="","",INDEX(ITT_EconomicEmpowerment_OP_A,MATCH("4.1",ITT_EconomicEmpowerment_OP_A,0))),"") -> 4.1 | D79: =IFERROR(IF(INDEX(ITT_EconomicEmpowerment_OP_B,MATCH("4.1",ITT_EconomicEmpowerment_OP_A,0))="","",INDEX(ITT_EconomicEmpowerment_OP_B,MATCH("4.1",ITT_EconomicEmpowerment_OP_A,0))),"") | E79: =IFERROR(IF(INDEX(ITT_EconomicEmpowerment_OP_E,MATCH("4.1",ITT_EconomicEmpowerment_OP_A,0))="","",INDEX(ITT_EconomicEmpowerment_OP_E,MATCH("4.1",ITT_EconomicEmpowerment_OP_A,0))),"") | F79: =IFERROR(IF(INDEX(ITT_EconomicEmpowerment_OP_G,MATCH("4.1",ITT_EconomicEmpowerment_OP_A,0))="","",INDEX(ITT_EconomicEmpowerment_OP_G,MATCH("4.1",ITT_EconomicEmpowerment_OP_A,0))),"") | G79: =IFERROR(IF(INDEX(ITT_EconomicEmpowerment_OP_J,MATCH("4.1",ITT_EconomicEmpowerment_OP_A,0))="","",INDEX(ITT_EconomicEmpowerment_OP_J,MATCH("4.1",ITT_EconomicEmpowerment_OP_A,0))),"") | H79: =IFERROR(IF(INDEX(ITT_EconomicEmpowerment_OP_K,MATCH("4.1",ITT_EconomicEmpowerment_OP_A,0))="","",INDEX(ITT_EconomicEmpowerment_OP_K,MATCH("4.1",ITT_EconomicEmpowerment_OP_A,0))),"") | M79: =IF(OR(L79="",$G79="",$H79=""),"",IF($H79-$G79=0,"",(L79-$G79)/($H79-$G79))) | S79: =IF(OR(R79="",$G79="",$H79=""),"",IF($H79-$G79=0,"",(R79-$G79)/($H79-$G79))) | Y79: =IF(OR(X79="",$G79="",$H79=""),"",IF($H79-$G79=0,"",(X79-$G79)/($H79-$G79))) | AE79: =IF(OR(AD79="",$G79="",$H79=""),"",IF($H79-$G79=0,"",(AD79-$G79)/($H79-$G79))) | AK79: =IF(OR(AJ79="",$G79="",$H79=""),"",IF($H79-$G79=0,"",(AJ79-$G79)/($H79-$G79)))
C80: =IFERROR(IF(INDEX(ITT_EconomicEmpowerment_OP_A,MATCH("4.2",ITT_EconomicEmpowerment_OP_A,0))="","",INDEX(ITT_EconomicEmpowerment_OP_A,MATCH("4.2",ITT_EconomicEmpowerment_OP_A,0))),"") -> 4.2 | D80: =IFERROR(IF(INDEX(ITT_EconomicEmpowerment_OP_B,MATCH("4.2",ITT_EconomicEmpowerment_OP_A,0))="","",INDEX(ITT_EconomicEmpowerment_OP_B,MATCH("4.2",ITT_EconomicEmpowerment_OP_A,0))),"") | E80: =IFERROR(IF(INDEX(ITT_EconomicEmpowerment_OP_E,MATCH("4.2",ITT_EconomicEmpowerment_OP_A,0))="","",INDEX(ITT_EconomicEmpowerment_OP_E,MATCH("4.2",ITT_EconomicEmpowerment_OP_A,0))),"") | F80: =IFERROR(IF(INDEX(ITT_EconomicEmpowerment_OP_G,MATCH("4.2",ITT_EconomicEmpowerment_OP_A,0))="","",INDEX(ITT_EconomicEmpowerment_OP_G,MATCH("4.2",ITT_EconomicEmpowerment_OP_A,0))),"") | G80: =IFERROR(IF(INDEX(ITT_EconomicEmpowerment_OP_J,MATCH("4.2",ITT_EconomicEmpowerment_OP_A,0))="","",INDEX(ITT_EconomicEmpowerment_OP_J,MATCH("4.2",ITT_EconomicEmpowerment_OP_A,0))),"") | H80: =IFERROR(IF(INDEX(ITT_EconomicEmpowerment_OP_K,MATCH("4.2",ITT_EconomicEmpowerment_OP_A,0))="","",INDEX(ITT_EconomicEmpowerment_OP_K,MATCH("4.2",ITT_EconomicEmpowerment_OP_A,0))),"") | M80: =IF(OR(L80="",$G80="",$H80=""),"",IF($H80-$G80=0,"",(L80-$G80)/($H80-$G80))) | S80: =IF(OR(R80="",$G80="",$H80=""),"",IF($H80-$G80=0,"",(R80-$G80)/($H80-$G80))) | Y80: =IF(OR(X80="",$G80="",$H80=""),"",IF($H80-$G80=0,"",(X80-$G80)/($H80-$G80))) | AE80: =IF(OR(AD80="",$G80="",$H80=""),"",IF($H80-$G80=0,"",(AD80-$G80)/($H80-$G80))) | AK80: =IF(OR(AJ80="",$G80="",$H80=""),"",IF($H80-$G80=0,"",(AJ80-$G80)/($H80-$G80)))
C81: =IFERROR(IF(INDEX(ITT_EconomicEmpowerment_OP_A,MATCH("4.3",ITT_EconomicEmpowerment_OP_A,0))="","",INDEX(ITT_EconomicEmpowerment_OP_A,MATCH("4.3",ITT_EconomicEmpowerment_OP_A,0))),"") -> 4.3 | D81: =IFERROR(IF(INDEX(ITT_EconomicEmpowerment_OP_B,MATCH("4.3",ITT_EconomicEmpowerment_OP_A,0))="","",INDEX(ITT_EconomicEmpowerment_OP_B,MATCH("4.3",ITT_EconomicEmpowerment_OP_A,0))),"") | E81: =IFERROR(IF(INDEX(ITT_EconomicEmpowerment_OP_E,MATCH("4.3",ITT_EconomicEmpowerment_OP_A,0))="","",INDEX(ITT_EconomicEmpowerment_OP_E,MATCH("4.3",ITT_EconomicEmpowerment_OP_A,0))),"") | F81: =IFERROR(IF(INDEX(ITT_EconomicEmpowerment_OP_G,MATCH("4.3",ITT_EconomicEmpowerment_OP_A,0))="","",INDEX(ITT_EconomicEmpowerment_OP_G,MATCH("4.3",ITT_EconomicEmpowerment_OP_A,0))),"") | G81: =IFERROR(IF(INDEX(ITT_EconomicEmpowerment_OP_J,MATCH("4.3",ITT_EconomicEmpowerment_OP_A,0))="","",INDEX(ITT_EconomicEmpowerment_OP_J,MATCH("4.3",ITT_EconomicEmpowerment_OP_A,0))),"") | H81: =IFERROR(IF(INDEX(ITT_EconomicEmpowerment_OP_K,MATCH("4.3",ITT_EconomicEmpowerment_OP_A,0))="","",INDEX(ITT_EconomicEmpowerment_OP_K,MATCH("4.3",ITT_EconomicEmpowerment_OP_A,0))),"") | M81: =IF(OR(L81="",$G81="",$H81=""),"",IF($H81-$G81=0,"",(L81-$G81)/($H81-$G81))) | S81: =IF(OR(R81="",$G81="",$H81=""),"",IF($H81-$G81=0,"",(R81-$G81)/($H81-$G81))) | Y81: =IF(OR(X81="",$G81="",$H81=""),"",IF($H81-$G81=0,"",(X81-$G81)/($H81-$G81))) | AE81: =IF(OR(AD81="",$G81="",$H81=""),"",IF($H81-$G81=0,"",(AD81-$G81)/($H81-$G81))) | AK81: =IF(OR(AJ81="",$G81="",$H81=""),"",IF($H81-$G81=0,"",(AJ81-$G81)/($H81-$G81)))
C82: =IFERROR(IF(INDEX(ITT_EconomicEmpowerment_OP_A,MATCH("5.1",ITT_EconomicEmpowerment_OP_A,0))="","",INDEX(ITT_EconomicEmpowerment_OP_A,MATCH("5.1",ITT_EconomicEmpowerment_OP_A,0))),"") -> 5.1 | D82: =IFERROR(IF(INDEX(ITT_EconomicEmpowerment_OP_B,MATCH("5.1",ITT_EconomicEmpowerment_OP_A,0))="","",INDEX(ITT_EconomicEmpowerment_OP_B,MATCH("5.1",ITT_EconomicEmpowerment_OP_A,0))),"") | E82: =IFERROR(IF(INDEX(ITT_EconomicEmpowerment_OP_E,MATCH("5.1",ITT_EconomicEmpowerment_OP_A,0))="","",INDEX(ITT_EconomicEmpowerment_OP_E,MATCH("5.1",ITT_EconomicEmpowerment_OP_A,0))),"") | F82: =IFERROR(IF(INDEX(ITT_EconomicEmpowerment_OP_G,MATCH("5.1",ITT_EconomicEmpowerment_OP_A,0))="","",INDEX(ITT_EconomicEmpowerment_OP_G,MATCH("5.1",ITT_EconomicEmpowerment_OP_A,0))),"") | G82: =IFERROR(IF(INDEX(ITT_EconomicEmpowerment_OP_J,MATCH("5.1",ITT_EconomicEmpowerment_OP_A,0))="","",INDEX(ITT_EconomicEmpowerment_OP_J,MATCH("5.1",ITT_EconomicEmpowerment_OP_A,0))),"") | H82: =IFERROR(IF(INDEX(ITT_EconomicEmpowerment_OP_K,MATCH("5.1",ITT_EconomicEmpowerment_OP_A,0))="","",INDEX(ITT_EconomicEmpowerment_OP_K,MATCH("5.1",ITT_EconomicEmpowerment_OP_A,0))),"") | M82: =IF(OR(L82="",$G82="",$H82=""),"",IF($H82-$G82=0,"",(L82-$G82)/($H82-$G82))) | S82: =IF(OR(R82="",$G82="",$H82=""),"",IF($H82-$G82=0,"",(R82-$G82)/($H82-$G82))) | Y82: =IF(OR(X82="",$G82="",$H82=""),"",IF($H82-$G82=0,"",(X82-$G82)/($H82-$G82))) | AE82: =IF(OR(AD82="",$G82="",$H82=""),"",IF($H82-$G82=0,"",(AD82-$G82)/($H82-$G82))) | AK82: =IF(OR(AJ82="",$G82="",$H82=""),"",IF($H82-$G82=0,"",(AJ82-$G82)/($H82-$G82)))
C83: =IFERROR(IF(INDEX(ITT_EconomicEmpowerment_OP_A,MATCH("5.2",ITT_EconomicEmpowerment_OP_A,0))="","",INDEX(ITT_EconomicEmpowerment_OP_A,MATCH("5.2",ITT_EconomicEmpowerment_OP_A,0))),"") -> 5.2 | D83: =IFERROR(IF(INDEX(ITT_EconomicEmpowerment_OP_B,MATCH("5.2",ITT_EconomicEmpowerment_OP_A,0))="","",INDEX(ITT_EconomicEmpowerment_OP_B,MATCH("5.2",ITT_EconomicEmpowerment_OP_A,0))),"") | E83: =IFERROR(IF(INDEX(ITT_EconomicEmpowerment_OP_E,MATCH("5.2",ITT_EconomicEmpowerment_OP_A,0))="","",INDEX(ITT_EconomicEmpowerment_OP_E,MATCH("5.2",ITT_EconomicEmpowerment_OP_A,0))),"") | F83: =IFERROR(IF(INDEX(ITT_EconomicEmpowerment_OP_G,MATCH("5.2",ITT_EconomicEmpowerment_OP_A,0))="","",INDEX(ITT_EconomicEmpowerment_OP_G,MATCH("5.2",ITT_EconomicEmpowerment_OP_A,0))),"") | G83: =IFERROR(IF(INDEX(ITT_EconomicEmpowerment_OP_J,MATCH("5.2",ITT_EconomicEmpowerment_OP_A,0))="","",INDEX(ITT_EconomicEmpowerment_OP_J,MATCH("5.2",ITT_EconomicEmpowerment_OP_A,0))),"") | H83: =IFERROR(IF(INDEX(ITT_EconomicEmpowerment_OP_K,MATCH("5.2",ITT_EconomicEmpowerment_OP_A,0))="","",INDEX(ITT_EconomicEmpowerment_OP_K,MATCH("5.2",ITT_EconomicEmpowerment_OP_A,0))),"") | M83: =IF(OR(L83="",$G83="",$H83=""),"",IF($H83-$G83=0,"",(L83-$G83)/($H83-$G83))) | S83: =IF(OR(R83="",$G83="",$H83=""),"",IF($H83-$G83=0,"",(R83-$G83)/($H83-$G83))) | Y83: =IF(OR(X83="",$G83="",$H83=""),"",IF($H83-$G83=0,"",(X83-$G83)/($H83-$G83))) | AE83: =IF(OR(AD83="",$G83="",$H83=""),"",IF($H83-$G83=0,"",(AD83-$G83)/($H83-$G83))) | AK83: =IF(OR(AJ83="",$G83="",$H83=""),"",IF($H83-$G83=0,"",(AJ83-$G83)/($H83-$G83)))
C84: =IFERROR(IF(INDEX(ITT_EconomicEmpowerment_OP_A,MATCH("5.3",ITT_EconomicEmpowerment_OP_A,0))="","",INDEX(ITT_EconomicEmpowerment_OP_A,MATCH("5.3",ITT_EconomicEmpowerment_OP_A,0))),"") -> 5.3 | D84: =IFERROR(IF(INDEX(ITT_EconomicEmpowerment_OP_B,MATCH("5.3",ITT_EconomicEmpowerment_OP_A,0))="","",INDEX(ITT_EconomicEmpowerment_OP_B,MATCH("5.3",ITT_EconomicEmpowerment_OP_A,0))),"") | E84: =IFERROR(IF(INDEX(ITT_EconomicEmpowerment_OP_E,MATCH("5.3",ITT_EconomicEmpowerment_OP_A,0))="","",INDEX(ITT_EconomicEmpowerment_OP_E,MATCH("5.3",ITT_EconomicEmpowerment_OP_A,0))),"") | F84: =IFERROR(IF(INDEX(ITT_EconomicEmpowerment_OP_G,MATCH("5.3",ITT_EconomicEmpowerment_OP_A,0))="","",INDEX(ITT_EconomicEmpowerment_OP_G,MATCH("5.3",ITT_EconomicEmpowerment_OP_A,0))),"") | G84: =IFERROR(IF(INDEX(ITT_EconomicEmpowerment_OP_J,MATCH("5.3",ITT_EconomicEmpowerment_OP_A,0))="","",INDEX(ITT_EconomicEmpowerment_OP_J,MATCH("5.3",ITT_EconomicEmpowerment_OP_A,0))),"") | H84: =IFERROR(IF(INDEX(ITT_EconomicEmpowerment_OP_K,MATCH("5.3",ITT_EconomicEmpowerment_OP_A,0))="","",INDEX(ITT_EconomicEmpowerment_OP_K,MATCH("5.3",ITT_EconomicEmpowerment_OP_A,0))),"") | M84: =IF(OR(L84="",$G84="",$H84=""),"",IF($H84-$G84=0,"",(L84-$G84)/($H84-$G84))) | S84: =IF(OR(R84="",$G84="",$H84=""),"",IF($H84-$G84=0,"",(R84-$G84)/($H84-$G84))) | Y84: =IF(OR(X84="",$G84="",$H84=""),"",IF($H84-$G84=0,"",(X84-$G84)/($H84-$G84))) | AE84: =IF(OR(AD84="",$G84="",$H84=""),"",IF($H84-$G84=0,"",(AD84-$G84)/($H84-$G84))) | AK84: =IF(OR(AJ84="",$G84="",$H84=""),"",IF($H84-$G84=0,"",(AJ84-$G84)/($H84-$G84)))
A85: Others | B85: Outcome | C85: =IFERROR(IF(INDEX(ITT_Others_OC_A,MATCH("1",ITT_Others_OC_A,0))="","",INDEX(ITT_Others_OC_A,MATCH("1",ITT_Others_OC_A,0))),"") -> 1 | D85: =IFERROR(IF(INDEX(ITT_Others_OC_B,MATCH("1",ITT_Others_OC_A,0))="","",INDEX(ITT_Others_OC_B,MATCH("1",ITT_Others_OC_A,0))),"") | E85: =IFERROR(IF(INDEX(ITT_Others_OC_E,MATCH("1",ITT_Others_OC_A,0))="","",INDEX(ITT_Others_OC_E,MATCH("1",ITT_Others_OC_A,0))),"") | F85: =IFERROR(IF(INDEX(ITT_Others_OC_G,MATCH("1",ITT_Others_OC_A,0))="","",INDEX(ITT_Others_OC_G,MATCH("1",ITT_Others_OC_A,0))),"") | G85: =IFERROR(IF(INDEX(ITT_Others_OC_J,MATCH("1",ITT_Others_OC_A,0))="","",INDEX(ITT_Others_OC_J,MATCH("1",ITT_Others_OC_A,0))),"") | H85: =IFERROR(IF(INDEX(ITT_Others_OC_K,MATCH("1",ITT_Others_OC_A,0))="","",INDEX(ITT_Others_OC_K,MATCH("1",ITT_Others_OC_A,0))),"") | M85: =IF(OR(L85="",$G85="",$H85=""),"",IF($H85-$G85=0,"",(L85-$G85)/($H85-$G85))) | S85: =IF(OR(R85="",$G85="",$H85=""),"",IF($H85-$G85=0,"",(R85-$G85)/($H85-$G85))) | Y85: =IF(OR(X85="",$G85="",$H85=""),"",IF($H85-$G85=0,"",(X85-$G85)/($H85-$G85))) | AE85: =IF(OR(AD85="",$G85="",$H85=""),"",IF($H85-$G85=0,"",(AD85-$G85)/($H85-$G85))) | AK85: =IF(OR(AJ85="",$G85="",$H85=""),"",IF($H85-$G85=0,"",(AJ85-$G85)/($H85-$G85)))
C86: =IFERROR(IF(INDEX(ITT_Others_OC_A,MATCH("2",ITT_Others_OC_A,0))="","",INDEX(ITT_Others_OC_A,MATCH("2",ITT_Others_OC_A,0))),"") -> 2 | D86: =IFERROR(IF(INDEX(ITT_Others_OC_B,MATCH("2",ITT_Others_OC_A,0))="","",INDEX(ITT_Others_OC_B,MATCH("2",ITT_Others_OC_A,0))),"") | E86: =IFERROR(IF(INDEX(ITT_Others_OC_E,MATCH("2",ITT_Others_OC_A,0))="","",INDEX(ITT_Others_OC_E,MATCH("2",ITT_Others_OC_A,0))),"") | F86: =IFERROR(IF(INDEX(ITT_Others_OC_G,MATCH("2",ITT_Others_OC_A,0))="","",INDEX(ITT_Others_OC_G,MATCH("2",ITT_Others_OC_A,0))),"") | G86: =IFERROR(IF(INDEX(ITT_Others_OC_J,MATCH("2",ITT_Others_OC_A,0))="","",INDEX(ITT_Others_OC_J,MATCH("2",ITT_Others_OC_A,0))),"") | H86: =IFERROR(IF(INDEX(ITT_Others_OC_K,MATCH("2",ITT_Others_OC_A,0))="","",INDEX(ITT_Others_OC_K,MATCH("2",ITT_Others_OC_A,0))),"") | M86: =IF(OR(L86="",$G86="",$H86=""),"",IF($H86-$G86=0,"",(L86-$G86)/($H86-$G86))) | S86: =IF(OR(R86="",$G86="",$H86=""),"",IF($H86-$G86=0,"",(R86-$G86)/($H86-$G86))) | Y86: =IF(OR(X86="",$G86="",$H86=""),"",IF($H86-$G86=0,"",(X86-$G86)/($H86-$G86))) | AE86: =IF(OR(AD86="",$G86="",$H86=""),"",IF($H86-$G86=0,"",(AD86-$G86)/($H86-$G86))) | AK86: =IF(OR(AJ86="",$G86="",$H86=""),"",IF($H86-$G86=0,"",(AJ86-$G86)/($H86-$G86)))
C87: =IFERROR(IF(INDEX(ITT_Others_OC_A,MATCH("3",ITT_Others_OC_A,0))="","",INDEX(ITT_Others_OC_A,MATCH("3",ITT_Others_OC_A,0))),"") -> 3 | D87: =IFERROR(IF(INDEX(ITT_Others_OC_B,MATCH("3",ITT_Others_OC_A,0))="","",INDEX(ITT_Others_OC_B,MATCH("3",ITT_Others_OC_A,0))),"") | E87: =IFERROR(IF(INDEX(ITT_Others_OC_E,MATCH("3",ITT_Others_OC_A,0))="","",INDEX(ITT_Others_OC_E,MATCH("3",ITT_Others_OC_A,0))),"") | F87: =IFERROR(IF(INDEX(ITT_Others_OC_G,MATCH("3",ITT_Others_OC_A,0))="","",INDEX(ITT_Others_OC_G,MATCH("3",ITT_Others_OC_A,0))),"") | G87: =IFERROR(IF(INDEX(ITT_Others_OC_J,MATCH("3",ITT_Others_OC_A,0))="","",INDEX(ITT_Others_OC_J,MATCH("3",ITT_Others_OC_A,0))),"") | H87: =IFERROR(IF(INDEX(ITT_Others_OC_K,MATCH("3",ITT_Others_OC_A,0))="","",INDEX(ITT_Others_OC_K,MATCH("3",ITT_Others_OC_A,0))),"") | M87: =IF(OR(L87="",$G87="",$H87=""),"",IF($H87-$G87=0,"",(L87-$G87)/($H87-$G87))) | S87: =IF(OR(R87="",$G87="",$H87=""),"",IF($H87-$G87=0,"",(R87-$G87)/($H87-$G87))) | Y87: =IF(OR(X87="",$G87="",$H87=""),"",IF($H87-$G87=0,"",(X87-$G87)/($H87-$G87))) | AE87: =IF(OR(AD87="",$G87="",$H87=""),"",IF($H87-$G87=0,"",(AD87-$G87)/($H87-$G87))) | AK87: =IF(OR(AJ87="",$G87="",$H87=""),"",IF($H87-$G87=0,"",(AJ87-$G87)/($H87-$G87)))
C88: =IFERROR(IF(INDEX(ITT_Others_OC_A,MATCH("4",ITT_Others_OC_A,0))="","",INDEX(ITT_Others_OC_A,MATCH("4",ITT_Others_OC_A,0))),"") -> 4 | D88: =IFERROR(IF(INDEX(ITT_Others_OC_B,MATCH("4",ITT_Others_OC_A,0))="","",INDEX(ITT_Others_OC_B,MATCH("4",ITT_Others_OC_A,0))),"") | E88: =IFERROR(IF(INDEX(ITT_Others_OC_E,MATCH("4",ITT_Others_OC_A,0))="","",INDEX(ITT_Others_OC_E,MATCH("4",ITT_Others_OC_A,0))),"") | F88: =IFERROR(IF(INDEX(ITT_Others_OC_G,MATCH("4",ITT_Others_OC_A,0))="","",INDEX(ITT_Others_OC_G,MATCH("4",ITT_Others_OC_A,0))),"") | G88: =IFERROR(IF(INDEX(ITT_Others_OC_J,MATCH("4",ITT_Others_OC_A,0))="","",INDEX(ITT_Others_OC_J,MATCH("4",ITT_Others_OC_A,0))),"") | H88: =IFERROR(IF(INDEX(ITT_Others_OC_K,MATCH("4",ITT_Others_OC_A,0))="","",INDEX(ITT_Others_OC_K,MATCH("4",ITT_Others_OC_A,0))),"") | M88: =IF(OR(L88="",$G88="",$H88=""),"",IF($H88-$G88=0,"",(L88-$G88)/($H88-$G88))) | S88: =IF(OR(R88="",$G88="",$H88=""),"",IF($H88-$G88=0,"",(R88-$G88)/($H88-$G88))) | Y88: =IF(OR(X88="",$G88="",$H88=""),"",IF($H88-$G88=0,"",(X88-$G88)/($H88-$G88))) | AE88: =IF(OR(AD88="",$G88="",$H88=""),"",IF($H88-$G88=0,"",(AD88-$G88)/($H88-$G88))) | AK88: =IF(OR(AJ88="",$G88="",$H88=""),"",IF($H88-$G88=0,"",(AJ88-$G88)/($H88-$G88)))
C89: =IFERROR(IF(INDEX(ITT_Others_OC_A,MATCH("5",ITT_Others_OC_A,0))="","",INDEX(ITT_Others_OC_A,MATCH("5",ITT_Others_OC_A,0))),"") -> 5 | D89: =IFERROR(IF(INDEX(ITT_Others_OC_B,MATCH("5",ITT_Others_OC_A,0))="","",INDEX(ITT_Others_OC_B,MATCH("5",ITT_Others_OC_A,0))),"") | E89: =IFERROR(IF(INDEX(ITT_Others_OC_E,MATCH("5",ITT_Others_OC_A,0))="","",INDEX(ITT_Others_OC_E,MATCH("5",ITT_Others_OC_A,0))),"") | F89: =IFERROR(IF(INDEX(ITT_Others_OC_G,MATCH("5",ITT_Others_OC_A,0))="","",INDEX(ITT_Others_OC_G,MATCH("5",ITT_Others_OC_A,0))),"") | G89: =IFERROR(IF(INDEX(ITT_Others_OC_J,MATCH("5",ITT_Others_OC_A,0))="","",INDEX(ITT_Others_OC_J,MATCH("5",ITT_Others_OC_A,0))),"") | H89: =IFERROR(IF(INDEX(ITT_Others_OC_K,MATCH("5",ITT_Others_OC_A,0))="","",INDEX(ITT_Others_OC_K,MATCH("5",ITT_Others_OC_A,0))),"") | M89: =IF(OR(L89="",$G89="",$H89=""),"",IF($H89-$G89=0,"",(L89-$G89)/($H89-$G89))) | S89: =IF(OR(R89="",$G89="",$H89=""),"",IF($H89-$G89=0,"",(R89-$G89)/($H89-$G89))) | Y89: =IF(OR(X89="",$G89="",$H89=""),"",IF($H89-$G89=0,"",(X89-$G89)/($H89-$G89))) | AE89: =IF(OR(AD89="",$G89="",$H89=""),"",IF($H89-$G89=0,"",(AD89-$G89)/($H89-$G89))) | AK89: =IF(OR(AJ89="",$G89="",$H89=""),"",IF($H89-$G89=0,"",(AJ89-$G89)/($H89-$G89)))
B90: Output | C90: =IFERROR(IF(INDEX(ITT_Others_OP_A,MATCH("1.1",ITT_Others_OP_A,0))="","",INDEX(ITT_Others_OP_A,MATCH("1.1",ITT_Others_OP_A,0))),"") -> 1.1 | D90: =IFERROR(IF(INDEX(ITT_Others_OP_B,MATCH("1.1",ITT_Others_OP_A,0))="","",INDEX(ITT_Others_OP_B,MATCH("1.1",ITT_Others_OP_A,0))),"") | E90: =IFERROR(IF(INDEX(ITT_Others_OP_E,MATCH("1.1",ITT_Others_OP_A,0))="","",INDEX(ITT_Others_OP_E,MATCH("1.1",ITT_Others_OP_A,0))),"") | F90: =IFERROR(IF(INDEX(ITT_Others_OP_G,MATCH("1.1",ITT_Others_OP_A,0))="","",INDEX(ITT_Others_OP_G,MATCH("1.1",ITT_Others_OP_A,0))),"") | G90: =IFERROR(IF(INDEX(ITT_Others_OP_J,MATCH("1.1",ITT_Others_OP_A,0))="","",INDEX(ITT_Others_OP_J,MATCH("1.1",ITT_Others_OP_A,0))),"") | H90: =IFERROR(IF(INDEX(ITT_Others_OP_K,MATCH("1.1",ITT_Others_OP_A,0))="","",INDEX(ITT_Others_OP_K,MATCH("1.1",ITT_Others_OP_A,0))),"") | M90: =IF(OR(L90="",$G90="",$H90=""),"",IF($H90-$G90=0,"",(L90-$G90)/($H90-$G90))) | S90: =IF(OR(R90="",$G90="",$H90=""),"",IF($H90-$G90=0,"",(R90-$G90)/($H90-$G90))) | Y90: =IF(OR(X90="",$G90="",$H90=""),"",IF($H90-$G90=0,"",(X90-$G90)/($H90-$G90))) | AE90: =IF(OR(AD90="",$G90="",$H90=""),"",IF($H90-$G90=0,"",(AD90-$G90)/($H90-$G90))) | AK90: =IF(OR(AJ90="",$G90="",$H90=""),"",IF($H90-$G90=0,"",(AJ90-$G90)/($H90-$G90)))
C91: =IFERROR(IF(INDEX(ITT_Others_OP_A,MATCH("1.2",ITT_Others_OP_A,0))="","",INDEX(ITT_Others_OP_A,MATCH("1.2",ITT_Others_OP_A,0))),"") -> 1.2 | D91: =IFERROR(IF(INDEX(ITT_Others_OP_B,MATCH("1.2",ITT_Others_OP_A,0))="","",INDEX(ITT_Others_OP_B,MATCH("1.2",ITT_Others_OP_A,0))),"") | E91: =IFERROR(IF(INDEX(ITT_Others_OP_E,MATCH("1.2",ITT_Others_OP_A,0))="","",INDEX(ITT_Others_OP_E,MATCH("1.2",ITT_Others_OP_A,0))),"") | F91: =IFERROR(IF(INDEX(ITT_Others_OP_G,MATCH("1.2",ITT_Others_OP_A,0))="","",INDEX(ITT_Others_OP_G,MATCH("1.2",ITT_Others_OP_A,0))),"") | G91: =IFERROR(IF(INDEX(ITT_Others_OP_J,MATCH("1.2",ITT_Others_OP_A,0))="","",INDEX(ITT_Others_OP_J,MATCH("1.2",ITT_Others_OP_A,0))),"") | H91: =IFERROR(IF(INDEX(ITT_Others_OP_K,MATCH("1.2",ITT_Others_OP_A,0))="","",INDEX(ITT_Others_OP_K,MATCH("1.2",ITT_Others_OP_A,0))),"") | M91: =IF(OR(L91="",$G91="",$H91=""),"",IF($H91-$G91=0,"",(L91-$G91)/($H91-$G91))) | S91: =IF(OR(R91="",$G91="",$H91=""),"",IF($H91-$G91=0,"",(R91-$G91)/($H91-$G91))) | Y91: =IF(OR(X91="",$G91="",$H91=""),"",IF($H91-$G91=0,"",(X91-$G91)/($H91-$G91))) | AE91: =IF(OR(AD91="",$G91="",$H91=""),"",IF($H91-$G91=0,"",(AD91-$G91)/($H91-$G91))) | AK91: =IF(OR(AJ91="",$G91="",$H91=""),"",IF($H91-$G91=0,"",(AJ91-$G91)/($H91-$G91)))
C92: =IFERROR(IF(INDEX(ITT_Others_OP_A,MATCH("1.3",ITT_Others_OP_A,0))="","",INDEX(ITT_Others_OP_A,MATCH("1.3",ITT_Others_OP_A,0))),"") -> 1.3 | D92: =IFERROR(IF(INDEX(ITT_Others_OP_B,MATCH("1.3",ITT_Others_OP_A,0))="","",INDEX(ITT_Others_OP_B,MATCH("1.3",ITT_Others_OP_A,0))),"") | E92: =IFERROR(IF(INDEX(ITT_Others_OP_E,MATCH("1.3",ITT_Others_OP_A,0))="","",INDEX(ITT_Others_OP_E,MATCH("1.3",ITT_Others_OP_A,0))),"") | F92: =IFERROR(IF(INDEX(ITT_Others_OP_G,MATCH("1.3",ITT_Others_OP_A,0))="","",INDEX(ITT_Others_OP_G,MATCH("1.3",ITT_Others_OP_A,0))),"") | G92: =IFERROR(IF(INDEX(ITT_Others_OP_J,MATCH("1.3",ITT_Others_OP_A,0))="","",INDEX(ITT_Others_OP_J,MATCH("1.3",ITT_Others_OP_A,0))),"") | H92: =IFERROR(IF(INDEX(ITT_Others_OP_K,MATCH("1.3",ITT_Others_OP_A,0))="","",INDEX(ITT_Others_OP_K,MATCH("1.3",ITT_Others_OP_A,0))),"") | M92: =IF(OR(L92="",$G92="",$H92=""),"",IF($H92-$G92=0,"",(L92-$G92)/($H92-$G92))) | S92: =IF(OR(R92="",$G92="",$H92=""),"",IF($H92-$G92=0,"",(R92-$G92)/($H92-$G92))) | Y92: =IF(OR(X92="",$G92="",$H92=""),"",IF($H92-$G92=0,"",(X92-$G92)/($H92-$G92))) | AE92: =IF(OR(AD92="",$G92="",$H92=""),"",IF($H92-$G92=0,"",(AD92-$G92)/($H92-$G92))) | AK92: =IF(OR(AJ92="",$G92="",$H92=""),"",IF($H92-$G92=0,"",(AJ92-$G92)/($H92-$G92)))
C93: =IFERROR(IF(INDEX(ITT_Others_OP_A,MATCH("2.1",ITT_Others_OP_A,0))="","",INDEX(ITT_Others_OP_A,MATCH("2.1",ITT_Others_OP_A,0))),"") -> 2.1 | D93: =IFERROR(IF(INDEX(ITT_Others_OP_B,MATCH("2.1",ITT_Others_OP_A,0))="","",INDEX(ITT_Others_OP_B,MATCH("2.1",ITT_Others_OP_A,0))),"") | E93: =IFERROR(IF(INDEX(ITT_Others_OP_E,MATCH("2.1",ITT_Others_OP_A,0))="","",INDEX(ITT_Others_OP_E,MATCH("2.1",ITT_Others_OP_A,0))),"") | F93: =IFERROR(IF(INDEX(ITT_Others_OP_G,MATCH("2.1",ITT_Others_OP_A,0))="","",INDEX(ITT_Others_OP_G,MATCH("2.1",ITT_Others_OP_A,0))),"") | G93: =IFERROR(IF(INDEX(ITT_Others_OP_J,MATCH("2.1",ITT_Others_OP_A,0))="","",INDEX(ITT_Others_OP_J,MATCH("2.1",ITT_Others_OP_A,0))),"") | H93: =IFERROR(IF(INDEX(ITT_Others_OP_K,MATCH("2.1",ITT_Others_OP_A,0))="","",INDEX(ITT_Others_OP_K,MATCH("2.1",ITT_Others_OP_A,0))),"") | M93: =IF(OR(L93="",$G93="",$H93=""),"",IF($H93-$G93=0,"",(L93-$G93)/($H93-$G93))) | S93: =IF(OR(R93="",$G93="",$H93=""),"",IF($H93-$G93=0,"",(R93-$G93)/($H93-$G93))) | Y93: =IF(OR(X93="",$G93="",$H93=""),"",IF($H93-$G93=0,"",(X93-$G93)/($H93-$G93))) | AE93: =IF(OR(AD93="",$G93="",$H93=""),"",IF($H93-$G93=0,"",(AD93-$G93)/($H93-$G93))) | AK93: =IF(OR(AJ93="",$G93="",$H93=""),"",IF($H93-$G93=0,"",(AJ93-$G93)/($H93-$G93)))
C94: =IFERROR(IF(INDEX(ITT_Others_OP_A,MATCH("2.2",ITT_Others_OP_A,0))="","",INDEX(ITT_Others_OP_A,MATCH("2.2",ITT_Others_OP_A,0))),"") -> 2.2 | D94: =IFERROR(IF(INDEX(ITT_Others_OP_B,MATCH("2.2",ITT_Others_OP_A,0))="","",INDEX(ITT_Others_OP_B,MATCH("2.2",ITT_Others_OP_A,0))),"") | E94: =IFERROR(IF(INDEX(ITT_Others_OP_E,MATCH("2.2",ITT_Others_OP_A,0))="","",INDEX(ITT_Others_OP_E,MATCH("2.2",ITT_Others_OP_A,0))),"") | F94: =IFERROR(IF(INDEX(ITT_Others_OP_G,MATCH("2.2",ITT_Others_OP_A,0))="","",INDEX(ITT_Others_OP_G,MATCH("2.2",ITT_Others_OP_A,0))),"") | G94: =IFERROR(IF(INDEX(ITT_Others_OP_J,MATCH("2.2",ITT_Others_OP_A,0))="","",INDEX(ITT_Others_OP_J,MATCH("2.2",ITT_Others_OP_A,0))),"") | H94: =IFERROR(IF(INDEX(ITT_Others_OP_K,MATCH("2.2",ITT_Others_OP_A,0))="","",INDEX(ITT_Others_OP_K,MATCH("2.2",ITT_Others_OP_A,0))),"") | M94: =IF(OR(L94="",$G94="",$H94=""),"",IF($H94-$G94=0,"",(L94-$G94)/($H94-$G94))) | S94: =IF(OR(R94="",$G94="",$H94=""),"",IF($H94-$G94=0,"",(R94-$G94)/($H94-$G94))) | Y94: =IF(OR(X94="",$G94="",$H94=""),"",IF($H94-$G94=0,"",(X94-$G94)/($H94-$G94))) | AE94: =IF(OR(AD94="",$G94="",$H94=""),"",IF($H94-$G94=0,"",(AD94-$G94)/($H94-$G94))) | AK94: =IF(OR(AJ94="",$G94="",$H94=""),"",IF($H94-$G94=0,"",(AJ94-$G94)/($H94-$G94)))
C95: =IFERROR(IF(INDEX(ITT_Others_OP_A,MATCH("2.3",ITT_Others_OP_A,0))="","",INDEX(ITT_Others_OP_A,MATCH("2.3",ITT_Others_OP_A,0))),"") -> 2.3 | D95: =IFERROR(IF(INDEX(ITT_Others_OP_B,MATCH("2.3",ITT_Others_OP_A,0))="","",INDEX(ITT_Others_OP_B,MATCH("2.3",ITT_Others_OP_A,0))),"") | E95: =IFERROR(IF(INDEX(ITT_Others_OP_E,MATCH("2.3",ITT_Others_OP_A,0))="","",INDEX(ITT_Others_OP_E,MATCH("2.3",ITT_Others_OP_A,0))),"") | F95: =IFERROR(IF(INDEX(ITT_Others_OP_G,MATCH("2.3",ITT_Others_OP_A,0))="","",INDEX(ITT_Others_OP_G,MATCH("2.3",ITT_Others_OP_A,0))),"") | G95: =IFERROR(IF(INDEX(ITT_Others_OP_J,MATCH("2.3",ITT_Others_OP_A,0))="","",INDEX(ITT_Others_OP_J,MATCH("2.3",ITT_Others_OP_A,0))),"") | H95: =IFERROR(IF(INDEX(ITT_Others_OP_K,MATCH("2.3",ITT_Others_OP_A,0))="","",INDEX(ITT_Others_OP_K,MATCH("2.3",ITT_Others_OP_A,0))),"") | M95: =IF(OR(L95="",$G95="",$H95=""),"",IF($H95-$G95=0,"",(L95-$G95)/($H95-$G95))) | S95: =IF(OR(R95="",$G95="",$H95=""),"",IF($H95-$G95=0,"",(R95-$G95)/($H95-$G95))) | Y95: =IF(OR(X95="",$G95="",$H95=""),"",IF($H95-$G95=0,"",(X95-$G95)/($H95-$G95))) | AE95: =IF(OR(AD95="",$G95="",$H95=""),"",IF($H95-$G95=0,"",(AD95-$G95)/($H95-$G95))) | AK95: =IF(OR(AJ95="",$G95="",$H95=""),"",IF($H95-$G95=0,"",(AJ95-$G95)/($H95-$G95)))
C96: =IFERROR(IF(INDEX(ITT_Others_OP_A,MATCH("3.1",ITT_Others_OP_A,0))="","",INDEX(ITT_Others_OP_A,MATCH("3.1",ITT_Others_OP_A,0))),"") -> 3.1 | D96: =IFERROR(IF(INDEX(ITT_Others_OP_B,MATCH("3.1",ITT_Others_OP_A,0))="","",INDEX(ITT_Others_OP_B,MATCH("3.1",ITT_Others_OP_A,0))),"") | E96: =IFERROR(IF(INDEX(ITT_Others_OP_E,MATCH("3.1",ITT_Others_OP_A,0))="","",INDEX(ITT_Others_OP_E,MATCH("3.1",ITT_Others_OP_A,0))),"") | F96: =IFERROR(IF(INDEX(ITT_Others_OP_G,MATCH("3.1",ITT_Others_OP_A,0))="","",INDEX(ITT_Others_OP_G,MATCH("3.1",ITT_Others_OP_A,0))),"") | G96: =IFERROR(IF(INDEX(ITT_Others_OP_J,MATCH("3.1",ITT_Others_OP_A,0))="","",INDEX(ITT_Others_OP_J,MATCH("3.1",ITT_Others_OP_A,0))),"") | H96: =IFERROR(IF(INDEX(ITT_Others_OP_K,MATCH("3.1",ITT_Others_OP_A,0))="","",INDEX(ITT_Others_OP_K,MATCH("3.1",ITT_Others_OP_A,0))),"") | M96: =IF(OR(L96="",$G96="",$H96=""),"",IF($H96-$G96=0,"",(L96-$G96)/($H96-$G96))) | S96: =IF(OR(R96="",$G96="",$H96=""),"",IF($H96-$G96=0,"",(R96-$G96)/($H96-$G96))) | Y96: =IF(OR(X96="",$G96="",$H96=""),"",IF($H96-$G96=0,"",(X96-$G96)/($H96-$G96))) | AE96: =IF(OR(AD96="",$G96="",$H96=""),"",IF($H96-$G96=0,"",(AD96-$G96)/($H96-$G96))) | AK96: =IF(OR(AJ96="",$G96="",$H96=""),"",IF($H96-$G96=0,"",(AJ96-$G96)/($H96-$G96)))
C97: =IFERROR(IF(INDEX(ITT_Others_OP_A,MATCH("3.2",ITT_Others_OP_A,0))="","",INDEX(ITT_Others_OP_A,MATCH("3.2",ITT_Others_OP_A,0))),"") -> 3.2 | D97: =IFERROR(IF(INDEX(ITT_Others_OP_B,MATCH("3.2",ITT_Others_OP_A,0))="","",INDEX(ITT_Others_OP_B,MATCH("3.2",ITT_Others_OP_A,0))),"") | E97: =IFERROR(IF(INDEX(ITT_Others_OP_E,MATCH("3.2",ITT_Others_OP_A,0))="","",INDEX(ITT_Others_OP_E,MATCH("3.2",ITT_Others_OP_A,0))),"") | F97: =IFERROR(IF(INDEX(ITT_Others_OP_G,MATCH("3.2",ITT_Others_OP_A,0))="","",INDEX(ITT_Others_OP_G,MATCH("3.2",ITT_Others_OP_A,0))),"") | G97: =IFERROR(IF(INDEX(ITT_Others_OP_J,MATCH("3.2",ITT_Others_OP_A,0))="","",INDEX(ITT_Others_OP_J,MATCH("3.2",ITT_Others_OP_A,0))),"") | H97: =IFERROR(IF(INDEX(ITT_Others_OP_K,MATCH("3.2",ITT_Others_OP_A,0))="","",INDEX(ITT_Others_OP_K,MATCH("3.2",ITT_Others_OP_A,0))),"") | M97: =IF(OR(L97="",$G97="",$H97=""),"",IF($H97-$G97=0,"",(L97-$G97)/($H97-$G97))) | S97: =IF(OR(R97="",$G97="",$H97=""),"",IF($H97-$G97=0,"",(R97-$G97)/($H97-$G97))) | Y97: =IF(OR(X97="",$G97="",$H97=""),"",IF($H97-$G97=0,"",(X97-$G97)/($H97-$G97))) | AE97: =IF(OR(AD97="",$G97="",$H97=""),"",IF($H97-$G97=0,"",(AD97-$G97)/($H97-$G97))) | AK97: =IF(OR(AJ97="",$G97="",$H97=""),"",IF($H97-$G97=0,"",(AJ97-$G97)/($H97-$G97)))
C98: =IFERROR(IF(INDEX(ITT_Others_OP_A,MATCH("3.3",ITT_Others_OP_A,0))="","",INDEX(ITT_Others_OP_A,MATCH("3.3",ITT_Others_OP_A,0))),"") -> 3.3 | D98: =IFERROR(IF(INDEX(ITT_Others_OP_B,MATCH("3.3",ITT_Others_OP_A,0))="","",INDEX(ITT_Others_OP_B,MATCH("3.3",ITT_Others_OP_A,0))),"") | E98: =IFERROR(IF(INDEX(ITT_Others_OP_E,MATCH("3.3",ITT_Others_OP_A,0))="","",INDEX(ITT_Others_OP_E,MATCH("3.3",ITT_Others_OP_A,0))),"") | F98: =IFERROR(IF(INDEX(ITT_Others_OP_G,MATCH("3.3",ITT_Others_OP_A,0))="","",INDEX(ITT_Others_OP_G,MATCH("3.3",ITT_Others_OP_A,0))),"") | G98: =IFERROR(IF(INDEX(ITT_Others_OP_J,MATCH("3.3",ITT_Others_OP_A,0))="","",INDEX(ITT_Others_OP_J,MATCH("3.3",ITT_Others_OP_A,0))),"") | H98: =IFERROR(IF(INDEX(ITT_Others_OP_K,MATCH("3.3",ITT_Others_OP_A,0))="","",INDEX(ITT_Others_OP_K,MATCH("3.3",ITT_Others_OP_A,0))),"") | M98: =IF(OR(L98="",$G98="",$H98=""),"",IF($H98-$G98=0,"",(L98-$G98)/($H98-$G98))) | S98: =IF(OR(R98="",$G98="",$H98=""),"",IF($H98-$G98=0,"",(R98-$G98)/($H98-$G98))) | Y98: =IF(OR(X98="",$G98="",$H98=""),"",IF($H98-$G98=0,"",(X98-$G98)/($H98-$G98))) | AE98: =IF(OR(AD98="",$G98="",$H98=""),"",IF($H98-$G98=0,"",(AD98-$G98)/($H98-$G98))) | AK98: =IF(OR(AJ98="",$G98="",$H98=""),"",IF($H98-$G98=0,"",(AJ98-$G98)/($H98-$G98)))
C99: =IFERROR(IF(INDEX(ITT_Others_OP_A,MATCH("4.1",ITT_Others_OP_A,0))="","",INDEX(ITT_Others_OP_A,MATCH("4.1",ITT_Others_OP_A,0))),"") -> 4.1 | D99: =IFERROR(IF(INDEX(ITT_Others_OP_B,MATCH("4.1",ITT_Others_OP_A,0))="","",INDEX(ITT_Others_OP_B,MATCH("4.1",ITT_Others_OP_A,0))),"") | E99: =IFERROR(IF(INDEX(ITT_Others_OP_E,MATCH("4.1",ITT_Others_OP_A,0))="","",INDEX(ITT_Others_OP_E,MATCH("4.1",ITT_Others_OP_A,0))),"") | F99: =IFERROR(IF(INDEX(ITT_Others_OP_G,MATCH("4.1",ITT_Others_OP_A,0))="","",INDEX(ITT_Others_OP_G,MATCH("4.1",ITT_Others_OP_A,0))),"") | G99: =IFERROR(IF(INDEX(ITT_Others_OP_J,MATCH("4.1",ITT_Others_OP_A,0))="","",INDEX(ITT_Others_OP_J,MATCH("4.1",ITT_Others_OP_A,0))),"") | H99: =IFERROR(IF(INDEX(ITT_Others_OP_K,MATCH("4.1",ITT_Others_OP_A,0))="","",INDEX(ITT_Others_OP_K,MATCH("4.1",ITT_Others_OP_A,0))),"") | M99: =IF(OR(L99="",$G99="",$H99=""),"",IF($H99-$G99=0,"",(L99-$G99)/($H99-$G99))) | S99: =IF(OR(R99="",$G99="",$H99=""),"",IF($H99-$G99=0,"",(R99-$G99)/($H99-$G99))) | Y99: =IF(OR(X99="",$G99="",$H99=""),"",IF($H99-$G99=0,"",(X99-$G99)/($H99-$G99))) | AE99: =IF(OR(AD99="",$G99="",$H99=""),"",IF($H99-$G99=0,"",(AD99-$G99)/($H99-$G99))) | AK99: =IF(OR(AJ99="",$G99="",$H99=""),"",IF($H99-$G99=0,"",(AJ99-$G99)/($H99-$G99)))
C100: =IFERROR(IF(INDEX(ITT_Others_OP_A,MATCH("4.2",ITT_Others_OP_A,0))="","",INDEX(ITT_Others_OP_A,MATCH("4.2",ITT_Others_OP_A,0))),"") -> 4.2 | D100: =IFERROR(IF(INDEX(ITT_Others_OP_B,MATCH("4.2",ITT_Others_OP_A,0))="","",INDEX(ITT_Others_OP_B,MATCH("4.2",ITT_Others_OP_A,0))),"") | E100: =IFERROR(IF(INDEX(ITT_Others_OP_E,MATCH("4.2",ITT_Others_OP_A,0))="","",INDEX(ITT_Others_OP_E,MATCH("4.2",ITT_Others_OP_A,0))),"") | F100: =IFERROR(IF(INDEX(ITT_Others_OP_G,MATCH("4.2",ITT_Others_OP_A,0))="","",INDEX(ITT_Others_OP_G,MATCH("4.2",ITT_Others_OP_A,0))),"") | G100: =IFERROR(IF(INDEX(ITT_Others_OP_J,MATCH("4.2",ITT_Others_OP_A,0))="","",INDEX(ITT_Others_OP_J,MATCH("4.2",ITT_Others_OP_A,0))),"") | H100: =IFERROR(IF(INDEX(ITT_Others_OP_K,MATCH("4.2",ITT_Others_OP_A,0))="","",INDEX(ITT_Others_OP_K,MATCH("4.2",ITT_Others_OP_A,0))),"") | M100: =IF(OR(L100="",$G100="",$H100=""),"",IF($H100-$G100=0,"",(L100-$G100)/($H100-$G100))) | S100: =IF(OR(R100="",$G100="",$H100=""),"",IF($H100-$G100=0,"",(R100-$G100)/($H100-$G100))) | Y100: =IF(OR(X100="",$G100="",$H100=""),"",IF($H100-$G100=0,"",(X100-$G100)/($H100-$G100))) | AE100: =IF(OR(AD100="",$G100="",$H100=""),"",IF($H100-$G100=0,"",(AD100-$G100)/($H100-$G100))) | AK100: =IF(OR(AJ100="",$G100="",$H100=""),"",IF($H100-$G100=0,"",(AJ100-$G100)/($H100-$G100)))
C101: =IFERROR(IF(INDEX(ITT_Others_OP_A,MATCH("4.3",ITT_Others_OP_A,0))="","",INDEX(ITT_Others_OP_A,MATCH("4.3",ITT_Others_OP_A,0))),"") -> 4.3 | D101: =IFERROR(IF(INDEX(ITT_Others_OP_B,MATCH("4.3",ITT_Others_OP_A,0))="","",INDEX(ITT_Others_OP_B,MATCH("4.3",ITT_Others_OP_A,0))),"") | E101: =IFERROR(IF(INDEX(ITT_Others_OP_E,MATCH("4.3",ITT_Others_OP_A,0))="","",INDEX(ITT_Others_OP_E,MATCH("4.3",ITT_Others_OP_A,0))),"") | F101: =IFERROR(IF(INDEX(ITT_Others_OP_G,MATCH("4.3",ITT_Others_OP_A,0))="","",INDEX(ITT_Others_OP_G,MATCH("4.3",ITT_Others_OP_A,0))),"") | G101: =IFERROR(IF(INDEX(ITT_Others_OP_J,MATCH("4.3",ITT_Others_OP_A,0))="","",INDEX(ITT_Others_OP_J,MATCH("4.3",ITT_Others_OP_A,0))),"") | H101: =IFERROR(IF(INDEX(ITT_Others_OP_K,MATCH("4.3",ITT_Others_OP_A,0))="","",INDEX(ITT_Others_OP_K,MATCH("4.3",ITT_Others_OP_A,0))),"") | M101: =IF(OR(L101="",$G101="",$H101=""),"",IF($H101-$G101=0,"",(L101-$G101)/($H101-$G101))) | S101: =IF(OR(R101="",$G101="",$H101=""),"",IF($H101-$G101=0,"",(R101-$G101)/($H101-$G101))) | Y101: =IF(OR(X101="",$G101="",$H101=""),"",IF($H101-$G101=0,"",(X101-$G101)/($H101-$G101))) | AE101: =IF(OR(AD101="",$G101="",$H101=""),"",IF($H101-$G101=0,"",(AD101-$G101)/($H101-$G101))) | AK101: =IF(OR(AJ101="",$G101="",$H101=""),"",IF($H101-$G101=0,"",(AJ101-$G101)/($H101-$G101)))
...

Sheet indicators
A1: Child Protection_Outcome | B1: Child Protection_Output | C1: Education_Outcome | D1: Education_Output | E1: Health and Well-being_Outcome | F1: Health and Well-being_Output | G1: Economic Empowerment_Outcome | H1: Economic Empowerment_Output | I1: Climate Change_Outcome | J1: Climate Change_Output | K1: Humanitarian Assistance_Outcome | L1: Humanitarian Assistance_Output | M1: Education - Community Engagement_Outcome | N1: Education - Community Engagement_Output | O1: All sector - Outcome | P1: All Sector - Output | Q1: Community Engagement
A2: % of children who received child protection services | B2: 1.1. # of children who received child protection services | C2: % of NEETs (Not in Education, Employment, or Training) (Gender marker) | D2: 2.1. # of children participating in GN education related programs (2.1.1.a + 2.1.2 + 2.1.3 - Duplicates) | E2: Under-five mortality rate (per 1000 live births) (SDG 3.2.1) (Gender marker) | F2: 3.1. # of children and adults who received basic health services (3.1.3 + 3.1.4 + 3.1.6 - Duplicates) | G2: % increase in household income of social economic organization members | H2: 4.1. # of income generation groups | I2: % of people contributing to community-wide climate adaptation and mitigation activities | J2: 5.1. # of people contributing to community-wide climate adaptation and mitigation activities (5.1.1 + 5.1.2 + 5.1.3 - Duplicates) | K2: Presence of local/national strategies for disaster management and disaster risk reduction | L2: 6.1. # of people who participated in disaster risk reduction (DRR) or anticipatory action (AA) activities | N2: 7.1. # of committees and sub-committees formally established and actively operating | O2: Child Protection | P2: Child Protection | Q2: 7.1. # of committees and sub-committees formally established and actively operating
B3: 1.1.1. # of children with new birth registration | C3: % of people who have completed upper secondary schools or above | D3: 2.1.1. # of schools having partnership with GN | E3: (Well-being) Improvement in subjective well-being | F3: 3.1.1. # of health facilities with essential infrastructure (basic amenities, infection prevention, trained staff, etc.)built, renovated and/or maintained | G3: % of participants who became employed or self-employed after joining social economic organizations (Member survey) (Gender marker) | H3: 4.2. # of members in income generation groups | I3: Total surface (hectare) under GN environment programmes | J3: 5.1.1. # of people (farmers, fishers, traders or community members) using low-carbon/eco-friendly/energy-efficient devices provided by GN | L3: 6.2. # of people who benefited from emergency relief programmes, including natural disasters, conflicts and climate crisis (6.2.1 + 6.2.2 + 6.2.3 + 6.2.5 + 6.2.6 - Duplicates) | N3: 7.1.1. # of committees | O3: % of children who received child protection services | P3: 1.1. # of children who received child protection services | Q3: 7.1.1. # of committees
B4: 1.1.2. # of children at risk who were referred to specialised services by GN | C4: School completion rate (primary and lower secondary school, separately) (Gender marker) | D4: 2.1.1.a. # of students who enrolled in GN partnership schools | E4: % of communities with community health or WASH committees in operation | F4: 3.1.2. # of health facilities built, renovated and/or maintained | G4: % of social enterprises that turned into a surplus | H4: 4.3. # of beneficiaries from microfinance programs | J4: 5.1.2. # of households that established and regularly practice GN-supported renewable resource management activities | L4: 6.2.1. # of people who received food assistance | N4: 7.1.2. # of sub-committees | O4: Education | P4: 1.1.1. # of children with new birth registration | Q4: 7.1.2. # of sub-committees
B5: 1.2. # of people participating in child rights programs (1.2.2 + 1.2.3 + 1.2.4 - Duplicates) | C5: % of children transitioning from primary to lower secondary education (Gender marker) | D5: 2.1.1.b. # of students who graduated from GN partnership schools | F5: 3.1.3. # of people receiving health check-ups | G5: Annual revenue and sales growth rate (%) of cooperatives | H5: 4.4. # of trainings conducted to build the capacities of members of social economy organizations (4.4.1 + 4.4.2 - Duplicates) | J5: 5.1.3. # of farms, fisheries or forest-dependent households adopting GN-supported sustainable production practices | L5: 6.2.2. # of people who received non-food item (NFI) kits | N5: 7.2. # of active members of committees and sub-committees (Gender marker) | O5: % of NEETs (Not in Education, Employment, or Training) (Gender marker) | P5: 1.1.2. # of children at risk who were referred to specialised services by GN | Q5: 7.2. # of active members of committees and sub-committees (Gender marker)
B6: 1.2.1. # of children’s, teens’ or youth clubs supported by GN | C6: School attendance rate (SDG 4.1.2; secondary data) | D6: 2.1.2. # of children who received financial and/or material support to access education | F6: 3.1.4. # of people who received health-related items, such as deworming tablets and LLINs | G6: Annual revenue and sales growth rate (%) of enterprises | H6: 4.4.1. # of participants in biz cooperative training & capacity building | J6: 5.1.4. # of people who completed GN-supported climate awareness, environmental protection campaigns or education/training activities | L6: 6.2.3. # of people who received cash and/or voucher assistance | N6: 7.2.1. # of active members of committees and sub-committees (Gender marker) | O6: % of people who have completed upper secondary schools or above | P6: 1.2. # of people participating in child rights programs (1.2.2 + 1.2.3 + 1.2.4 - Duplicates) | Q6: 7.2.1. # of active members of committees and sub-committees (Gender marker)
B7: 1.2.2. # of members in children’s, teens’ or youth clubs supported by GN | C7: Primary school attendance rate | D7: 2.1.3. # of children who participated in GN extracurricular classes or non-formal education for out-of-school children | F7: 3.1.5. # of community health workers (CHWs) | G7: Microfinance repayment rate | H7: 4.4.2. # of participants completing financial literacy training | J7: 5.2. # of people (farmers, fishers, traders or community members) who received GN-supported training for in climate-adaptive and environmentally friendly livelihood practice | L7: 6.2.4. # of households provided with shelters | N7: 7.3. # of GN volunteers engaged in programme activities | O7: School completion rate (primary and lower secondary school, separately) (Gender marker) | P7: 1.2.1. # of children’s, teens’ or youth clubs supported by GN | Q7: 7.3. # of GN volunteers engaged in programme activities
B8: 1.2.3. # of children and adults who have participated in child rights campaign activities | C8: Lower secondary school attendance rate | D8: 2.1.4. # of teachers and educators who have received capacity building training | F8: 3.1.6. # of people participating in basic health education | H8: 4.5. # of social enterprises | J8: 5.3. # of advocacy activities that aim to improve government policy for climate mitigation/adaptation and environmental protection | L8: 6.2.5. # of people who received psychosocial support (PSS) activities | N8: 7.4. # of training sessions for committee or sub-committee members | O8: % of children transitioning from primary to lower secondary education (Gender marker) | P8: 1.2.2. # of members in children’s, teens’ or youth clubs supported by GN | Q8: 7.4. # of training sessions for committee or sub-committee members
B9: 1.2.4. # of adults trained on child rights, child protection and safeguarding | D9: 2.2. # of people with improved quality life skills (2.2.1 + 2.2.2 + 2.2.3 – Duplicates) | F9: 3.1.7. # of community health committees | H9: 7.1. # of committees and sub-committees formally established and actively operating | J9: 5.4. # of people who participated in GN environment and climate change advoacy | L9: 6.2.6. # of people who received gender-based violence (GBV) related support and/or case management | N9: 7.5. # of meetings held by committees and sub-committees | O9: School attendance rate (SDG 4.1.2; secondary data) | P9: 1.2.3. # of children and adults who have participated in child rights campaign activities | Q9: 7.5. # of meetings held by committees and sub-committees
B10: 1.3. # of community- and/or child-led initiatives that influence child-related decisions at the community, regional or national level | D10: 2.2.1. # of people who participated in literacy and numeracy education | F10: 3.1.8. # of members in community health committees | H10: 7.1.1. # of committees | J10: 5.5. # of formal partnership agreements established with local stakeholders to coordinate and jointly implement climate resilience and environmental sustainability activities | L10: 6.3. # of participants in refugees/internally displaced persons (IDP) support programs in protracted situations (6.3.1 + 6.3.2 + 6.3.3 + 6.3.4 - Duplicates) | N10: 7.6. # of activities decided by community committees and sub-committees in the following year's GN Plan of Action (POA) | O10: Primary school attendance rate | P10: 1.2.4. # of adults trained on child rights, child protection and safeguarding | Q10: 7.6. # of activities decided by community committees and sub-committees in the following year's GN Plan of Action (POA)
B11: 1.4. # of activities that aimed at strengthening child rights or child protection-related laws, policies or budgets at a regional or national or international level | D11: 2.2.2. # of people participating in vocational education and training programs | F11: 3.1.9. # of staff, care workers, trainers, health workers, or community health workers trained in basic health support training | H11: 7.1.2. # of sub-committees | L11: 6.3.1. # of people who participated in refugee/host community livelihoods programs | N11: 7.7. Financial value of community contribution (volunteer labour, in-kind, cash, land) to project implementation | O11: Lower secondary school attendance rate | P11: 1.3. # of community- and/or child-led initiatives that influence child-related decisions at the community, regional or national level | Q11: 7.7. Financial value of community contribution (volunteer labour, in-kind, cash, land) to project implementation
B12: 1.5. # of people who participated in GN Child Protection advoacy | D12: 2.2.3. # of people participating in ICT education programs (Gender marker) | F12: 3.1.10. # of participants who received mental health support programs | H12: 7.2. # of active members of committees and sub-committees (Gender marker) | L12: 6.3.2. # of people participated in peacebuilding or social cohesion activities | N12: 7.8. # of local or national policies or regulations or laws initiated or influenced by Good Neighbors | O12: Health & WASH | P12: 1.4. # of activities that aimed at strengthening child rights or child protection-related laws, policies or budgets at a regional or national or international level | Q12: 7.8. # of local or national policies or regulations or laws initiated or influenced by Good Neighbors
B13: 7.1. # of committees and sub-committees formally established and actively operating | D13: 2.3. # of people participating in GN's global citizenship education program | F13: 3.2. # of mothers and children under the age of 5 with improved access to maternal and child health (MCH) services (3.2.1 + 3.2.2 + 3.2.3 + 3.2.4 - Duplicates) | H13: 7.2.1. # of active members of committees and sub-committees (Gender marker) | L13: 6.3.3. # of people (households) who benefitted from rehabilitation projects | N13: 7.9. # of people who participated in GN gender equality and women's rights advoacy | O13: Under-five mortality rate (per 1000 live births) (SDG 3.2.1) (Gender marker) | P13: 1.5. # of people who participated in GN Child Protection advoacy | Q13: 7.9. # of people who participated in GN gender equality and women's rights advoacy
B14: 7.1.1. # of committees | D14: 2.4. # of people who participated in GN Education advoacy | F14: 3.2.1. # of mothers who received antenatal and postnatal services | H14: 7.3. # of GN volunteers engaged in programme activities | L14: 6.3.4. # of people who participated in GN emergency relief & disaster risk reduction advoacy | O14: (Well-being) Improvement in subjective well-being | P14: Education
B15: 7.1.2. # of sub-committees | D15: 7.1. # of committees and sub-committees formally established and actively operating | F15: 3.2.2. # of mothers who were attended by skilled health personnel during their live birth | H15: 7.4. # of training sessions for committee or sub-committee members | O15: % of communities with community health or WASH committees in operation | P15: 2.1. # of children participating in GN education related programs (2.1.1.a + 2.1.2 + 2.1.3 - Duplicates)
B16: 7.2. # of active members of committees and sub-committees (Gender marker) | D16: 7.1.1. # of committees | F16: 3.2.3. # of children under 5 who received mandatory vaccinations | H16: 7.5. # of meetings held by committees and sub-committees | O16: Income Generation | P16: 2.1.1. # of schools having partnership with GN
B17: 7.2.1. # of active members of committees and sub-committees (Gender marker) | D17: 7.1.2. # of sub-committees | F17: 3.2.4. # of people who received sexual and reproductive health education | H17: 7.6. # of activities decided by community committees and sub-committees in the following year's GN Plan of Action (POA) | O17: % increase in household income of social economic organization members | P17: 2.1.1.a. # of students who enrolled in GN partnership schools
B18: 7.3. # of GN volunteers engaged in programme activities | D18: 7.2. # of active members of committees and sub-committees (Gender marker) | F18: 3.3. # of children and adults who received nutritional (including vitamins and other supplements) and food support | H18: 7.7. Financial value of community contribution (volunteer labour, in-kind, cash, land) to project implementation | O18: % of participants who became employed or self-employed after joining social economic organizations (Member survey) (Gender marker) | P18: 2.1.1.b. # of students who graduated from GN partnership schools
B19: 7.4. # of training sessions for committee or sub-committee members | D19: 7.2.1. # of active members of committees and sub-committees (Gender marker) | F19: 3.4. # of people with access to improved water sources | H19: 7.8. # of local or national policies or regulations or laws initiated or influenced by Good Neighbors | O19: % of social enterprises that turned into a surplus | P19: 2.1.2. # of children who received financial and/or material support to access education
B20: 7.5. # of meetings held by committees and sub-committees | D20: 7.3. # of GN volunteers engaged in programme activities | F20: 3.4.1. # of WASH facilities newly constructed or renovated | H20: 7.9. # of people who participated in GN gender equality and women's rights advoacy | O20: Annual revenue and sales growth rate (%) of cooperatives | P20: 2.1.3. # of children who participated in GN extracurricular classes or non-formal education for out-of-school children
B21: 7.6. # of activities decided by community committees and sub-committees in the following year's GN Plan of Action (POA) | D21: 7.4. # of training sessions for committee or sub-committee members | F21: 3.4.2. # of community WASH committee | O21: Annual revenue and sales growth rate (%) of enterprises | P21: 2.1.4. # of teachers and educators who have received capacity building training
B22: 7.7. Financial value of community contribution (volunteer labour, in-kind, cash, land) to project implementation | D22: 7.5. # of meetings held by committees and sub-committees | F22: 3.4.3. # of members in community WASH committees | O22: Microfinance repayment rate | P22: 2.2. # of people with improved quality life skills (2.2.1 + 2.2.2 + 2.2.3 – Duplicates)
